Workbook

Sheet LEIA-ME
A1: TERRITÓRIOS SECTI — Amostras de dados e filtros CT&I (Bahia)
A2: Cada aba traz a amostra de um dataset citado no resumo executivo. A linha 1 de cada aba repete a descrição e o arquivo de origem; a linha 2 é o cabeçalho, com filtro.
A3: A coluna "Filtro CT&I" diz se as linhas da aba já foram selecionadas por CT&I (✅), se trazem uma coluna que classifica cada linha (🏷️), se não foram filtradas mas têm variável CT&I (🔶) ou se não há variável CT&I (⬜).
A4: A aba Filtros_CTI é a regra oficial de recorte CT&I do painel. Clique no nome de uma aba para abri-la.
A6: Aba | B6: Fonte | C6: O que retorna | D6: Recorte da amostra | E6: Filtro CT&I | F6: Variáveis CT&I | G6: Linhas | H6: Colunas | I6: Arquivo de origem
A7: Filtros_CTI | B7: Todas | C7: Lista única de filtros CT&I: fonte, campo, operador, valores, nível e justificativa | D7: — | E7: — | F7: — | G7: =COUNTA(Filtros_CTI!A:A)-2 -> 30 | H7: =COUNTA(Filtros_CTI!2:2) -> 8 | I7: categorias_cti/filtros_cti_consolidado.csv
A8: IBGE_Populacao | B8: IBGE | C8: População residente estimada por município (SIDRA 6579) | D8: 417 municípios × 2024–2026 | E8: ⬜ Sem variável | F8: — | G8: =COUNTA(IBGE_Populacao!A:A)-2 -> 1251 | H8: =COUNTA(IBGE_Populacao!2:2) -> 11 | I8: amostras/ibge_2.1_populacao_6579_BA.csv
A9: IBGE_PIB_VAB | B9: IBGE | C9: PIB e valor adicionado por setor, em mil R$ (SIDRA 5938), formato longo | D9: 417 municípios × 2022–2023 | E9: ⬜ Sem variável | F9: — | G9: =COUNTA(IBGE_PIB_VAB!A:A)-2 -> 5838 | H9: =COUNTA(IBGE_PIB_VAB!2:2) -> 11 | I9: amostras/ibge_2.2_pib_vab_5938_BA.csv
A10: IBGE_PIB_per_capita_2023 | B10: IBGE | C10: PIB e PIB per capita oficiais (base do PIB dos Municípios) | D10: 417 municípios, 2023 | E10: ⬜ Sem variável | F10: — | G10: =COUNTA(IBGE_PIB_per_capita_2023!A:A)-2 -> 417 | H10: =COUNTA(IBGE_PIB_per_capita_2023!2:2) -> 8 | I10: amostras/ibge_2.3_pib_per_capita_oficial_BA_2023.csv
A11: IBGE_Derivados | B11: IBGE | C11: PIB per capita, densidade demográfica e PIB por km² | D11: 15 municípios de referência, 2023 | E11: ⬜ Sem variável | F11: — | G11: =COUNTA(IBGE_Derivados!A:A)-2 -> 15 | H11: =COUNTA(IBGE_Derivados!2:2) -> 11 | I11: amostras/ibge_2.3_2.5_2.6_derivados_amostra_BA.csv
A12: IBGE_Area | B12: IBGE | C12: Área (km²) e centroide de cada município | D12: 417 municípios | E12: ⬜ Sem variável | F12: — | G12: =COUNTA(IBGE_Area!A:A)-2 -> 417 | H12: =COUNTA(IBGE_Area!2:2) -> 9 | I12: amostras/ibge_2.4_area_centroide_BA.csv
A13: IBGE_Malha | B13: IBGE | C13: Metadados do polígono de cada município (o GeoJSON completo fica fora da planilha) | D13: 30 municípios | E13: ⬜ Sem variável | F13: — | G13: =COUNTA(IBGE_Malha!A:A)-2 -> 30 | H13: =COUNTA(IBGE_Malha!2:2) -> 4 | I13: amostras/ibge_2.7_malha_amostra_BA.csv
A14: INEP_IES | B14: INEP | C14: Instituições de ensino superior: tipo, rede, sede, docentes por titulação | D14: 40 IES com mais doutores | E14: 🔶 Não filtrado | F14: ies_tecnologica_if_cefet (IF/CEFET); QT_DOC_EX_DOUT | G14: =COUNTA(INEP_IES!A:A)-2 -> 40 | H14: =COUNTA(INEP_IES!2:2) -> 21 | I14: amostras/inep_3.1_3.7_ies_BA_amostra.csv
A15: INEP_Cursos | B15: INEP | C15: Cursos de graduação: área CINE, grau, modalidade, vagas, matrículas, ingressantes e concluintes | D15: Estratificada: 15 STEM pres. + 5 ampliado + 5 fora + 10 STEM EAD | E15: 🏷️ Classificado | F15: nivel_cti ← CO_CINE_AREA_GERAL (05/06/07 núcleo; 08/09 ampliado) | G15: =COUNTA(INEP_Cursos!A:A)-2 -> 35 | H15: =COUNTA(INEP_Cursos!2:2) -> 27 | I15: amostras/inep_3.2_a_3.6_cursos_BA_amostra.csv
A16: INEP_Cursos_Municipio | B16: INEP | C16: Soma de cursos, vagas e matrículas presenciais por município e nível CT&I | D16: 13 municípios de referência, só presencial | E16: 🏷️ Classificado | F16: nivel_cti | G16: =COUNTA(INEP_Cursos_Municipio!A:A)-2 -> 36 | H16: =COUNTA(INEP_Cursos_Municipio!2:2) -> 8 | I16: amostras/inep_cursos_presenciais_por_municipio_nivel_cti_amostra.csv
A17: ANEEL_SIGA | B17: ANEEL | C17: Usinas de geração: tipo, fonte, fase, potência, coordenadas, município (texto) | D17: Todas as 1.163 usinas da BA | E17: 🔶 Não filtrado | F17: SigTipoGeracao ∈ {EOL, UFV} (auxiliar) | G17: =COUNTA(ANEEL_SIGA!A:A)-2 -> 1163 | H17: =COUNTA(ANEEL_SIGA!2:2) -> 23 | I17: amostras/aneel_4.1_4.2_siga_geracao_BA.csv
A18: ANEEL_INDGER | B18: ANEEL | C18: Unidades consumidoras ativas e indicadores comerciais por município e mês | D18: COELBA, 1.500 linhas (2023–2026) | E18: ⬜ Sem variável | F18: — | G18: =COUNTA(ANEEL_INDGER!A:A)-2 -> 1500 | H18: =COUNTA(ANEEL_INDGER!2:2) -> 63 | I18: amostras/aneel_4.3_indger_comercial_BA_amostra.csv
A19: ANEEL_SAMP | B19: ANEEL | C19: Mercado de energia por classe de consumo (kWh, kW, R$); sem município | D19: COELBA, 1.000 linhas (jan/2024) | E19: 🔶 Não filtrado | F19: DscDetalheMercado: energia injetada/compensada (auxiliar) | G19: =COUNTA(ANEEL_SAMP!A:A)-2 -> 1000 | H19: =COUNTA(ANEEL_SAMP!2:2) -> 18 | I19: amostras/aneel_4.3_samp_mercado_COELBA_amostra.csv
A20: ANEEL_PeD | B20: ANEEL | C20: Projetos de P&D regulado: situação, tema, fase de inovação, produto, custos | D20: 99 projetos COELBA, 2009–2026 | E20: ✅ Filtrado (dataset inteiro é CT&I) | F20: SigFasInovacaoProjeto; SigTemaProjeto; SigTipoProdutoProjeto | G20: =COUNTA(ANEEL_PeD!A:A)-2 -> 99 | H20: =COUNTA(ANEEL_PeD!2:2) -> 17 | I20: amostras/aneel_4.4_ped_projetos_COELBA.csv
A21: ANEEL_DECFEC_Conjunto | B21: ANEEL | C21: DEC e FEC anuais por conjunto elétrico, com limite regulatório | D21: 211 conjuntos COELBA, 2025 | E21: ⬜ Sem variável | F21: — | G21: =COUNTA(ANEEL_DECFEC_Conjunto!A:A)-2 -> 211 | H21: =COUNTA(ANEEL_DECFEC_Conjunto!2:2) -> 11 | I21: amostras/aneel_4.5_decfec_conjunto_BA_2025.csv
A22: ANEEL_DECFEC_Municipio | B22: ANEEL | C22: DEC e FEC por município (média dos conjuntos, ponderada por consumidores) | D22: 415 municípios, 2025 | E22: ⬜ Sem variável | F22: — | G22: =COUNTA(ANEEL_DECFEC_Municipio!A:A)-2 -> 415 | H22: =COUNTA(ANEEL_DECFEC_Municipio!2:2) -> 8 | I22: amostras/aneel_4.5_decfec_municipio_BA_2025.csv
A23: ANEEL_INDQUAL | B23: ANEEL | C23: De-para conjunto elétrico ↔ município | D23: 211 conjuntos ativos em 2025 | E23: ⬜ Sem variável | F23: — | G23: =COUNTA(ANEEL_INDQUAL!A:A)-2 -> 1262 | H23: =COUNTA(ANEEL_INDQUAL!2:2) -> 5 | I23: amostras/aneel_4.5_indqual_conjunto_municipio_BA.csv
A24: BNDES_Nao_Automaticas | B24: BNDES | C24: Operações diretas e indiretas não automáticas, com colunas de classificação CT&I | D24: 15 CT&I + 5 auxiliar + 10 fora | E24: 🏷️ Classificado | F24: inovacao; instrumento_financeiro; fonte_de_recurso_desembolsos → cti_nivel | G24: =COUNTA(BNDES_Nao_Automaticas!A:A)-2 -> 30 | H24: =COUNTA(BNDES_Nao_Automaticas!2:2) -> 44 | I24: amostras/bndes_5.x_nao_automaticas_BA_amostra.csv
A25: BNDES_Indiretas_Automaticas | B25: BNDES | C25: Operações indiretas automáticas (FINAME, BNDES Automático), com colunas CT&I | D25: 15 CT&I + 5 auxiliar + 10 fora | E25: 🏷️ Classificado | F25: inovacao; instrumento_financeiro; fonte_de_recurso_desembolsos → cti_nivel | G25: =COUNTA(BNDES_Indiretas_Automaticas!A:A)-2 -> 30 | H25: =COUNTA(BNDES_Indiretas_Automaticas!2:2) -> 40 | I25: amostras/bndes_5.x_indiretas_automaticas_BA_amostra.csv
A26: BNDES_CTI_Municipio_Ano | B26: BNDES | C26: Operações CT&I somadas por município e ano | D26: Completo: 76 municípios × anos, 2002–2026 | E26: ✅ Filtrado | F26: cti_nivel = CT&I (regra explícita) | G26: =COUNTA(BNDES_CTI_Municipio_Ano!A:A)-2 -> 131 | H26: =COUNTA(BNDES_CTI_Municipio_Ano!2:2) -> 6 | I26: amostras/bndes_5.5_cti_por_municipio_ano_BA.csv
A27: SICONFI_Receita | B27: SICONFI | C27: Receitas por conta (DCA Anexo I-C) | D27: Salvador 2024, 40 linhas | E27: ⬜ Sem variável | F27: — | G27: =COUNTA(SICONFI_Receita!A:A)-2 -> 40 | H27: =COUNTA(SICONFI_Receita!2:2) -> 11 | I27: amostras/siconfi_6.2_dca_anexoIC_receita_salvador_2024_amostra.csv
A28: SICONFI_RREO_CTI | B28: SICONFI | C28: Despesa por função/subfunção (RREO Anexo 02) | D28: Salvador 2025, 6º bimestre | E28: ✅ Filtrado (texto da conta) | F28: conta contém Ciência, Tecnol ou TOTAL | G28: =COUNTA(SICONFI_RREO_CTI!A:A)-2 -> 52 | H28: =COUNTA(SICONFI_RREO_CTI!2:2) -> 15 | I28: amostras/siconfi_6.3_rreo_anexo02_salvador_2025_cti.csv
A29: SICONFI_DCA_CTI | B29: SICONFI | C29: Despesa liquidada por município: total, Função 19, subfunções 571–573 e 126 | D29: 415 municípios, 2024 | E29: 🏷️ Classificado em colunas | F29: Função 19; subfunções 571/572/573; 126 (auxiliar) | G29: =COUNTA(SICONFI_DCA_CTI!A:A)-2 -> 415 | H29: =COUNTA(SICONFI_DCA_CTI!2:2) -> 9 | I29: amostras/siconfi_6.3_6.4_dca_IE_BA_2024_ciencia_tecnologia_por_municipio.csv
A30: ANATEL_Densidade | B30: ANATEL | C30: Acessos de banda larga fixa por 100 domicílios, por município e mês | D30: 5 municípios × 2021, 2022, 2025, 2026 | E30: ⬜ Sem variável | F30: — | G30: =COUNTA(ANATEL_Densidade!A:A)-2 -> 162 | H30: =COUNTA(ANATEL_Densidade!2:2) -> 9 | I30: amostras/anatel_7.1_densidade_scm_BA_amostra.csv
A31: ANATEL_Acessos | B31: ANATEL | C31: Acessos por prestadora, tecnologia, meio de acesso e velocidade (jan–ago/2026) | D31: 40 maiores linhas, municípios de referência | E31: 🔶 Não filtrado | F31: Meio de Acesso = Fibra; Faixa > 34Mbps (auxiliar) | G31: =COUNTA(ANATEL_Acessos!A:A)-2 -> 40 | H31: =COUNTA(ANATEL_Acessos!2:2) -> 21 | I31: amostras/anatel_acessos_bl_fixa_2026_BA_amostra.csv
A33: Fontes e datas: coleta de 01 a 07/10/2026; detalhes, regras e ressalvas em RESULTADOS_AMOSTRAGEM.md. Linhas e Colunas são fórmulas que contam o conteúdo de cada aba.

Sheet IBGE_Populacao
A1: ← LEIA-ME | B1: População residente estimada por município (SIDRA 6579) | C1: Origem: amostras/ibge_2.1_populacao_6579_BA.csv
A2: codigo_ibge | B2: variavel_id | C2: variavel | D2: unidade | E2: ano_referencia | F2: populacao | G2: municipio | H2: uf | I2: fonte | J2: url_fonte | K2: data_coleta
A3: 2900108 | B3: 9324 | C3: População residente estimada | D3: Pessoas | E3: 2024 | F3: 7452 | G3: Abaíra | H3: BA | I3: IBGE/SIDRA agregado 6579 | J3: https://servicodados.ibge.gov.br/api/v3/agregados/6579/periodos/-3/variaveis/9324?localidades=N6[N3[29]] | K3: 2026-10-05
A4: 2900108 | B4: 9324 | C4: População residente estimada | D4: Pessoas | E4: 2025 | F4: 7407 | G4: Abaíra | H4: BA | I4: IBGE/SIDRA agregado 6579 | J4: https://servicodados.ibge.gov.br/api/v3/agregados/6579/periodos/-3/variaveis/9324?localidades=N6[N3[29]] | K4: 2026-10-05
A5: 2900108 | B5: 9324 | C5: População residente estimada | D5: Pessoas | E5: 2026 | F5: 7366 | G5: Abaíra | H5: BA | I5: IBGE/SIDRA agregado 6579 | J5: https://servicodados.ibge.gov.br/api/v3/agregados/6579/periodos/-3/variaveis/9324?localidades=N6[N3[29]] | K5: 2026-10-05
A6: 2900207 | B6: 9324 | C6: População residente estimada | D6: Pessoas | E6: 2024 | F6: 18240 | G6: Abaré | H6: BA | I6: IBGE/SIDRA agregado 6579 | J6: https://servicodados.ibge.gov.br/api/v3/agregados/6579/periodos/-3/variaveis/9324?localidades=N6[N3[29]] | K6: 2026-10-05
A7: 2900207 | B7: 9324 | C7: População residente estimada | D7: Pessoas | E7: 2025 | F7: 18269 | G7: Abaré | H7: BA | I7: IBGE/SIDRA agregado 6579 | J7: https://servicodados.ibge.gov.br/api/v3/agregados/6579/periodos/-3/variaveis/9324?localidades=N6[N3[29]] | K7: 2026-10-05
A8: 2900207 | B8: 9324 | C8: População residente estimada | D8: Pessoas | E8: 2026 | F8: 18303 | G8: Abaré | H8: BA | I8: IBGE/SIDRA agregado 6579 | J8: https://servicodados.ibge.gov.br/api/v3/agregados/6579/periodos/-3/variaveis/9324?localidades=N6[N3[29]] | K8: 2026-10-05
A9: 2900306 | B9: 9324 | C9: População residente estimada | D9: Pessoas | E9: 2024 | F9: 14215 | G9: Acajutiba | H9: BA | I9: IBGE/SIDRA agregado 6579 | J9: https://servicodados.ibge.gov.br/api/v3/agregados/6579/periodos/-3/variaveis/9324?localidades=N6[N3[29]] | K9: 2026-10-05
A10: 2900306 | B10: 9324 | C10: População residente estimada | D10: Pessoas | E10: 2025 | F10: 14200 | G10: Acajutiba | H10: BA | I10: IBGE/SIDRA agregado 6579 | J10: https://servicodados.ibge.gov.br/api/v3/agregados/6579/periodos/-3/variaveis/9324?localidades=N6[N3[29]] | K10: 2026-10-05
A11: 2900306 | B11: 9324 | C11: População residente estimada | D11: Pessoas | E11: 2026 | F11: 14187 | G11: Acajutiba | H11: BA | I11: IBGE/SIDRA agregado 6579 | J11: https://servicodados.ibge.gov.br/api/v3/agregados/6579/periodos/-3/variaveis/9324?localidades=N6[N3[29]] | K11: 2026-10-05
A12: 2900355 | B12: 9324 | C12: População residente estimada | D12: Pessoas | E12: 2024 | F12: 14554 | G12: Adustina | H12: BA | I12: IBGE/SIDRA agregado 6579 | J12: https://servicodados.ibge.gov.br/api/v3/agregados/6579/periodos/-3/variaveis/9324?localidades=N6[N3[29]] | K12: 2026-10-05
A13: 2900355 | B13: 9324 | C13: População residente estimada | D13: Pessoas | E13: 2025 | F13: 14510 | G13: Adustina | H13: BA | I13: IBGE/SIDRA agregado 6579 | J13: https://servicodados.ibge.gov.br/api/v3/agregados/6579/periodos/-3/variaveis/9324?localidades=N6[N3[29]] | K13: 2026-10-05
A14: 2900355 | B14: 9324 | C14: População residente estimada | D14: Pessoas | E14: 2026 | F14: 14470 | G14: Adustina | H14: BA | I14: IBGE/SIDRA agregado 6579 | J14: https://servicodados.ibge.gov.br/api/v3/agregados/6579/periodos/-3/variaveis/9324?localidades=N6[N3[29]] | K14: 2026-10-05
... A1253: 2933604 | B1253: 9324 | C1253: População residente estimada | D1253: Pessoas | E1253: 2026 | F1253: 47056 | G1253: Xique-Xique | H1253: BA | I1253: IBGE/SIDRA agregado 6579 | J1253: https://servicodados.ibge.gov.br/api/v3/agregados/6579/periodos/-3/variaveis/9324?localidades=N6[N3[29]] | K1253: 2026-10-05

Sheet IBGE_PIB_VAB
A1: ← LEIA-ME | B1: PIB e valor adicionado por setor, em mil R$ (SIDRA 5938), formato longo | C1: Origem: amostras/ibge_2.2_pib_vab_5938_BA.csv
A2: codigo_ibge | B2: variavel_id | C2: variavel | D2: unidade | E2: ano_referencia | F2: valor | G2: municipio | H2: uf | I2: fonte | J2: url_fonte | K2: data_coleta
A3: 2900108 | B3: 37 | C3: Produto Interno Bruto a preços correntes | D3: Mil Reais | E3: 2022 | F3: 79220 | G3: Abaíra | H3: BA | I3: IBGE/SIDRA agregado 5938 | J3: https://servicodados.ibge.gov.br/api/v3/agregados/5938/periodos/-2/variaveis/37|498|513|517|6575|525|543?localidades=N6[N3[29]] | K3: 2026-10-05
A4: 2900108 | B4: 37 | C4: Produto Interno Bruto a preços correntes | D4: Mil Reais | E4: 2023 | F4: 84854 | G4: Abaíra | H4: BA | I4: IBGE/SIDRA agregado 5938 | J4: https://servicodados.ibge.gov.br/api/v3/agregados/5938/periodos/-2/variaveis/37|498|513|517|6575|525|543?localidades=N6[N3[29]] | K4: 2026-10-05
A5: 2900207 | B5: 37 | C5: Produto Interno Bruto a preços correntes | D5: Mil Reais | E5: 2022 | F5: 206162 | G5: Abaré | H5: BA | I5: IBGE/SIDRA agregado 5938 | J5: https://servicodados.ibge.gov.br/api/v3/agregados/5938/periodos/-2/variaveis/37|498|513|517|6575|525|543?localidades=N6[N3[29]] | K5: 2026-10-05
A6: 2900207 | B6: 37 | C6: Produto Interno Bruto a preços correntes | D6: Mil Reais | E6: 2023 | F6: 224239 | G6: Abaré | H6: BA | I6: IBGE/SIDRA agregado 5938 | J6: https://servicodados.ibge.gov.br/api/v3/agregados/5938/periodos/-2/variaveis/37|498|513|517|6575|525|543?localidades=N6[N3[29]] | K6: 2026-10-05
A7: 2900306 | B7: 37 | C7: Produto Interno Bruto a preços correntes | D7: Mil Reais | E7: 2022 | F7: 157504 | G7: Acajutiba | H7: BA | I7: IBGE/SIDRA agregado 5938 | J7: https://servicodados.ibge.gov.br/api/v3/agregados/5938/periodos/-2/variaveis/37|498|513|517|6575|525|543?localidades=N6[N3[29]] | K7: 2026-10-05
A8: 2900306 | B8: 37 | C8: Produto Interno Bruto a preços correntes | D8: Mil Reais | E8: 2023 | F8: 186446 | G8: Acajutiba | H8: BA | I8: IBGE/SIDRA agregado 5938 | J8: https://servicodados.ibge.gov.br/api/v3/agregados/5938/periodos/-2/variaveis/37|498|513|517|6575|525|543?localidades=N6[N3[29]] | K8: 2026-10-05
A9: 2900355 | B9: 37 | C9: Produto Interno Bruto a preços correntes | D9: Mil Reais | E9: 2022 | F9: 368395 | G9: Adustina | H9: BA | I9: IBGE/SIDRA agregado 5938 | J9: https://servicodados.ibge.gov.br/api/v3/agregados/5938/periodos/-2/variaveis/37|498|513|517|6575|525|543?localidades=N6[N3[29]] | K9: 2026-10-05
A10: 2900355 | B10: 37 | C10: Produto Interno Bruto a preços correntes | D10: Mil Reais | E10: 2023 | F10: 275494 | G10: Adustina | H10: BA | I10: IBGE/SIDRA agregado 5938 | J10: https://servicodados.ibge.gov.br/api/v3/agregados/5938/periodos/-2/variaveis/37|498|513|517|6575|525|543?localidades=N6[N3[29]] | K10: 2026-10-05
A11: 2900405 | B11: 37 | C11: Produto Interno Bruto a preços correntes | D11: Mil Reais | E11: 2022 | F11: 159896 | G11: Água Fria | H11: BA | I11: IBGE/SIDRA agregado 5938 | J11: https://servicodados.ibge.gov.br/api/v3/agregados/5938/periodos/-2/variaveis/37|498|513|517|6575|525|543?localidades=N6[N3[29]] | K11: 2026-10-05
A12: 2900405 | B12: 37 | C12: Produto Interno Bruto a preços correntes | D12: Mil Reais | E12: 2023 | F12: 174798 | G12: Água Fria | H12: BA | I12: IBGE/SIDRA agregado 5938 | J12: https://servicodados.ibge.gov.br/api/v3/agregados/5938/periodos/-2/variaveis/37|498|513|517|6575|525|543?localidades=N6[N3[29]] | K12: 2026-10-05
A13: 2900504 | B13: 37 | C13: Produto Interno Bruto a preços correntes | D13: Mil Reais | E13: 2022 | F13: 89980 | G13: Érico Cardoso | H13: BA | I13: IBGE/SIDRA agregado 5938 | J13: https://servicodados.ibge.gov.br/api/v3/agregados/5938/periodos/-2/variaveis/37|498|513|517|6575|525|543?localidades=N6[N3[29]] | K13: 2026-10-05
A14: 2900504 | B14: 37 | C14: Produto Interno Bruto a preços correntes | D14: Mil Reais | E14: 2023 | F14: 102934 | G14: Érico Cardoso | H14: BA | I14: IBGE/SIDRA agregado 5938 | J14: https://servicodados.ibge.gov.br/api/v3/agregados/5938/periodos/-2/variaveis/37|498|513|517|6575|525|543?localidades=N6[N3[29]] | K14: 2026-10-05
... A836: 2933604 | B836: 37 | C836: Produto Interno Bruto a preços correntes | D836: Mil Reais | E836: 2023 | F836: 780080 | G836: Xique-Xique | H836: BA | I836: IBGE/SIDRA agregado 5938 | J836: https://servicodados.ibge.gov.br/api/v3/agregados/5938/periodos/-2/variaveis/37|498|513|517|6575|525|543?localidades=N6[N3[29]] | K836: 2026-10-05
A837: 2900108 | B837: 498 | C837: Valor adicionado bruto a preços correntes total | E837: 2022 | G837: Abaíra | H837: BA | I837: IBGE/SIDRA agregado 5938 | J837: https://servicodados.ibge.gov.br/api/v3/agregados/5938/periodos/-2/variaveis/37|498|513|517|6575|525|543?localidades=N6[N3[29]] | K837: 2026-10-05
A838: 2900108 | B838: 498 | C838: Valor adicionado bruto a preços correntes total | E838: 2023 | G838: Abaíra | H838: BA | I838: IBGE/SIDRA agregado 5938 | J838: https://servicodados.ibge.gov.br/api/v3/agregados/5938/periodos/-2/variaveis/37|498|513|517|6575|525|543?localidades=N6[N3[29]] | K838: 2026-10-05
A839: 2900207 | B839: 498 | C839: Valor adicionado bruto a preços correntes total | E839: 2022 | G839: Abaré | H839: BA | I839: IBGE/SIDRA agregado 5938 | J839: https://servicodados.ibge.gov.br/api/v3/agregados/5938/periodos/-2/variaveis/37|498|513|517|6575|525|543?localidades=N6[N3[29]] | K839: 2026-10-05
A840: 2900207 | B840: 498 | C840: Valor adicionado bruto a preços correntes total | E840: 2023 | G840: Abaré | H840: BA | I840: IBGE/SIDRA agregado 5938 | J840: https://servicodados.ibge.gov.br/api/v3/agregados/5938/periodos/-2/variaveis/37|498|513|517|6575|525|543?localidades=N6[N3[29]] | K840: 2026-10-05
A841: 2900306 | B841: 498 | C841: Valor adicionado bruto a preços correntes total | E841: 2022 | G841: Acajutiba | H841: BA | I841: IBGE/SIDRA agregado 5938 | J841: https://servicodados.ibge.gov.br/api/v3/agregados/5938/periodos/-2/variaveis/37|498|513|517|6575|525|543?localidades=N6[N3[29]] | K841: 2026-10-05
A842: 2900306 | B842: 498 | C842: Valor adicionado bruto a preços correntes total | E842: 2023 | G842: Acajutiba | H842: BA | I842: IBGE/SIDRA agregado 5938 | J842: https://servicodados.ibge.gov.br/api/v3/agregados/5938/periodos/-2/variaveis/37|498|513|517|6575|525|543?localidades=N6[N3[29]] | K842: 2026-10-05
A843: 2900355 | B843: 498 | C843: Valor adicionado bruto a preços correntes total | E843: 2022 | G843: Adustina | H843: BA | I843: IBGE/SIDRA agregado 5938 | J843: https://servicodados.ibge.gov.br/api/v3/agregados/5938/periodos/-2/variaveis/37|498|513|517|6575|525|543?localidades=N6[N3[29]] | K843: 2026-10-05
A844: 2900355 | B844: 498 | C844: Valor adicionado bruto a preços correntes total | E844: 2023 | G844: Adustina | H844: BA | I844: IBGE/SIDRA agregado 5938 | J844: https://servicodados.ibge.gov.br/api/v3/agregados/5938/periodos/-2/variaveis/37|498|513|517|6575|525|543?localidades=N6[N3[29]] | K844: 2026-10-05
A845: 2900405 | B845: 498 | C845: Valor adicionado bruto a preços correntes total | E845: 2022 | G845: Água Fria | H845: BA | I845: IBGE/SIDRA agregado 5938 | J845: https://servicodados.ibge.gov.br/api/v3/agregados/5938/periodos/-2/variaveis/37|498|513|517|6575|525|543?localidades=N6[N3[29]] | K845: 2026-10-05
A846: 2900405 | B846: 498 | C846: Valor adicionado bruto a preços correntes total | E846: 2023 | G846: Água Fria | H846: BA | I846: IBGE/SIDRA agregado 5938 | J846: https://servicodados.ibge.gov.br/api/v3/agregados/5938/periodos/-2/variaveis/37|498|513|517|6575|525|543?localidades=N6[N3[29]] | K846: 2026-10-05
A847: 2900504 | B847: 498 | C847: Valor adicionado bruto a preços correntes total | E847: 2022 | G847: Érico Cardoso | H847: BA | I847: IBGE/SIDRA agregado 5938 | J847: https://servicodados.ibge.gov.br/api/v3/agregados/5938/periodos/-2/variaveis/37|498|513|517|6575|525|543?localidades=N6[N3[29]] | K847: 2026-10-05
A848: 2900504 | B848: 498 | C848: Valor adicionado bruto a preços correntes total | E848: 2023 | G848: Érico Cardoso | H848: BA | I848: IBGE/SIDRA agregado 5938 | J848: https://servicodados.ibge.gov.br/api/v3/agregados/5938/periodos/-2/variaveis/37|498|513|517|6575|525|543?localidades=N6[N3[29]] | K848: 2026-10-05
... A5840: 2933604 | B5840: 543 | C5840: Impostos, líquidos de subsídios, sobre produtos a preços correntes | E5840: 2023 | G5840: Xique-Xique | H5840: BA | I5840: IBGE/SIDRA agregado 5938 | J5840: https://servicodados.ibge.gov.br/api/v3/agregados/5938/periodos/-2/variaveis/37|498|513|517|6575|525|543?localidades=N6[N3[29]] | K5840: 2026-10-05

Sheet IBGE_PIB_per_capita_2023
A1: ← LEIA-ME | B1: PIB e PIB per capita oficiais (base do PIB dos Municípios) | C1: Origem: amostras/ibge_2.3_pib_per_capita_oficial_BA_2023.csv
A2: codigo_ibge | B2: municipio | C2: ano_referencia | D2: pib_mil_reais | E2: pib_per_capita_reais | F2: populacao_implicita | G2: fonte | H2: url_fonte
A3: 2900207 | B3: Abaré | C3: 2023 | D3: 224238.54 | E3: 12712.66 | F3: 17639 | G3: IBGE PIB dos Municípios (base TXT oficial) | H3: https://ftp.ibge.gov.br/Pib_Municipios/2022_2023/base/base_de_dados_2010_2023_txt.zip
A4: 2900108 | B4: Abaíra | C4: 2023 | D4: 84853.976 | E4: 11622.24 | F4: 7301 | G4: IBGE PIB dos Municípios (base TXT oficial) | H4: https://ftp.ibge.gov.br/Pib_Municipios/2022_2023/base/base_de_dados_2010_2023_txt.zip
A5: 2900306 | B5: Acajutiba | C5: 2023 | D5: 186446.17 | E5: 13515.49 | F5: 13795 | G5: IBGE PIB dos Municípios (base TXT oficial) | H5: https://ftp.ibge.gov.br/Pib_Municipios/2022_2023/base/base_de_dados_2010_2023_txt.zip
A6: 2900355 | B6: Adustina | C6: 2023 | D6: 275493.88 | E6: 19399.61 | F6: 14201 | G6: IBGE PIB dos Municípios (base TXT oficial) | H6: https://ftp.ibge.gov.br/Pib_Municipios/2022_2023/base/base_de_dados_2010_2023_txt.zip
A7: 2900603 | B7: Aiquara | C7: 2023 | D7: 75418.036 | E7: 16959.31 | F7: 4447 | G7: IBGE PIB dos Municípios (base TXT oficial) | H7: https://ftp.ibge.gov.br/Pib_Municipios/2022_2023/base/base_de_dados_2010_2023_txt.zip
A8: 2900702 | B8: Alagoinhas | C8: 2023 | D8: 5705227.5 | E8: 37769.21 | F8: 151055 | G8: IBGE PIB dos Municípios (base TXT oficial) | H8: https://ftp.ibge.gov.br/Pib_Municipios/2022_2023/base/base_de_dados_2010_2023_txt.zip
A9: 2900801 | B9: Alcobaça | C9: 2023 | D9: 439081.54 | E9: 17899.78 | F9: 24530 | G9: IBGE PIB dos Municípios (base TXT oficial) | H9: https://ftp.ibge.gov.br/Pib_Municipios/2022_2023/base/base_de_dados_2010_2023_txt.zip
A10: 2900900 | B10: Almadina | C10: 2023 | D10: 79710.606 | E10: 15276.08 | F10: 5218 | G10: IBGE PIB dos Municípios (base TXT oficial) | H10: https://ftp.ibge.gov.br/Pib_Municipios/2022_2023/base/base_de_dados_2010_2023_txt.zip
A11: 2901007 | B11: Amargosa | C11: 2023 | D11: 608765.2 | E11: 16668.91 | F11: 36521 | G11: IBGE PIB dos Municípios (base TXT oficial) | H11: https://ftp.ibge.gov.br/Pib_Municipios/2022_2023/base/base_de_dados_2010_2023_txt.zip
A12: 2901106 | B12: Amélia Rodrigues | C12: 2023 | D12: 521349.04 | E12: 21598.68 | F12: 24138 | G12: IBGE PIB dos Municípios (base TXT oficial) | H12: https://ftp.ibge.gov.br/Pib_Municipios/2022_2023/base/base_de_dados_2010_2023_txt.zip
A13: 2901155 | B13: América Dourada | C13: 2023 | D13: 198616.02 | E13: 13121.23 | F13: 15137 | G13: IBGE PIB dos Municípios (base TXT oficial) | H13: https://ftp.ibge.gov.br/Pib_Municipios/2022_2023/base/base_de_dados_2010_2023_txt.zip
A14: 2901205 | B14: Anagé | C14: 2023 | D14: 299894.81 | E14: 11789.24 | F14: 25438 | G14: IBGE PIB dos Municípios (base TXT oficial) | H14: https://ftp.ibge.gov.br/Pib_Municipios/2022_2023/base/base_de_dados_2010_2023_txt.zip
... A419: 2900504 | B419: Érico Cardoso | C419: 2023 | D419: 102934.02 | E419: 9707.09 | F419: 10604 | G419: IBGE PIB dos Municípios (base TXT oficial) | H419: https://ftp.ibge.gov.br/Pib_Municipios/2022_2023/base/base_de_dados_2010_2023_txt.zip

Sheet IBGE_Derivados
A1: ← LEIA-ME | B1: PIB per capita, densidade demográfica e PIB por km² | C1: Origem: amostras/ibge_2.3_2.5_2.6_derivados_amostra_BA.csv
A2: codigo_ibge | B2: municipio | C2: ano_referencia | D2: pib_mil_reais | E2: pib_per_capita_reais | F2: fonte_pib_per_capita | G2: area_km2 | H2: pib_por_km2_mil_reais | I2: populacao_ultimo_ano | J2: ano_populacao | K2: densidade_demografica_hab_km2
A3: 2901106 | B3: Amélia Rodrigues | C3: 2023 | D3: 521349.04 | E3: 21598.68 | F3: IBGE PIB dos Municípios (oficial) | G3: 166.872 | H3: 3124.25 | I3: 24814 | J3: 2026 | K3: 148.7
A4: 2903201 | B4: Barreiras | C4: 2023 | D4: 9499499 | E4: 59470.74 | F4: IBGE PIB dos Municípios (oficial) | G4: 8051.274 | H4: 1179.88 | I4: 172521 | J4: 2026 | K4: 21.43
A5: 2905701 | B5: Camaçari | C5: 2023 | D5: 27418878 | E5: 91283.07 | F5: IBGE PIB dos Municípios (oficial) | G5: 785.421 | H5: 34909.78 | I5: 323676 | J5: 2026 | K5: 412.11
A6: 2906006 | B6: Campo Formoso | C6: 2023 | D6: 1617786 | E6: 22665.37 | F6: IBGE PIB dos Municípios (oficial) | G6: 7161.827 | H6: 225.89 | I6: 75311 | J6: 2026 | K6: 10.52
A7: 2907202 | B7: Casa Nova | C7: 2023 | D7: 1135275.6 | E7: 15748.91 | F7: IBGE PIB dos Municípios (oficial) | G7: 9647.072 | H7: 117.68 | I7: 76416 | J7: 2026 | K7: 7.92
A8: 2910800 | B8: Feira de Santana | C8: 2023 | D8: 21846455 | E8: 35449.37 | F8: IBGE PIB dos Municípios (oficial) | G8: 1304.425 | H8: 16747.96 | I8: 663408 | J8: 2026 | K8: 508.58
A9: 2913606 | B9: Ilhéus | C9: 2023 | D9: 7234380.8 | E9: 40494.94 | F9: IBGE PIB dos Municípios (oficial) | G9: 1588.555 | H9: 4554.06 | I9: 189259 | J9: 2026 | K9: 119.14
A10: 2914802 | B10: Itabuna | C10: 2023 | D10: 5152367.1 | E10: 27595.86 | F10: IBGE PIB dos Municípios (oficial) | G10: 401.028 | H10: 12847.9 | I10: 196041 | J10: 2026 | K10: 488.85
A11: 2918407 | B11: Juazeiro | C11: 2023 | D11: 6159603.8 | E11: 25900.17 | F11: IBGE PIB dos Municípios (oficial) | G11: 6721.237 | H11: 916.44 | I11: 257616 | J11: 2026 | K11: 38.33
A12: 2919207 | B12: Lauro de Freitas | C12: 2023 | D12: 8918479.6 | E12: 43861.88 | F12: IBGE PIB dos Municípios (oficial) | G12: 57.942 | H12: 153920.81 | I12: 221023 | J12: 2026 | K12: 3814.56
A13: 2925303 | B13: Porto Seguro | C13: 2023 | D13: 5009893.7 | E13: 29763.04 | F13: IBGE PIB dos Municípios (oficial) | G13: 2285.734 | H13: 2191.81 | I13: 184087 | J13: 2026 | K13: 80.54
A14: 2927408 | B14: Salvador | C14: 2023 | D14: 76698777 | E14: 31724.15 | F14: IBGE PIB dos Municípios (oficial) | G14: 693.442 | H14: 110605.9 | I14: 2559945 | J14: 2026 | K14: 3691.65
... A17: 2933307 | B17: Vitória da Conquista | C17: 2023 | D17: 12666571 | E17: 34152.84 | F17: IBGE PIB dos Municípios (oficial) | G17: 3254.186 | H17: 3892.39 | I17: 398970 | J17: 2026 | K17: 122.6

Sheet IBGE_Area
A1: ← LEIA-ME | B1: Área (km²) e centroide de cada município | C1: Origem: amostras/ibge_2.4_area_centroide_BA.csv
A2: codigo_ibge | B2: area_km2 | C2: centroide_lon | D2: centroide_lat | E2: municipio | F2: uf | G2: fonte | H2: url_fonte | I2: data_coleta
A3: 2900108 | B3: 538.677 | C3: -41.7429 | D3: -13.2966 | E3: Abaíra | F3: BA | G3: IBGE Malhas v3 | H3: https://servicodados.ibge.gov.br/api/v3/malhas/estados/29/metadados?intrarregiao=municipio | I3: 2026-10-05
A4: 2900207 | B4: 1604.923 | C4: -39.3177 | D4: -8.8335 | E4: Abaré | F4: BA | G4: IBGE Malhas v3 | H4: https://servicodados.ibge.gov.br/api/v3/malhas/estados/29/metadados?intrarregiao=municipio | I4: 2026-10-05
A5: 2900306 | B5: 181.475 | C5: -38.0005 | D5: -11.6632 | E5: Acajutiba | F5: BA | G5: IBGE Malhas v3 | H5: https://servicodados.ibge.gov.br/api/v3/malhas/estados/29/metadados?intrarregiao=municipio | I5: 2026-10-05
A6: 2900355 | B6: 629.099 | C6: -38.0376 | D6: -10.5623 | E6: Adustina | F6: BA | G6: IBGE Malhas v3 | H6: https://servicodados.ibge.gov.br/api/v3/malhas/estados/29/metadados?intrarregiao=municipio | I6: 2026-10-05
A7: 2900405 | B7: 742.775 | C7: -38.7105 | D7: -11.8232 | E7: Água Fria | F7: BA | G7: IBGE Malhas v3 | H7: https://servicodados.ibge.gov.br/api/v3/malhas/estados/29/metadados?intrarregiao=municipio | I7: 2026-10-05
A8: 2900504 | B8: 735.249 | C8: -42.0673 | D8: -13.4002 | E8: Érico Cardoso | F8: BA | G8: IBGE Malhas v3 | H8: https://servicodados.ibge.gov.br/api/v3/malhas/estados/29/metadados?intrarregiao=municipio | I8: 2026-10-05
A9: 2900603 | B9: 167.877 | C9: -39.8809 | D9: -14.0918 | E9: Aiquara | F9: BA | G9: IBGE Malhas v3 | H9: https://servicodados.ibge.gov.br/api/v3/malhas/estados/29/metadados?intrarregiao=municipio | I9: 2026-10-05
A10: 2900702 | B10: 707.835 | C10: -38.4022 | D10: -12.1131 | E10: Alagoinhas | F10: BA | G10: IBGE Malhas v3 | H10: https://servicodados.ibge.gov.br/api/v3/malhas/estados/29/metadados?intrarregiao=municipio | I10: 2026-10-05
A11: 2900801 | B11: 1477.929 | C11: -39.4096 | D11: -17.4692 | E11: Alcobaça | F11: BA | G11: IBGE Malhas v3 | H11: https://servicodados.ibge.gov.br/api/v3/malhas/estados/29/metadados?intrarregiao=municipio | I11: 2026-10-05
A12: 2900900 | B12: 245.236 | C12: -39.6641 | D12: -14.7013 | E12: Almadina | F12: BA | G12: IBGE Malhas v3 | H12: https://servicodados.ibge.gov.br/api/v3/malhas/estados/29/metadados?intrarregiao=municipio | I12: 2026-10-05
A13: 2901007 | B13: 431.655 | C13: -39.6263 | D13: -13.0409 | E13: Amargosa | F13: BA | G13: IBGE Malhas v3 | H13: https://servicodados.ibge.gov.br/api/v3/malhas/estados/29/metadados?intrarregiao=municipio | I13: 2026-10-05
A14: 2901106 | B14: 166.872 | C14: -38.7205 | D14: -12.4212 | E14: Amélia Rodrigues | F14: BA | G14: IBGE Malhas v3 | H14: https://servicodados.ibge.gov.br/api/v3/malhas/estados/29/metadados?intrarregiao=municipio | I14: 2026-10-05
... A419: 2933604 | B419: 5079.662 | C419: -42.7801 | D419: -10.9843 | E419: Xique-Xique | F419: BA | G419: IBGE Malhas v3 | H419: https://servicodados.ibge.gov.br/api/v3/malhas/estados/29/metadados?intrarregiao=municipio | I419: 2026-10-05

Sheet IBGE_Malha
A1: ← LEIA-ME | B1: Metadados do polígono de cada município (o GeoJSON completo fica fora da planilha) | C1: Origem: amostras/ibge_2.7_malha_amostra_BA.csv
A2: codigo_ibge | B2: tipo_geometria | C2: n_vertices_aprox | D2: municipio
A3: 2900108 | B3: Polygon | C3: 23 | D3: Abaíra
A4: 2900207 | B4: Polygon | C4: 22 | D4: Abaré
A5: 2900306 | B5: Polygon | C5: 14 | D5: Acajutiba
A6: 2900355 | B6: Polygon | C6: 17 | D6: Adustina
A7: 2900405 | B7: Polygon | C7: 16 | D7: Água Fria
A8: 2900504 | B8: Polygon | C8: 26 | D8: Érico Cardoso
A9: 2900603 | B9: Polygon | C9: 13 | D9: Aiquara
A10: 2900702 | B10: Polygon | C10: 22 | D10: Alagoinhas
A11: 2900801 | B11: Polygon | C11: 23 | D11: Alcobaça
A12: 2900900 | B12: Polygon | C12: 10 | D12: Almadina
A13: 2901007 | B13: Polygon | C13: 19 | D13: Amargosa
A14: 2901106 | B14: Polygon | C14: 11 | D14: Amélia Rodrigues
... A32: 2902401 | B32: Polygon | C32: 22 | D32: Aurelino Leal

Sheet INEP_IES
A1: ← LEIA-ME | B1: Instituições de ensino superior: tipo, rede, sede, docentes por titulação | C1: Origem: amostras/inep_3.1_3.7_ies_BA_amostra.csv
A2: NU_ANO_CENSO | B2: CO_IES | C2: NO_IES | D2: SG_IES | E2: CO_MUNICIPIO_IES | F2: NO_MUNICIPIO_IES | G2: SG_UF_IES | H2: organizacao_academica | I2: categoria_administrativa | J2: ies_tecnologica_if_cefet | K2: IN_REPOSITORIO_INSTITUCIONAL | L2: IN_ACESSO_PORTAL_CAPES | M2: QT_DOC_TOTAL | N2: QT_DOC_EXE | O2: QT_DOC_EX_DOUT | P2: QT_DOC_EX_MEST | Q2: QT_DOC_EX_ESP | R2: QT_DOC_EX_GRAD | S2: QT_DOC_EX_INT_DE | T2: QT_TEC_DOUTORADO_FEM | U2: QT_TEC_DOUTORADO_MASC
A3: 2024 | B3: 578 | C3: UNIVERSIDADE FEDERAL DA BAHIA | D3: UFBA | E3: 2927408 | F3: Salvador | G3: BA | H3: Universidade | I3: Pública Federal | J3: FALSE | K3: 1 | L3: 1 | M3: 3131 | N3: 3131 | O3: 2466 | P3: 400 | Q3: 63 | R3: 202 | S3: 2127 | T3: 74 | U3: 45
A4: 2024 | B4: 40 | C4: UNIVERSIDADE DO ESTADO DA BAHIA | D4: UNEB | E4: 2927408 | F4: Salvador | G4: BA | H4: Universidade | I4: Pública Estadual | J4: FALSE | K4: 1 | L4: 1 | M4: 1681 | N4: 1681 | O4: 1093 | P4: 583 | Q4: 5 | R4: 0 | S4: 911 | T4: 37 | U4: 10
A5: 2024 | B5: 688 | C5: UNIVERSIDADE ESTADUAL DO SUDOESTE DA BAHIA | D5: UESB | E5: 2933307 | F5: Vitória da Conquista | G5: BA | H5: Universidade | I5: Pública Estadual | J5: FALSE | K5: 1 | L5: 1 | M5: 1034 | N5: 1034 | O5: 708 | P5: 235 | Q5: 89 | R5: 2 | S5: 742 | T5: 9 | U5: 9
A6: 2024 | B6: 4503 | C6: UNIVERSIDADE FEDERAL DO RECÔNCAVO DA BAHIA | D6: UFRB | E6: 2909802 | F6: Cruz das Almas | G6: BA | H6: Universidade | I6: Pública Federal | J6: FALSE | K6: 1 | L6: 1 | M6: 1020 | N6: 1020 | O6: 702 | P6: 243 | Q6: 31 | R6: 44 | S6: 859 | T6: 16 | U6: 14
A7: 2024 | B7: 666 | C7: UNIVERSIDADE ESTADUAL DE FEIRA DE SANTANA | D7: UEFS | E7: 2910800 | F7: Feira de Santana | G7: BA | H7: Universidade | I7: Pública Estadual | J7: FALSE | K7: 0 | L7: 1 | M7: 851 | N7: 851 | O7: 611 | P7: 199 | Q7: 40 | R7: 1 | S7: 447 | T7: 30 | U7: 20
A8: 2024 | B8: 24 | C8: UNIVERSIDADE ESTADUAL DE SANTA CRUZ | D8: UESC | E8: 2913606 | F8: Ilhéus | G8: BA | H8: Universidade | I8: Pública Estadual | J8: FALSE | K8: 0 | L8: 1 | M8: 820 | N8: 820 | O8: 603 | P8: 176 | Q8: 38 | R8: 3 | S8: 642 | T8: 11 | U8: 6
A9: 2024 | B9: 599 | C9: INSTITUTO FEDERAL DE EDUCAÇÃO, CIÊNCIA E TECNOLOGIA DA BAHIA | D9: IFBA | E9: 2927408 | F9: Salvador | G9: BA | H9: Instituto Federal de Educação, Ciência e Tecnologia | I9: Pública Federal | J9: TRUE | K9: 1 | L9: 1 | M9: 895 | N9: 895 | O9: 370 | P9: 418 | Q9: 107 | R9: 0 | S9: 756 | T9: 17 | U9: 6
A10: 2024 | B10: 18506 | C10: UNIVERSIDADE FEDERAL DO OESTE DA BAHIA | D10: UFOB | E10: 2903201 | F10: Barreiras | G10: BA | H10: Universidade | I10: Pública Federal | J10: FALSE | K10: 1 | L10: 1 | M10: 411 | N10: 411 | O10: 296 | P10: 72 | Q10: 29 | R10: 14 | S10: 328 | T10: 3 | U10: 0
A11: 2024 | B11: 534 | C11: ESCOLA BAHIANA DE MEDICINA E SAÚDE PÚBLICA | D11: EBMSP | E11: 2927408 | F11: Salvador | G11: BA | H11: Faculdade | I11: Privada sem fins lucrativos | J11: FALSE | K11: 1 | L11: 1 | M11: 518 | N11: 518 | O11: 274 | P11: 193 | Q11: 51 | R11: 0 | S11: 0 | T11: 1 | U11: 1
A12: 2024 | B12: 18812 | C12: UNIVERSIDADE FEDERAL DO SUL DA BAHIA | D12: UFSB | E12: 2914802 | F12: Itabuna | G12: BA | H12: Universidade | I12: Pública Federal | J12: FALSE | K12: 0 | L12: 1 | M12: 335 | N12: 335 | O12: 266 | P12: 43 | Q12: 26 | R12: 0 | S12: 261 | T12: 5 | U12: 4
A13: 2024 | B13: 14509 | C13: INSTITUTO FEDERAL DE EDUCAÇÃO, CIÊNCIA E TECNOLOGIA BAIANO | D13: IFBAIANO | E13: 2927408 | F13: Salvador | G13: BA | H13: Instituto Federal de Educação, Ciência e Tecnologia | I13: Pública Federal | J13: TRUE | K13: 1 | L13: 1 | M13: 434 | N13: 434 | O13: 217 | P13: 170 | Q13: 31 | R13: 16 | S13: 405 | T13: 18 | U13: 13
A14: 2024 | B14: 1883 | C14: CENTRO UNIVERSITÁRIO UNIME | D14: UNIME | E14: 2919207 | F14: Lauro de Freitas | G14: BA | H14: Centro Universitário | I14: Privada com fins lucrativos | J14: FALSE | K14: 1 | L14: 0 | M14: 441 | N14: 441 | O14: 124 | P14: 152 | Q14: 165 | R14: 0 | S14: 0 | T14: 0 | U14: 0
... A21: 2024 | B21: 1461 | C21: Centro Universitário Zarns - Salvador | D21: ZARNS SALVADOR | E21: 2927408 | F21: Salvador | G21: BA | H21: Centro Universitário | I21: Privada com fins lucrativos | J21: FALSE | K21: 1 | L21: 0 | M21: 122 | N21: 122 | O21: 66 | P21: 55 | Q21: 1 | R21: 0 | S21: 0 | T21: 2 | U21: 0
A22: 2024 | B22: 3034 | C22: Faculdade Anhanguera Unime de Salvador | E22: 2927408 | F22: Salvador | G22: BA | H22: Faculdade | I22: Privada com fins lucrativos | J22: FALSE | K22: 1 | L22: 0 | M22: 188 | N22: 188 | O22: 61 | P22: 74 | Q22: 53 | R22: 0 | S22: 0 | T22: 0 | U22: 0
A23: 2024 | B23: 18708 | C23: Faculdade AGES de Senhor do Bonfim | D23: Faculdade AGES | E23: 2930105 | F23: Senhor do Bonfim | G23: BA | H23: Faculdade | I23: Privada com fins lucrativos | J23: FALSE | K23: 1 | L23: 0 | M23: 232 | N23: 232 | O23: 57 | P23: 128 | Q23: 47 | R23: 0 | S23: 0 | T23: 0 | U23: 0
A24: 2024 | B24: 2402 | C24: Centro Universitário UNIFTC | E24: 2927408 | F24: Salvador | G24: BA | H24: Centro Universitário | I24: Privada com fins lucrativos | J24: FALSE | K24: 1 | L24: 1 | M24: 239 | N24: 239 | O24: 52 | P24: 125 | Q24: 62 | R24: 0 | S24: 0 | T24: 0 | U24: 0
A25: 2024 | B25: 2560 | C25: FACULDADE DE ENSINO SUPERIOR DA CIDADE DE FEIRA DE SANTANA | D25: FAESF/UNEF | E25: 2910800 | F25: Feira de Santana | G25: BA | H25: Faculdade | I25: Privada com fins lucrativos | J25: FALSE | K25: 1 | L25: 0 | M25: 122 | N25: 122 | O25: 50 | P25: 72 | Q25: 0 | R25: 0 | S25: 1 | T25: 0 | U25: 0
A26: 2024 | B26: 2944 | C26: FACULDADE ANHANGUERA DE ITABUNA | E26: 2914802 | F26: Itabuna | G26: BA | H26: Faculdade | I26: Privada com fins lucrativos | J26: FALSE | K26: 1 | L26: 0 | M26: 141 | N26: 141 | O26: 50 | P26: 41 | Q26: 50 | R26: 0 | S26: 0 | T26: 0 | U26: 0
A27: 2024 | B27: 2437 | C27: FACULDADE ANHANGUERA DE TEIXEIRA DE FREITAS | E27: 2931350 | F27: Teixeira de Freitas | G27: BA | H27: Faculdade | I27: Privada com fins lucrativos | J27: FALSE | K27: 1 | L27: 0 | M27: 109 | N27: 109 | O27: 46 | P27: 25 | Q27: 38 | R27: 0 | S27: 0 | T27: 0 | U27: 0
A28: 2024 | B28: 1718 | C28: CENTRO UNIVERSITÁRIO NOBRE DE FEIRA DE SANTANA | E28: 2910800 | F28: Feira de Santana | G28: BA | H28: Centro Universitário | I28: Privada com fins lucrativos | J28: FALSE | K28: 1 | L28: 0 | M28: 127 | N28: 127 | O28: 45 | P28: 82 | Q28: 0 | R28: 0 | S28: 0 | T28: 2 | U28: 0
A29: 2024 | B29: 396 | C29: Centro Universitário Ruy Barbosa Wyden | D29: UniRuy Wyden | E29: 2927408 | F29: Salvador | G29: BA | H29: Centro Universitário | I29: Privada com fins lucrativos | J29: FALSE | K29: 0 | L29: 0 | M29: 98 | N29: 98 | O29: 45 | P29: 42 | Q29: 11 | R29: 0 | S29: 0 | T29: 1 | U29: 0
A30: 2024 | B30: 1053 | C30: Centro Universitário de Excelência | D30: UNEX | E30: 2910800 | F30: Feira de Santana | G30: BA | H30: Centro Universitário | I30: Privada com fins lucrativos | J30: FALSE | K30: 1 | L30: 1 | M30: 147 | N30: 147 | O30: 43 | P30: 68 | Q30: 36 | R30: 0 | S30: 0 | T30: 1 | U30: 0
A31: 2024 | B31: 3588 | C31: CENTRO UNIVERSITÁRIO DOM PEDRO II | D31: UNIDOMPEDRO | E31: 2927408 | F31: Salvador | G31: BA | H31: Centro Universitário | I31: Privada com fins lucrativos | J31: FALSE | K31: 0 | L31: 0 | M31: 209 | N31: 209 | O31: 38 | P31: 68 | Q31: 103 | R31: 0 | S31: 0 | T31: 1 | U31: 1
A32: 2024 | B32: 4959 | C32: FACULDADE ANHANGUERA DE FEIRA DE SANTANA | E32: 2910800 | F32: Feira de Santana | G32: BA | H32: Faculdade | I32: Privada com fins lucrativos | J32: FALSE | K32: 1 | L32: 0 | M32: 61 | N32: 61 | O32: 38 | P32: 10 | Q32: 13 | R32: 0 | S32: 0 | T32: 0 | U32: 0
A33: 2024 | B33: 18625 | C33: Faculdade Anhanguera De Vitória Da Conquista | E33: 2933307 | F33: Vitória da Conquista | G33: BA | H33: Faculdade | I33: Privada com fins lucrativos | J33: FALSE | K33: 1 | L33: 0 | M33: 74 | N33: 74 | O33: 37 | P33: 16 | Q33: 21 | R33: 0 | S33: 0 | T33: 0 | U33: 0
A34: 2024 | B34: 2023 | C34: Centro Universitário FG | D34: UNIFG | E34: 2911709 | F34: Guanambi | G34: BA | H34: Centro Universitário | I34: Privada com fins lucrativos | J34: FALSE | K34: 1 | L34: 1 | M34: 131 | N34: 131 | O34: 36 | P34: 46 | Q34: 49 | R34: 0 | S34: 0 | T34: 1 | U34: 1
A35: 2024 | B35: 19260 | C35: FACULDADE ANHANGUERA DE JEQUIÉ | D35: FPJ | E35: 2918001 | F35: Jequié | G35: BA | H35: Faculdade | I35: Privada com fins lucrativos | J35: FALSE | K35: 1 | L35: 0 | M35: 65 | N35: 65 | O35: 35 | P35: 9 | Q35: 21 | R35: 0 | S35: 0 | T35: 0 | U35: 0
A36: 2024 | B36: 21553 | C36: FACULDADE ANHANGUERA DE SANTO ANTÔNIO DE JESUS | E36: 2928703 | F36: Santo Antônio de Jesus | G36: BA | H36: Faculdade | I36: Privada com fins lucrativos | J36: FALSE | K36: 1 | L36: 0 | M36: 67 | N36: 67 | O36: 34 | P36: 8 | Q36: 25 | R36: 0 | S36: 0 | T36: 0 | U36: 0
A37: 2024 | B37: 2474 | C37: CENTRO UNIVERSITÁRIO MARIA MILZA | D37: UNIMAM | E37: 2909802 | F37: Cruz das Almas | G37: BA | H37: Centro Universitário | I37: Privada com fins lucrativos | J37: FALSE | K37: 1 | L37: 1 | M37: 220 | N37: 220 | O37: 33 | P37: 126 | Q37: 61 | R37: 0 | S37: 0 | T37: 9 | U37: 3
A38: 2024 | B38: 1055 | C38: Centro Universitário Maurício de Nassau de Salvador | D38: Uninassau Salvador | E38: 2927408 | F38: Salvador | G38: BA | H38: Centro Universitário | I38: Privada sem fins lucrativos | J38: FALSE | K38: 1 | L38: 0 | M38: 114 | N38: 114 | O38: 31 | P38: 62 | Q38: 21 | R38: 0 | S38: 0 | T38: 4 | U38: 0
A39: 2024 | B39: 1643 | C39: FACULDADE ANÍSIO TEIXEIRA DE FEIRA DE SANTANA | D39: FAT | E39: 2910800 | F39: Feira de Santana | G39: BA | H39: Centro Universitário | I39: Privada sem fins lucrativos | J39: FALSE | K39: 1 | L39: 1 | M39: 191 | N39: 191 | O39: 30 | P39: 104 | Q39: 57 | R39: 0 | S39: 0 | T39: 1 | U39: 2
A40: 2024 | B40: 2222 | C40: Centro Universitário do Rio São Francisco Unirios | D40: UNIRIOS | E40: 2924009 | F40: Paulo Afonso | G40: BA | H40: Centro Universitário | I40: Privada com fins lucrativos | J40: FALSE | K40: 1 | L40: 0 | M40: 108 | N40: 108 | O40: 29 | P40: 58 | Q40: 21 | R40: 0 | S40: 3 | T40: 0 | U40: 0
A41: 2024 | B41: 3365 | C41: Faculdade UniBRAS Juazeiro | D41: FACBRAS | E41: 2918407 | F41: Juazeiro | G41: BA | H41: Faculdade | I41: Privada com fins lucrativos | J41: FALSE | K41: 0 | L41: 0 | M41: 41 | N41: 41 | O41: 26 | P41: 15 | Q41: 0 | R41: 0 | S41: 0 | T41: 1 | U41: 0
A42: 2024 | B42: 3864 | C42: Centro Universitário UNIRB - Alagoinhas | E42: 2900702 | F42: Alagoinhas | G42: BA | H42: Centro Universitário | I42: Privada com fins lucrativos | J42: FALSE | K42: 1 | L42: 1 | M42: 52 | N42: 52 | O42: 25 | P42: 27 | Q42: 0 | R42: 0 | S42: 0 | T42: 0 | U42: 0

Sheet INEP_Cursos
A1: ← LEIA-ME | B1: Cursos de graduação: área CINE, grau, modalidade, vagas, matrículas, ingressantes e concluintes | C1: Origem: amostras/inep_3.2_a_3.6_cursos_BA_amostra.csv
A2: NU_ANO_CENSO | B2: CO_IES | C2: NO_IES | D2: CO_CURSO | E2: NO_CURSO | F2: CO_MUNICIPIO | G2: NO_MUNICIPIO | H2: SG_UF | I2: modalidade | J2: dimensao | K2: grau_academico | L2: CO_CINE_AREA_GERAL | M2: NO_CINE_AREA_GERAL | N2: CO_CINE_AREA_ESPECIFICA | O2: NO_CINE_AREA_ESPECIFICA | P2: CO_CINE_AREA_DETALHADA | Q2: NO_CINE_AREA_DETALHADA | R2: CO_CINE_ROTULO | S2: NO_CINE_ROTULO | T2: nivel_cti | U2: QT_CURSO | V2: QT_VG_TOTAL | W2: QT_VG_TOTAL_EAD | X2: QT_INSCRITO_TOTAL | Y2: QT_ING | Z2: QT_MAT | AA2: QT_CONC
A3: 2024 | B3: 1883 | C3: CENTRO UNIVERSITÁRIO UNIME | D3: 1322107 | E3: Engenharia Química | F3: 2919207 | G3: Lauro de Freitas | H3: BA | I3: Presencial | J3: Presencial (município de oferta) | K3: Bacharelado | L3: 07 | M3: Engenharia, produção e construção | N3: 071 | O3: Engenharia e profissões correlatas | P3: 0711 | Q3: Engenharia química e de processos | R3: 0711E05 | S3: Engenharia química | T3: CT&I núcleo (STEM) | U3: 1 | V3: 0 | W3: 0 | X3: 0 | Y3: 0 | Z3: 6 | AA3: 2
A4: 2024 | B4: 2437 | C4: FACULDADE ANHANGUERA DE TEIXEIRA DE FREITAS | D4: 73519 | E4: Ciência Da Computação | F4: 2931350 | G4: Teixeira de Freitas | H4: BA | I4: Presencial | J4: Presencial (município de oferta) | K4: Bacharelado | L4: 06 | M4: Computação e Tecnologias da Informação e Comunicação (TIC) | N4: 061 | O4: Computação e Tecnologias da Informação e Comunicação (TIC) | P4: 0613 | Q4: Análise e desenvolvimento de algoritmos e aplicações | R4: 0613C01 | S4: Ciência da computação | T4: CT&I núcleo (STEM) | U4: 1 | V4: 0 | W4: 0 | X4: 0 | Y4: 0 | Z4: 2 | AA4: 1
A5: 2024 | B5: 3962 | C5: UNIVERSIDADE SENAI CIMATEC | D5: 1151355 | E5: Engenharia De Controle E Automação | F5: 2927408 | G5: Salvador | H5: BA | I5: Presencial | J5: Presencial (município de oferta) | K5: Bacharelado | L5: 07 | M5: Engenharia, produção e construção | N5: 071 | O5: Engenharia e profissões correlatas | P5: 0714 | Q5: Eletrônica e automação | R5: 0714E05 | S5: Engenharia de controle e automação | T5: CT&I núcleo (STEM) | U5: 1 | V5: 80 | W5: 0 | X5: 201 | Y5: 25 | Z5: 97 | AA5: 19
A6: 2024 | B6: 396 | C6: Centro Universitário Ruy Barbosa Wyden | D6: 1258415 | E6: Engenharia De Controle E Automação | F6: 2927408 | G6: Salvador | H6: BA | I6: Presencial | J6: Presencial (município de oferta) | K6: Bacharelado | L6: 07 | M6: Engenharia, produção e construção | N6: 071 | O6: Engenharia e profissões correlatas | P6: 0714 | Q6: Eletrônica e automação | R6: 0714E05 | S6: Engenharia de controle e automação | T6: CT&I núcleo (STEM) | U6: 1 | V6: 607 | W6: 0 | X6: 5 | Y6: 4 | Z6: 20 | AA6: 6
A7: 2024 | B7: 396 | C7: Centro Universitário Ruy Barbosa Wyden | D7: 1070727 | E7: Manutenção Industrial | F7: 2927408 | G7: Salvador | H7: BA | I7: Presencial | J7: Presencial (município de oferta) | K7: Tecnológico | L7: 07 | M7: Engenharia, produção e construção | N7: 071 | O7: Engenharia e profissões correlatas | P7: 0715 | Q7: Engenharia mecânica e metalurgia | R7: 0715M01 | S7: Manutenção industrial | T7: CT&I núcleo (STEM) | U7: 1 | V7: 0 | W7: 0 | X7: 0 | Y7: 0 | Z7: 0 | AA7: 0
A8: 2024 | B8: 385 | C8: UNIVERSIDADE SALVADOR | D8: 1258708 | E8: Engenharia De Petróleo | F8: 2927408 | G8: Salvador | H8: BA | I8: Presencial | J8: Presencial (município de oferta) | K8: Bacharelado | L8: 07 | M8: Engenharia, produção e construção | N8: 072 | O8: Produção e processamento | P8: 0724 | Q8: Mineração e extração | R8: 0724E02 | S8: Engenharia de petróleo | T8: CT&I núcleo (STEM) | U8: 1 | V8: 0 | W8: 0 | X8: 0 | Y8: 0 | Z8: 0 | AA8: 0
A9: 2024 | B9: 24 | C9: UNIVERSIDADE ESTADUAL DE SANTA CRUZ | D9: 150314 | E9: Engenharia Civil | F9: 2913606 | G9: Ilhéus | H9: BA | I9: Presencial | J9: Presencial (município de oferta) | K9: Bacharelado | L9: 07 | M9: Engenharia, produção e construção | N9: 073 | O9: Arquitetura e construção | P9: 0732 | Q9: Engenharia civil e construção | R9: 0732E01 | S9: Engenharia civil | T9: CT&I núcleo (STEM) | U9: 1 | V9: 70 | W9: 0 | X9: 211 | Y9: 46 | Z9: 162 | AA9: 9
A10: 2024 | B10: 3984 | C10: FUNDAÇÃO UNIVERSIDADE FEDERAL DO VALE DO SÃO FRANCISCO | D10: 1661974 | E10: Geologia | F10: 2930105 | G10: Senhor do Bonfim | H10: BA | I10: Presencial | J10: Presencial (município de oferta) | K10: Bacharelado | L10: 05 | M10: Ciências naturais, matemática e estatística | N10: 053 | O10: Ciências físicas | P10: 0532 | Q10: Ciências da terra | R10: 0532G02 | S10: Geologia | T10: CT&I núcleo (STEM) | U10: 1 | V10: 40 | W10: 0 | X10: 40 | Y10: 35 | Z10: 0 | AA10: 0
A11: 2024 | B11: 2222 | C11: Centro Universitário do Rio São Francisco Unirios | D11: 73140 | E11: Sistema De Informação | F11: 2924009 | G11: Paulo Afonso | H11: BA | I11: Presencial | J11: Presencial (município de oferta) | K11: Bacharelado | L11: 06 | M11: Computação e Tecnologias da Informação e Comunicação (TIC) | N11: 061 | O11: Computação e Tecnologias da Informação e Comunicação (TIC) | P11: 0613 | Q11: Análise e desenvolvimento de algoritmos e aplicações | R11: 0613S01 | S11: Sistemas de informação | T11: CT&I núcleo (STEM) | U11: 1 | V11: 130 | W11: 0 | X11: 104 | Y11: 104 | Z11: 201 | AA11: 11
A12: 2024 | B12: 2023 | C12: Centro Universitário FG | D12: 1489887 | E12: Análise E Desenvolvimento De Sistemas | F12: 2911709 | G12: Guanambi | H12: BA | I12: Presencial | J12: Presencial (município de oferta) | K12: Tecnológico | L12: 06 | M12: Computação e Tecnologias da Informação e Comunicação (TIC) | N12: 061 | O12: Computação e Tecnologias da Informação e Comunicação (TIC) | P12: 0613 | Q12: Análise e desenvolvimento de algoritmos e aplicações | R12: 0613S01 | S12: Sistemas de informação | T12: CT&I núcleo (STEM) | U12: 1 | V12: 45 | W12: 0 | X12: 105 | Y12: 45 | Z12: 80 | AA12: 12
A13: 2024 | B13: 10058 | C13: FACULDADE DA FRATERNIDADE DE VALENÇA | D13: 1204205 | E13: Engenharia Civil | F13: 2932903 | G13: Valença | H13: BA | I13: Presencial | J13: Presencial (município de oferta) | K13: Bacharelado | L13: 07 | M13: Engenharia, produção e construção | N13: 073 | O13: Arquitetura e construção | P13: 0732 | Q13: Engenharia civil e construção | R13: 0732E01 | S13: Engenharia civil | T13: CT&I núcleo (STEM) | U13: 1 | V13: 304 | W13: 0 | X13: 304 | Y13: 6 | Z13: 6 | AA13: 0
A14: 2024 | B14: 385 | C14: UNIVERSIDADE SALVADOR | D14: 1404804 | E14: Análise E Desenvolvimento De Sistemas | F14: 2927408 | G14: Salvador | H14: BA | I14: Presencial | J14: Presencial (município de oferta) | K14: Tecnológico | L14: 06 | M14: Computação e Tecnologias da Informação e Comunicação (TIC) | N14: 061 | O14: Computação e Tecnologias da Informação e Comunicação (TIC) | P14: 0613 | Q14: Análise e desenvolvimento de algoritmos e aplicações | R14: 0613S01 | S14: Sistemas de informação | T14: CT&I núcleo (STEM) | U14: 1 | V14: 17 | W14: 0 | X14: 45 | Y14: 17 | Z14: 61 | AA14: 22
... A37: 2024 | B37: 298 | C37: Universidade Pitágoras Unopar Anhanguera | D37: 1548987 | E37: Arquitetura De Dados | F37: 2925303 | G37: Porto Seguro | H37: BA | I37: EAD | J37: EAD ofertado no Brasil (por município/polo) | K37: Tecnológico | L37: 06 | M37: Computação e Tecnologias da Informação e Comunicação (TIC) | N37: 061 | O37: Computação e Tecnologias da Informação e Comunicação (TIC) | P37: 0612 | Q37: Infraestrutura e gestão de TIC | R37: 0612B01 | S37: Banco de dados | T37: CT&I núcleo (STEM) | U37: 0 | V37: 0 | W37: 0 | X37: 0 | Y37: 3 | Z37: 3 | AA37: 1

Sheet INEP_Cursos_Municipio
A1: ← LEIA-ME | B1: Soma de cursos, vagas e matrículas presenciais por município e nível CT&I | C1: Origem: amostras/inep_cursos_presenciais_por_municipio_nivel_cti_amostra.csv
A2: CO_MUNICIPIO | B2: NO_MUNICIPIO | C2: nivel_cti | D2: QT_CURSO | E2: QT_VG_TOTAL | F2: QT_MAT | G2: QT_ING | H2: QT_CONC
A3: 2903201 | B3: Barreiras | C3: CT&I ampliado | D3: 21 | E3: 3040 | F3: 4018 | G3: 1115 | H3: 569
A4: 2903201 | B4: Barreiras | C4: CT&I núcleo (STEM) | D4: 13 | E4: 687 | F4: 949 | G4: 273 | H4: 138
A5: 2903201 | B5: Barreiras | C5: Fora de CT&I | D5: 25 | E5: 2008 | F5: 3356 | G5: 1052 | H5: 378
A6: 2905701 | B6: Camaçari | C6: CT&I ampliado | D6: 5 | E6: 193 | F6: 97 | G6: 48 | H6: 17
A7: 2905701 | B7: Camaçari | C7: CT&I núcleo (STEM) | D7: 6 | E7: 305 | F7: 424 | G7: 160 | H7: 47
A8: 2905701 | B8: Camaçari | C8: Fora de CT&I | D8: 11 | E8: 833 | F8: 1350 | G8: 451 | H8: 207
A9: 2907202 | B9: Casa Nova | C9: Fora de CT&I | D9: 1 | E9: 223 | F9: 99 | G9: 18 | H9: 31
A10: 2910800 | B10: Feira de Santana | C10: CT&I ampliado | D10: 57 | E10: 10656 | F10: 8847 | G10: 2771 | H10: 1321
A11: 2910800 | B11: Feira de Santana | C11: CT&I núcleo (STEM) | D11: 45 | E11: 4532 | F11: 3841 | G11: 1137 | H11: 506
A12: 2910800 | B12: Feira de Santana | C12: Fora de CT&I | D12: 71 | E12: 9057 | F12: 12983 | G12: 4362 | H12: 1792
A13: 2913606 | B13: Ilhéus | C13: CT&I ampliado | D13: 13 | E13: 1390 | F13: 2197 | G13: 529 | H13: 344
A14: 2913606 | B14: Ilhéus | C14: CT&I núcleo (STEM) | D14: 13 | E14: 1168 | F14: 1815 | G14: 524 | H14: 163
... A38: 2933307 | B38: Vitória da Conquista | C38: Fora de CT&I | D38: 41 | E38: 6247 | F38: 8850 | G38: 2851 | H38: 1163

Sheet ANEEL_SIGA
A1: ← LEIA-ME | B1: Usinas de geração: tipo, fonte, fase, potência, coordenadas, município (texto) | C1: Origem: amostras/aneel_4.1_4.2_siga_geracao_BA.csv
A2: DatGeracaoConjuntoDados | B2: NomEmpreendimento | C2: IdeNucleoCEG | D2: CodCEG | E2: SigUFPrincipal | F2: SigTipoGeracao | G2: DscFaseUsina | H2: DscOrigemCombustivel | I2: DscFonteCombustivel | J2: DscTipoOutorga | K2: NomFonteCombustivel | L2: DatEntradaOperacao | M2: MdaPotenciaOutorgadaKw | N2: MdaPotenciaFiscalizadaKw | O2: MdaGarantiaFisicaKw | P2: IdcGeracaoQualificada | Q2: NumCoordNEmpreendimento | R2: NumCoordEEmpreendimento | S2: DatInicioVigencia | T2: DatFimVigencia | U2: DscPropriRegimePariticipacao | V2: DscSubBacia | W2: DscMuninicpios
A3: 2026-10-01 | B3: Bahia Pulp (Antiga Bacell) | C3: 000182 | D3: UTE.FL.BA.000182-1.1 | E3: BA | F3: UTE | G3: Operação | H3: Biomassa | I3: Floresta | J3: Autorização | K3: Licor Negro | L3: 1995-11-29 | M3: 108600 | N3: 108600 | O3: 300 | P3: Não | Q3: -12.643082 | R3: -38.337171 | S3: 2026-08-04 | T3: 2061-08-04 | U3: 100% para BRACELL BAHIA SPECIALTY CELLULOSE S.A. - 69.037.133/0001-39 (PIE) | W3: Camaçari - BA
A4: 2026-10-01 | B4: Suzano Mucuri (Antiga Bahia Sul) | C4: 000187 | D4: UTE.FL.BA.000187-2.1 | E4: BA | F4: UTE | G4: Operação | H4: Biomassa | I4: Floresta | J4: Autorização | K4: Licor Negro | L4: 1992-03-01 | M4: 214080 | N4: 214080 | O4: 0 | P4: Não | Q4: -18.042462 | R4: -39.919661 | S4: 2011-04-14 | T4: 2041-04-14 | U4: 100% para SUZANO S.A. - 16.404.287/0001-55 (APE) | W4: Mucuri - BA
A5: 2026-10-01 | B5: Camaçari | C5: 000602 | D5: UTE.GN.BA.000602-5.1 | E5: BA | F5: UTE | G5: Operação | H5: Fóssil | I5: Gás natural | J5: Autorização | K5: Gás Natural | L5: 1996-01-01 | M5: 130710 | N5: 130710 | O5: 0 | P5: Sim | Q5: -12.687227 | R5: -38.352569 | S5: 1996-10-16 | T5: 2026-10-16 | U5: 100% para Braskem S/A - 42.150.391/0001-70 (PIE) | W5: Camaçari - BA
A6: 2026-10-01 | B6: Fazenda Cachoeira | C6: 000939 | D6: UTE.PE.BA.000939-3.1 | E6: BA | F6: UTE | G6: Operação | H6: Fóssil | I6: Petróleo | J6: Registro | K6: Óleo Diesel | L6: 1998-09-11 | M6: 60 | N6: 60 | O6: 0 | P6: Não | Q6: -11.047991 | R6: -45.192991 | U6: 100% para Alcides Trento - (REG) | W6: Formosa do Rio Preto - BA
A7: 2026-10-01 | B7: Norfil Agro | C7: 000945 | D7: CGH.PH.BA.000945-8.1 | E7: BA | F7: CGH | G7: Operação | H7: Hídrica | I7: Potencial hidráulico | J7: Registro | K7: Potencial hidráulico | L7: 1990-01-01 | M7: 450 | N7: 450 | O7: 0 | P7: Não | Q7: -12.879247 | R7: -45.800474 | U7: 100% para NORFIL AGRO LTDA - 06.213.692/0001-32 (REG) | V7: 46 - Grande e outros - Sao Francisco | W7: São Desidério - BA
A8: 2026-10-01 | B8: Itapebi | C8: 001175 | D8: UHE.PH.BA.001175-4.1 | E8: BA | F8: UHE | G8: Operação | H8: Hídrica | I8: Potencial hidráulico | J8: Concessão | K8: Potencial hidráulico | L8: 2003-02-18 | M8: 462011 | N8: 462011 | O8: 202100 | P8: Não | Q8: -15.965643 | R8: -39.592639 | S8: 1999-05-28 | T8: 2039-05-18 | U8: 100% para ITAPEBI GERACAO DE ENERGIA SA - 02.397.080/0001-96 (PIE) | V8: 54 - Jequitinhonha | W8: Itapebi - BA
A9: 2026-10-01 | B9: Itapetinga | C9: 001178 | D9: UTE.PE.BA.001178-9.1 | E9: BA | F9: UTE | G9: Operação | H9: Fóssil | I9: Petróleo | J9: Registro | K9: Óleo Diesel | L9: 2008-07-01 | M9: 324 | N9: 324 | O9: 0 | P9: Não | Q9: -15.246167 | R9: -40.247381 | U9: 100% para REIZIGER PARTICIPACOES LTDA - 04.483.165/0001-12 (REG) | W9: Itapetinga - BA
A10: 2026-10-01 | B10: Paulo Afonso I | C10: 002012 | D10: UHE.PH.BA.002012-5.1 | E10: BA | F10: UHE | G10: Operação | H10: Hídrica | I10: Potencial hidráulico | J10: Concessão | K10: Potencial hidráulico | L10: 1964-12-30 | M10: 180001 | N10: 180001 | O10: 10 | P10: Não | Q10: -9.3981038 | R10: -38.202872 | S10: 2022-06-17 | T10: 2052-06-17 | U10: 100% para AXIA ENERGIA NORDESTE S.A. - 33.541.368/0001-16 (PIE) | V10: 49 - Sao Francisco, a jusante do Pajeu | W10: Delmiro Gouveia - AL, Paulo Afonso - BA
A11: 2026-10-01 | B11: Presidente Goulart | C11: 002146 | D11: PCH.PH.BA.002146-6.1 | E11: BA | F11: PCH | G11: Operação | H11: Hídrica | I11: Potencial hidráulico | J11: Concessão | K11: Potencial hidráulico | L11: 1963-12-31 | M11: 8000 | N11: 8000 | O11: 5210 | P11: Não | Q11: -13.338903 | R11: -44.633047 | S11: 1997-08-08 | T11: 2029-03-21 | U11: 100% para AFLUENTE GERACAO DE ENERGIA ELETRICA S.A. - 07.620.094/0001-40 (SP) | V11: 45 - Corrente e outros - Sao Francisco | W11: Correntina - BA
A12: 2026-10-01 | B12: Refinaria Landulpho Alves (RLAM) | C12: 002197 | D12: UTE.PE.BA.002197-0.1 | E12: BA | F12: UTE | G12: Operação | H12: Fóssil | I12: Petróleo | J12: Autorização | K12: Gás de Refinaria | L12: 2001-08-01 | M12: 62500 | N12: 62500 | O12: 0 | P12: Não | Q12: -12.62401 | R12: -38.670535 | S12: 1998-08-24 | T12: 2028-08-24 | U12: 100% para REFINARIA DE MATARIPE S.A. - 41.777.706/0001-41 (APE) | W12: São Francisco do Conde - BA
A13: 2026-10-01 | B13: Rieger Agropecuária | C13: 002271 | D13: CGH.PH.BA.002271-3.2 | E13: BA | F13: CGH | G13: Operação | H13: Hídrica | I13: Potencial hidráulico | J13: Registro | K13: Potencial hidráulico | L13: 1987-08-01 | M13: 3000 | N13: 3000 | O13: 0 | P13: Não | Q13: -12.452215 | R13: -45.190382 | U13: 100% para RIEGER AGROPECUARIA LTDA - 77.837.656/0001-98 (REG) | V13: 46 - Grande e outros - Sao Francisco | W13: São Desidério - BA
A14: 2026-10-01 | B14: Salvador | C14: 002683 | D14: UTE.RU.BA.002683-2.1 | E14: BA | F14: UTE | G14: Operação | H14: Biomassa | I14: Resíduos sólidos urbanos | J14: Autorização | K14: Biogás - RU | L14: 2010-12-22 | M14: 19730 | N14: 19730 | O14: 8500 | P14: Não | Q14: -12.860337 | R14: -38.352079 | S14: 2009-02-10 | T14: 2039-02-10 | U14: 100% para TERMOVERDE SALVADOR S.A. - 10.267.349/0001-48 (PIE) | W14: Salvador - BA
A15: 2026-10-01 | B15: Sítio Grande | C15: 002754 | D15: PCH.PH.BA.002754-5.1 | E15: BA | F15: PCH | G15: Operação | H15: Hídrica | I15: Potencial hidráulico | J15: Autorização | K15: Potencial hidráulico | L15: 2010-10-23 | M15: 25000 | N15: 25000 | O15: 18640 | P15: Não | Q15: -12.440829 | R15: -45.165558 | S15: 2010-10-23 | T15: 2047-10-27 | U15: 100% para BAHIA PCH I S.A. - 08.747.075/0001-42 (PIE) | V15: 46 - Grande e outros - Sao Francisco | W15: São Desidério - BA
A16: 2026-10-01 | B16: Sobradinho | C16: 002755 | D16: UHE.PH.BA.002755-3.1 | E16: BA | F16: UHE | G16: Operação | H16: Hídrica | I16: Potencial hidráulico | J16: Concessão | K16: Potencial hidráulico | L16: 1982-03-03 | M16: 1050300 | N16: 1050300 | O16: 504500 | P16: Não | Q16: -9.4302384 | R16: -40.827199 | S16: 2022-06-17 | T16: 2052-06-17 | U16: 100% para AXIA ENERGIA NORDESTE S.A. - 33.541.368/0001-16 (PIE) | V16: 47 - Salitre e outros - Sao Francisco | W16: Sobradinho - BA
A17: 2026-10-01 | B17: Funil | C17: 027046 | D17: UHE.PH.BA.027046-6.1 | E17: BA | F17: UHE | G17: Operação | H17: Hídrica | I17: Potencial hidráulico | J17: Concessão | K17: Potencial hidráulico | L17: 1970-02-13 | M17: 30000 | N17: 30000 | O17: 10910 | P17: Não | Q17: -14.229056 | R17: -39.462047 | S17: 2022-06-17 | T17: 2052-06-17 | U17: 100% para AXIA ENERGIA NORDESTE S.A. - 33.541.368/0001-16 (PIE) | V17: 52 - Contas | W17: Ubaitaba - BA
A18: 2026-10-01 | B18: Paulo Afonso II | C18: 027048 | D18: UHE.PH.BA.027048-2.1 | E18: BA | F18: UHE | G18: Operação | H18: Hídrica | I18: Potencial hidráulico | J18: Concessão | K18: Potencial hidráulico | L18: 1961-10-24 | M18: 443000 | N18: 443000 | O18: 10 | P18: Não | Q18: -9.3968831 | R18: -38.202663 | S18: 2022-06-17 | T18: 2052-06-17 | U18: 100% para AXIA ENERGIA NORDESTE S.A. - 33.541.368/0001-16 (PIE) | V18: 49 - Sao Francisco, a jusante do Pajeu | W18: Delmiro Gouveia - AL, Paulo Afonso - BA
A19: 2026-10-01 | B19: Paulo Afonso III | C19: 027049 | D19: UHE.PH.BA.027049-0.1 | E19: BA | F19: UHE | G19: Operação | H19: Hídrica | I19: Potencial hidráulico | J19: Concessão | K19: Potencial hidráulico | L19: 1971-10-21 | M19: 794200 | N19: 794200 | O19: 10 | P19: Não | Q19: -9.3960503 | R19: -38.201937 | S19: 2022-06-17 | T19: 2052-06-17 | U19: 100% para AXIA ENERGIA NORDESTE S.A. - 33.541.368/0001-16 (PIE) | V19: 49 - Sao Francisco, a jusante do Pajeu | W19: Delmiro Gouveia - AL, Paulo Afonso - BA
A20: 2026-10-01 | B20: Paulo Afonso IV | C20: 027050 | D20: UHE.PH.BA.027050-4.1 | E20: BA | F20: UHE | G20: Operação | H20: Hídrica | I20: Potencial hidráulico | J20: Concessão | K20: Potencial hidráulico | L20: 1979-12-01 | M20: 2462400 | N20: 2462400 | O20: 2225000 | P20: Não | Q20: -9.4156453 | R20: -38.207671 | S20: 2022-06-17 | T20: 2052-06-17 | U20: 100% para AXIA ENERGIA NORDESTE S.A. - 33.541.368/0001-16 (PIE) | V20: 49 - Sao Francisco, a jusante do Pajeu | W20: Delmiro Gouveia - AL, Paulo Afonso - BA
A21: 2026-10-01 | B21: Pedra | C21: 027052 | D21: UHE.PH.BA.027052-0.1 | E21: BA | F21: UHE | G21: Operação | H21: Hídrica | I21: Potencial hidráulico | J21: Concessão | K21: Potencial hidráulico | L21: 1978-11-13 | M21: 20007 | N21: 20007 | O21: 3740 | P21: Não | Q21: -13.86835 | R21: -40.235759 | S21: 2022-06-17 | T21: 2052-06-17 | U21: 100% para AXIA ENERGIA NORDESTE S.A. - 33.541.368/0001-16 (PIE) | V21: 52 - Contas | W21: Jequié - BA
A22: 2026-10-01 | B22: Termobahia (Antiga Celso Furtado) | C22: 027263 | D22: UTE.GN.BA.027263-9.1 | E22: BA | F22: UTE | G22: Operação | H22: Fóssil | I22: Gás natural | J22: Autorização | K22: Gás Natural | L22: 2004-02-09 | M22: 173000 | N22: 185891 | O22: 100700 | P22: Sim | Q22: -12.703788 | R22: -38.566924 | S22: 1999-10-27 | T22: 2029-10-27 | U22: 100% para PETRÓLEO BRASILEIRO S.A. PETROBRAS - 33.000.167/0001-01 (PIE) | W22: São Francisco do Conde - BA
A23: 2026-10-01 | B23: Alto Fêmeas I | C23: 027414 | D23: UHE.PH.BA.027414-3.1 | E23: BA | F23: UHE | G23: Operação | H23: Hídrica | I23: Potencial hidráulico | J23: Concessão | K23: Potencial hidráulico | L23: 1992-01-01 | M23: 10650 | N23: 10650 | O23: 8550 | P23: Não | Q23: -12.452378 | R23: -45.190692 | S23: 2019-10-11 | T23: 2028-12-20 | U23: 100% para AFLUENTE GERACAO DE ENERGIA ELETRICA S.A. - 07.620.094/0001-40 (SP) | V23: 46 - Grande e outros - Sao Francisco | W23: São Desidério - BA
A24: 2026-10-01 | B24: Fazenda Magna Mater | C24: 027739 | D24: CGH.PH.BA.027739-8.1 | E24: BA | F24: CGH | G24: Operação | H24: Hídrica | I24: Potencial hidráulico | J24: Registro | K24: Potencial hidráulico | L24: 1900-01-03 | M24: 7.5 | N24: 7 | O24: 0 | P24: Não | Q24: -13.097025 | R24: -41.850734 | U24: 100% para Roberto Solano de Freitas - (REG) | V24: 52 - Contas | W24: Piatã - BA
A25: 2026-10-01 | B25: Iguatemi Bahia | C25: 028067 | D25: UTE.GN.BA.028067-4.1 | E25: BA | F25: UTE | G25: Operação | H25: Fóssil | I25: Gás natural | J25: Autorização | K25: Gás Natural | L25: 2004-12-30 | M25: 8316 | N25: 8316 | O25: 0 | P25: Sim | Q25: -12.89601 | R25: -38.290535 | S25: 2001-03-09 | T25: 2031-03-09 | U25: 100% para CONDOMINIO SHOPPING DA BAHIA - 14.804.587/0001-04 (APE) | W25: Salvador - BA
A26: 2026-10-01 | B26: Fazenda Cachoeira | C26: 028185 | D26: CGH.PH.BA.028185-9.1 | E26: BA | F26: CGH | G26: Operação | H26: Hídrica | I26: Potencial hidráulico | J26: Registro | K26: Potencial hidráulico | L26: 1900-01-03 | M26: 60 | N26: 60 | O26: 0 | P26: Não | Q26: -11.455881 | R26: -45.642429 | U26: 100% para Alcides Trento - (REG) | V26: 46 - Grande e outros - Sao Francisco | W26: Formosa do Rio Preto - BA
A27: 2026-10-01 | B27: Kaiser - Feira de Santana | C27: 028278 | D27: UTE.PE.BA.028278-2.1 | E27: BA | F27: UTE | G27: Operação | H27: Fóssil | I27: Petróleo | J27: Registro | K27: Óleo Diesel | L27: 1900-01-03 | M27: 1600 | N27: 1600 | O27: 0 | P27: Não | Q27: -12.297923 | R27: -38.966334 | U27: 100% para CERVEJARIA HNK BR LTDA - 21.900.899/0001-79 (REG) | W27: Feira de Santana - BA
A28: 2026-10-01 | B28: Pedra do Cavalo | C28: 028565 | D28: UHE.PH.BA.028565-0.1 | E28: BA | F28: UHE | G28: Operação | H28: Hídrica | I28: Potencial hidráulico | J28: Concessão | K28: Potencial hidráulico | L28: 2004-12-16 | M28: 160000 | N28: 160000 | O28: 60000 | P28: Não | Q28: -12.583539 | R28: -38.998023 | S28: 2002-04-23 | T28: 2044-04-25 | U28: 100% para VOTORANTIM CIMENTOS N/NE S/A - 10.656.452/0001-80 (PIE) | V28: 51 - Jequirica, Paraguacu e outros | W28: Cachoeira - BA, Governador Mangabeira - BA
A29: 2026-10-01 | B29: Millennium | C29: 028588 | D29: UTE.GN.BA.028588-9.1 | E29: BA | F29: UTE | G29: Operação | H29: Fóssil | I29: Gás natural | J29: Registro | K29: Gás Natural | L29: 1900-01-03 | M29: 4781 | N29: 4781 | O29: 0 | P29: Sim | Q29: -12.698817 | R29: -38.32574 | U29: 100% para TRONOX PIGMENTOS DO BRASIL SA - 15.115.504/0009-81 (REG) | W29: Camaçari - BA
A30: 2026-10-01 | B30: Condomínio Shopping Center Piedade | C30: 028599 | D30: UTE.PE.BA.028599-4.1 | E30: BA | F30: UTE | G30: Operação | H30: Fóssil | I30: Petróleo | J30: Registro | K30: Óleo Diesel | L30: 2002-05-06 | M30: 223 | N30: 223 | O30: 0 | P30: Não | Q30: -12.96701 | R30: -38.501535 | U30: 100% para CONDOMINIO SHOPPING CENTER PIEDADE - 13.792.742/0001-49 (REG) | W30: Salvador - BA
A31: 2026-10-01 | B31: Brumado | C31: 028663 | D31: UTE.PE.BA.028663-0.1 | E31: BA | F31: UTE | G31: Operação | H31: Fóssil | I31: Petróleo | J31: Autorização | K31: Óleo Diesel | L31: 1977-09-01 | M31: 12895 | N31: 12895 | O31: 0 | P31: Não | Q31: -14.239268 | R31: -41.723303 | S31: 2002-07-16 | T31: 2032-07-16 | U31: 100% para MAGNESITA MINERACAO S.A. - 00.592.603/0001-20 (APE) | W31: Brumado - BA
A32: 2026-10-01 | B32: Agrovale | C32: 028696 | D32: UTE.AI.BA.028696-6.1 | E32: BA | F32: UTE | G32: Operação | H32: Biomassa | I32: Agroindustriais | J32: Autorização | K32: Bagaço de Cana de Açúcar | L32: 1979-05-01 | M32: 16000 | N32: 16000 | O32: 600 | P32: Não | Q32: -9.4978452 | R32: -40.365933 | S32: 2004-05-06 | T32: 2034-05-06 | U32: 100% para AGRO INDUSTRIAS DO VALE DO SAO FRANCISCO SA AGROVALE - 13.642.699/0001-35 (PIE) | W32: Juazeiro - BA
A33: 2026-10-01 | B33: Colino 2 | C33: 028997 | D33: PCH.PH.BA.028997-3.1 | E33: BA | F33: PCH | G33: Operação | H33: Hídrica | I33: Potencial hidráulico | J33: Autorização | K33: Potencial hidráulico | L33: 2008-07-17 | M33: 16000 | N33: 16000 | O33: 4690 | P33: Não | Q33: -17.072399 | R33: -40.106022 | S33: 2008-07-17 | T33: 2048-04-29 | U33: 100% para ENERGETICA SERRA DA PRATA S/A - 05.982.449/0001-16 (PIE) | V33: 55 - Sao mateus, Itanhem e outros | W33: Jucuruçu - BA, Vereda - BA
A34: 2026-10-01 | B34: Cachoeira da Lixa | C34: 028999 | D34: PCH.PH.BA.028999-0.1 | E34: BA | F34: PCH | G34: Operação | H34: Hídrica | I34: Potencial hidráulico | J34: Autorização | K34: Potencial hidráulico | L34: 2008-05-24 | M34: 14800 | N34: 14800 | O34: 7440 | P34: Não | Q34: -17.074798 | R34: -40.069347 | S34: 2008-05-24 | T34: 2048-02-27 | U34: 100% para ENERGETICA SERRA DA PRATA S/A - 05.982.449/0001-16 (PIE) | V34: 55 - Sao mateus, Itanhem e outros | W34: Itamaraju - BA, Jucuruçu - BA
A35: 2026-10-01 | B35: Colino 1 | C35: 029004 | D35: PCH.PH.BA.029004-1.1 | E35: BA | F35: PCH | G35: Operação | H35: Hídrica | I35: Potencial hidráulico | J35: Autorização | K35: Potencial hidráulico | L35: 2008-09-23 | M35: 11000 | N35: 11000 | O35: 6620 | P35: Não | Q35: -17.075421 | R35: -40.085557 | S35: 2008-09-23 | T35: 2048-06-29 | U35: 100% para ENERGETICA SERRA DA PRATA S/A - 05.982.449/0001-16 (PIE) | V35: 55 - Sao mateus, Itanhem e outros | W35: Jucuruçu - BA, Vereda - BA
A36: 2026-10-01 | B36: Veracel | C36: 029014 | D36: UTE.FL.BA.029014-9.1 | E36: BA | F36: UTE | G36: Operação | H36: Biomassa | I36: Floresta | J36: Autorização | K36: Licor Negro | L36: 2006-01-02 | M36: 126600 | N36: 126000 | O36: 0 | P36: Não | Q36: -16.37401 | R36: -39.570535 | S36: 2003-12-30 | T36: 2033-12-30 | U36: 100% para VERACEL CELULOSE S.A. - 40.551.996/0001-48 (APE) | W36: Eunápolis - BA
A37: 2026-10-01 | B37: Asperbras | C37: 029182 | D37: UTE.PE.BA.029182-0.1 | E37: BA | F37: UTE | G37: Operação | H37: Fóssil | I37: Petróleo | J37: Registro | K37: Óleo Diesel | L37: 2002-10-30 | M37: 640 | N37: 640 | O37: 0 | P37: Não | Q37: -12.7871 | R37: -38.403291 | U37: 100% para ASPERBRAS BAHIA LTDA - 03.685.549/0001-55 (REG) | W37: Simões Filho - BA
A38: 2026-10-01 | B38: Torah | C38: 029191 | D38: UTE.PE.BA.029191-9.1 | E38: BA | F38: UTE | G38: Operação | H38: Fóssil | I38: Petróleo | J38: Registro | K38: Óleo Diesel | L38: 2002-05-31 | M38: 720 | N38: 720 | O38: 0 | P38: Não | Q38: -13.014772 | R38: -38.488061 | U38: 100% para TORAH - TURISMO ORGANIZACAO E ADMINISTRACAO HOTELEIRA LTDA - 04.970.748/0001-78 (REG) | W38: Salvador - BA
A39: 2026-10-01 | B39: Calçados Azaléia | C39: 029626 | D39: UTE.PE.BA.029626-0.1 | E39: BA | F39: UTE | G39: Operação | H39: Fóssil | I39: Petróleo | J39: Autorização | K39: Óleo Diesel | L39: 2002-01-01 | M39: 7500 | N39: 7500 | O39: 0 | P39: Não | Q39: -15.24501 | R39: -40.238535 | S39: 2007-10-18 | T39: 2037-10-18 | U39: 100% para VULCABRAS BA CALCADOS E ARTIGOS ESPORTIVOS S.A. - 00.733.658/0001-02 (APE) | W39: Itapetinga - BA
A40: 2026-10-01 | B40: Global II | C40: 029639 | D40: UTE.PE.BA.029639-2.1 | E40: BA | F40: UTE | G40: Operação | H40: Fóssil | I40: Petróleo | J40: Autorização | K40: Óleo Combustível | L40: 2010-05-20 | M40: 136400 | N40: 136400 | O40: 109300 | P40: Não | Q40: -12.729994 | R40: -38.482121 | S40: 2007-12-07 | T40: 2042-12-07 | U40: 100% para COMPANHIA ENERGÉTICA CANDEIAS - 10.508.162/0001-99 (PIE) | W40: Candeias - BA
A41: 2026-10-01 | B41: Global I | C41: 029653 | D41: UTE.PE.BA.029653-8.1 | E41: BA | F41: UTE | G41: Operação | H41: Fóssil | I41: Petróleo | J41: Autorização | K41: Óleo Combustível | L41: 2010-05-07 | M41: 136400 | N41: 136400 | O41: 105300 | P41: Não | Q41: -12.73021 | R41: -38.481217 | S41: 2007-12-21 | T41: 2042-12-21 | U41: 100% para COMPANHIA ENERGÉTICA CANDEIAS - 10.508.162/0001-99 (PIE) | W41: Candeias - BA
A42: 2026-10-01 | B42: Condomínio Shopping Center Lapa | C42: 029659 | D42: UTE.PE.BA.029659-7.1 | E42: BA | F42: UTE | G42: Operação | H42: Fóssil | I42: Petróleo | J42: Registro | K42: Óleo Diesel | L42: 2008-01-11 | M42: 1920 | N42: 1920 | O42: 0 | P42: Não | Q42: -12.96701 | R42: -38.501535 | U42: 100% para Condomínio Shopping Center Lapa - 01.143.325/0001-96 (REG) | W42: Salvador - BA
A43: 2026-10-01 | B43: Juliana II | C43: 029697 | D43: CGH.PH.BA.029697-0.1 | E43: BA | F43: CGH | G43: Operação | H43: Hídrica | I43: Potencial hidráulico | J43: Registro | K43: Potencial hidráulico | L43: 2008-05-09 | M43: 400 | N43: 400 | O43: 150 | P43: Não | Q43: -13.836944 | R43: -39.2775 | U43: 100% para HOWDEN SOUTH AMERICA VENTILADORES E COMPRESSORES INDÚSTRIA E COMÉRCIO LTDA. - 01.094.363/0001-04 (REG) | V43: 51 - Jequirica, Paraguacu e outros | W43: Igrapiúna - BA
A44: 2026-10-01 | B44: Juliana I | C44: 029698 | D44: CGH.PH.BA.029698-8.1 | E44: BA | F44: CGH | G44: Operação | H44: Hídrica | I44: Potencial hidráulico | J44: Registro | K44: Potencial hidráulico | L44: 2008-05-09 | M44: 144 | N44: 144 | O44: 50 | P44: Não | Q44: -13.836974 | R44: -39.277566 | U44: 100% para HOWDEN SOUTH AMERICA VENTILADORES E COMPRESSORES INDÚSTRIA E COMÉRCIO LTDA. - 01.094.363/0001-04 (REG) | V44: 51 - Jequirica, Paraguacu e outros | W44: Igrapiúna - BA
A45: 2026-10-01 | B45: Vargido | C45: 029699 | D45: CGH.PH.BA.029699-6.1 | E45: BA | F45: CGH | G45: Operação | H45: Hídrica | I45: Potencial hidráulico | J45: Registro | K45: Potencial hidráulico | L45: 2008-05-09 | M45: 300 | N45: 300 | O45: 40 | P45: Não | Q45: -13.851069 | R45: -39.280233 | U45: 100% para HOWDEN SOUTH AMERICA VENTILADORES E COMPRESSORES INDÚSTRIA E COMÉRCIO LTDA. - 01.094.363/0001-04 (REG) | V45: 51 - Jequirica, Paraguacu e outros | W45: Igrapiúna - BA
A46: 2026-10-01 | B46: Poly Embalagens | C46: 029741 | D46: UTE.PE.BA.029741-0.1 | E46: BA | F46: UTE | G46: Operação | H46: Fóssil | I46: Petróleo | J46: Registro | K46: Óleo Diesel | L46: 2007-10-01 | M46: 324 | N46: 324 | O46: 0 | P46: Não | Q46: -12.780454 | R46: -38.394423 | U46: 100% para Poly Embalagens Ltda. - 01.029.001/0001-21 (REG) | W46: Simões Filho - BA
A47: 2026-10-01 | B47: Poly II | C47: 029744 | D47: UTE.PE.BA.029744-5.1 | E47: BA | F47: UTE | G47: Operação | H47: Fóssil | I47: Petróleo | J47: Registro | K47: Óleo Diesel | L47: 2008-08-28 | M47: 168 | N47: 168 | O47: 0 | P47: Não | Q47: -12.780454 | R47: -38.394423 | U47: 100% para Poly Embalagens Ltda. - 01.029.001/0001-21 (REG) | W47: Simões Filho - BA
A48: 2026-10-01 | B48: Fortik Nordeste | C48: 029791 | D48: UTE.PE.BA.029791-7.1 | E48: BA | F48: UTE | G48: Operação | H48: Fóssil | I48: Petróleo | J48: Registro | K48: Óleo Diesel | L48: 1900-01-03 | M48: 972 | N48: 972 | O48: 0 | P48: Não | Q48: -12.337427 | R48: -38.776779 | U48: 100% para FCC - INDUSTRIA E COMERCIO LTDA. - 03.281.950/0001-20 (REG) | W48: Conceição do Jacuípe - BA
A49: 2026-10-01 | B49: Aeroporto Internacional de Salvador | C49: 029861 | D49: UTE.PE.BA.029861-1.1 | E49: BA | F49: UTE | G49: Operação | H49: Fóssil | I49: Petróleo | J49: Registro | K49: Óleo Diesel | L49: 1900-01-03 | M49: 2023 | N49: 2023 | O49: 0 | P49: Não | Q49: -12.910252 | R49: -38.330343 | U49: 100% para EMPRESA BRASILEIRA DE INFRAESTRUTURA AEROPORTUARIA - INFRAERO - 00.352.294/0001-10 (REG) | W49: Salvador - BA
A50: 2026-10-01 | B50: Sansuy | C50: 029907 | D50: UTE.PE.BA.029907-3.1 | E50: BA | F50: UTE | G50: Operação | H50: Fóssil | I50: Petróleo | J50: Registro | K50: Óleo Diesel | L50: 2008-10-07 | M50: 1920 | N50: 1920 | O50: 0 | P50: Não | Q50: -12.698817 | R50: -38.32574 | U50: 100% para Sansuy S.A Indústria de Plásticos - 14.807.945/0001-24 (REG) | W50: Camaçari - BA
A51: 2026-10-01 | B51: Cromex - BA | C51: 029924 | D51: UTE.PE.BA.029924-3.1 | E51: BA | F51: UTE | G51: Operação | H51: Fóssil | I51: Petróleo | J51: Registro | K51: Óleo Diesel | L51: 2008-10-07 | M51: 1296 | N51: 1296 | O51: 0 | P51: Não | Q51: -12.818452 | R51: -38.43379 | U51: 100% para Cromex Bahia Ltda. - 03.860.076/0000-18 (REG) | W51: Simões Filho - BA
A52: 2026-10-01 | B52: Eternit Simões Filho | C52: 030096 | D52: UTE.PE.BA.030096-9.1 | E52: BA | F52: UTE | G52: Operação | H52: Fóssil | I52: Petróleo | J52: Registro | K52: Óleo Diesel | L52: 2010-06-07 | M52: 1440 | N52: 1440 | O52: 0 | P52: Não | Q52: -12.744584 | R52: -38.404707 | U52: 100% para ETERNIT S.A - 61.092.037/0001-81 (REG), 100% para STEMAC ENERGIA S.A. - 03.841.196/0001-35 (REG) | W52: Simões Filho - BA
A53: 2026-10-01 | B53: Itambé | C53: 030133 | D53: UTE.PE.BA.030133-7.1 | E53: BA | F53: UTE | G53: Operação | H53: Fóssil | I53: Petróleo | J53: Registro | K53: Óleo Diesel | L53: 2008-07-01 | M53: 186 | N53: 186 | O53: 0 | P53: Não | Q53: -15.248019 | R53: -40.624042 | U53: Não Informado | W53: Itambé - BA
A54: 2026-10-01 | B54: Itapetinga - Filial 04 | C54: 030134 | D54: UTE.PE.BA.030134-5.1 | E54: BA | F54: UTE | G54: Operação | H54: Fóssil | I54: Petróleo | J54: Registro | K54: Óleo Diesel | L54: 2008-07-01 | M54: 324 | N54: 324 | O54: 0 | P54: Não | Q54: -15.246167 | R54: -40.247381 | U54: 100% para VULCABRAS AZALEIA-RS,CALCADOS E ARTIGOS ESPORTIVOS S/A - 98.408.073/0001-11 (REG) | W54: Itapetinga - BA
A55: 2026-10-01 | B55: Itambé - Filial 06 | C55: 030135 | D55: UTE.PE.BA.030135-3.1 | E55: BA | F55: UTE | G55: Operação | H55: Fóssil | I55: Petróleo | J55: Registro | K55: Óleo Diesel | L55: 2008-07-01 | M55: 186 | N55: 186 | O55: 0 | P55: Não | Q55: -15.248019 | R55: -40.624042 | U55: Não Informado | W55: Itambé - BA
A56: 2026-10-01 | B56: Potiguará | C56: 030136 | D56: UTE.PE.BA.030136-1.1 | E56: BA | F56: UTE | G56: Operação | H56: Fóssil | I56: Petróleo | J56: Registro | K56: Óleo Diesel | L56: 2008-07-01 | M56: 186 | N56: 186 | O56: 0 | P56: Não | Q56: -15.592456 | R56: -39.87566 | U56: 100% para VULCABRAS AZALEIA-RS,CALCADOS E ARTIGOS ESPORTIVOS S/A - 98.408.073/0001-11 (REG) | W56: Potiraguá - BA
A57: 2026-10-01 | B57: Itarantim | C57: 030137 | D57: UTE.PE.BA.030137-0.1 | E57: BA | F57: UTE | G57: Operação | H57: Fóssil | I57: Petróleo | J57: Registro | K57: Óleo Diesel | L57: 2008-07-01 | M57: 186 | N57: 186 | O57: 0 | P57: Não | Q57: -15.65783 | R57: -40.061545 | U57: 100% para VULCABRAS AZALEIA-RS,CALCADOS E ARTIGOS ESPORTIVOS S/A - 98.408.073/0001-11 (REG) | W57: Itarantim - BA
... A69: 2026-10-01 | B69: IBC | C69: 030212 | D69: UTE.PE.BA.030212-0.1 | E69: BA | F69: UTE | G69: Operação | H69: Fóssil | I69: Petróleo | J69: Registro | K69: Óleo Diesel | L69: 2009-03-01 | M69: 440 | N69: 440 | O69: 0 | P69: Não | Q69: -12.66591 | R69: -38.20632 | U69: 100% para SINTEX LAMINADOS SINTETICOS LTDA. - 04.774.215/0001-10 (REG) | W69: Camaçari - BA
A70: 2026-10-01 | B70: Macaúbas | C70: 030283 | D70: EOL.CV.BA.030283-0.1 | E70: BA | F70: EOL | G70: Operação | H70: Eólica | I70: Cinética do vento | J70: Autorização | K70: Cinética do vento | L70: 2012-07-06 | M70: 35070 | N70: 35070 | O70: 13400 | P70: Não | Q70: -12.351191 | R70: -42.338525 | S70: 2010-06-21 | T70: 2045-06-21 | U70: 100% para MACAUBAS ENERGETICA SA - 09.194.393/0001-96 (PIE) | W70: Brotas de Macaúbas - BA
A71: 2026-10-01 | B71: Pedra do Reino | C71: 030288 | D71: EOL.CV.BA.030288-0.1 | E71: BA | F71: EOL | G71: Operação | H71: Eólica | I71: Cinética do vento | J71: Autorização | K71: Cinética do vento | L71: 2013-02-04 | M71: 30000 | N71: 30000 | O71: 10840 | P71: Não | Q71: -9.5175483 | R71: -40.886394 | S71: 2010-06-30 | T71: 2045-06-30 | U71: 100% para EOLICA PEDRA DO REINO S.A. - 11.608.271/0001-40 (PIE) | W71: Sobradinho - BA
A72: 2026-10-01 | B72: Novo Horizonte | C72: 030305 | D72: EOL.CV.BA.030305-4.1 | E72: BA | F72: EOL | G72: Operação | H72: Eólica | I72: Cinética do vento | J72: Autorização | K72: Cinética do vento | L72: 2012-07-06 | M72: 30060 | N72: 30060 | O72: 10970 | P72: Não | Q72: -12.312699 | R72: -42.350988 | S72: 2010-07-30 | T72: 2045-07-30 | U72: 100% para NOVO HORIZONTE ENERGETICA S/A - 09.214.349/0001-09 (PIE) | W72: Brotas de Macaúbas - BA
A73: 2026-10-01 | B73: Seabra | C73: 030306 | D73: EOL.CV.BA.030306-2.1 | E73: BA | F73: EOL | G73: Operação | H73: Eólica | I73: Cinética do vento | J73: Autorização | K73: Cinética do vento | L73: 2012-07-06 | M73: 35390 | N73: 35390 | O73: 11330 | P73: Não | Q73: -12.278703 | R73: -42.362604 | S73: 2010-07-30 | T73: 2045-07-30 | U73: 100% para SEABRA ENERGETICA S/A - 09.196.341/0001-59 (PIE) | W73: Brotas de Macaúbas - BA
A74: 2026-10-01 | B74: Serra do Salto | C74: 030314 | D74: EOL.CV.BA.030314-3.1 | E74: BA | F74: EOL | G74: Operação | H74: Eólica | I74: Cinética do vento | J74: Autorização | K74: Cinética do vento | L74: 2014-07-04 | M74: 19200 | N74: 19200 | O74: 7460 | P74: Não | Q74: -14.155456 | R74: -42.63822 | S74: 2010-08-06 | T74: 2045-08-06 | U74: 100% para CENTRAIS EOLICAS SERRA DO SALTO LTDA. - 11.349.836/0001-12 (PIE) | W74: Guanambi - BA
A75: 2026-10-01 | B75: Ilhéus | C75: 030315 | D75: EOL.CV.BA.030315-1.1 | E75: BA | F75: EOL | G75: Operação | H75: Eólica | I75: Cinética do vento | J75: Autorização | K75: Cinética do vento | L75: 2014-07-04 | M75: 11200 | N75: 11200 | O75: 5040 | P75: Não | Q75: -13.8823 | R75: -42.66305 | S75: 2010-08-06 | T75: 2045-08-06 | U75: 100% para CENTRAIS EOLICAS ILHEUS LTDA. - 11.366.468/0001-10 (PIE) | W75: Guanambi - BA
A76: 2026-10-01 | B76: Candiba | C76: 030316 | D76: EOL.CV.BA.030316-0.1 | E76: BA | F76: EOL | G76: Operação | H76: Eólica | I76: Cinética do vento | J76: Autorização | K76: Cinética do vento | L76: 2014-07-04 | M76: 9600 | N76: 9600 | O76: 4280 | P76: Não | Q76: -14.183147 | R76: -42.622749 | S76: 2010-08-06 | T76: 2045-08-06 | U76: 100% para CENTRAIS EOLICAS CANDIBA LTDA. - 11.349.756/0001-67 (PIE) | W76: Guanambi - BA
A77: 2026-10-01 | B77: Licínio de Almeida | C77: 030317 | D77: EOL.CV.BA.030317-8.1 | E77: BA | F77: EOL | G77: Operação | H77: Eólica | I77: Cinética do vento | J77: Autorização | K77: Cinética do vento | L77: 2014-07-04 | M77: 24000 | N77: 24000 | O77: 10940 | P77: Não | Q77: -14.176944 | R77: -42.654063 | S77: 2010-08-06 | T77: 2045-08-06 | U77: 100% para CENTRAIS EOLICAS LICINIO DE ALMEIDA LTDA. - 11.349.904/0001-43 (PIE) | W77: Guanambi - BA
A78: 2026-10-01 | B78: Nossa Senhora da Conceição | C78: 030318 | D78: EOL.CV.BA.030318-6.1 | E78: BA | F78: EOL | G78: Operação | H78: Eólica | I78: Cinética do vento | J78: Autorização | K78: Cinética do vento | L78: 2014-07-04 | M78: 28800 | N78: 28800 | O78: 12430 | P78: Não | Q78: -13.895694 | R78: -42.676889 | S78: 2010-08-06 | T78: 2045-08-06 | U78: 100% para CENTRAIS EOLICAS NOSSA SENHORA DA CONCEICAO LTDA. - 11.371.340/0001-45 (PIE) | W78: Igaporã - BA
A79: 2026-10-01 | B79: Pajeú do Vento | C79: 030319 | D79: EOL.CV.BA.030319-4.1 | E79: BA | F79: EOL | G79: Operação | H79: Eólica | I79: Cinética do vento | J79: Autorização | K79: Cinética do vento | L79: 2014-07-04 | M79: 25600 | N79: 25600 | O79: 11800 | P79: Não | Q79: -14.01475 | R79: -42.633861 | S79: 2010-08-06 | T79: 2045-08-06 | U79: 100% para CENTRAIS EOLICAS PAJEU DO VENTO LTDA. - 11.365.985/0001-75 (PIE) | W79: Caetité - BA
A80: 2026-10-01 | B80: Alvorada | C80: 030320 | D80: EOL.CV.BA.030320-8.1 | E80: BA | F80: EOL | G80: Operação | H80: Eólica | I80: Cinética do vento | J80: Autorização | K80: Cinética do vento | L80: 2014-07-04 | M80: 8000 | N80: 8000 | O80: 3970 | P80: Não | Q80: -14.185151 | R80: -42.591073 | S80: 2010-08-06 | T80: 2045-08-26 | U80: 100% para CENTRAIS EOLICAS ALVORADA LTDA. - 11.349.807/0001-50 (PIE) | W80: Caetité - BA
A81: 2026-10-01 | B81: Igaporã | C81: 030321 | D81: EOL.CV.BA.030321-6.1 | E81: BA | F81: EOL | G81: Operação | H81: Eólica | I81: Cinética do vento | J81: Autorização | K81: Cinética do vento | L81: 2014-07-04 | M81: 30400 | N81: 30400 | O81: 13950 | P81: Não | Q81: -13.860574 | R81: -42.657342 | S81: 2010-08-06 | T81: 2045-08-06 | U81: 100% para CENTRAIS EOLICAS IGAPORA LTDA. - 11.366.011/0001-06 (PIE) | W81: Igaporã - BA
... A87: 2026-10-01 | B87: Guirapá | C87: 030342 | D87: EOL.CV.BA.030342-9.1 | E87: BA | F87: EOL | G87: Operação | H87: Eólica | I87: Cinética do vento | J87: Autorização | K87: Cinética do vento | L87: 2014-07-04 | M87: 28800 | N87: 28800 | O87: 13600 | P87: Não | Q87: -14.218915 | R87: -42.641388 | S87: 2010-08-20 | T87: 2045-08-20 | U87: 100% para CENTRAIS EOLICAS GUIRAPA LTDA. - 11.345.796/0001-30 (PIE) | W87: Guanambi - BA
A88: 2026-10-01 | B88: Girassol | C88: 030426 | D88: CGH.PH.BA.030426-3.1 | E88: BA | F88: CGH | G88: Operação | H88: Hídrica | I88: Potencial hidráulico | J88: Registro | K88: Potencial hidráulico | L88: 2010-02-10 | M88: 1000 | N88: 1000 | O88: 0 | P88: Não | Q88: -13.996944 | R88: -45.4025 | U88: 100% para M2 ENERGIA LTDA - 10.212.345/0001-62 (REG) | V88: 45 - Corrente e outros - Sao Francisco | W88: Jaborandi - BA
A89: 2026-10-01 | B89: Ciemil | C89: 030434 | D89: UTE.PE.BA.030434-4.1 | E89: BA | F89: UTE | G89: Operação | H89: Fóssil | I89: Petróleo | J89: Registro | K89: Óleo Diesel | L89: 2011-02-02 | M89: 144 | N89: 144 | O89: 0 | P89: Não | Q89: -14.866111 | R89: -40.839444 | U89: 100% para CIEMIL MINERACAO LTDA - 13.860.192/0001-58 (REG) | W89: Vitória da Conquista - BA
A90: 2026-10-01 | B90: Caetité 2 | C90: 030437 | D90: EOL.CV.BA.030437-9.1 | E90: BA | F90: EOL | G90: Operação | H90: Eólica | I90: Cinética do vento | J90: Autorização | K90: Cinética do vento | L90: 2014-10-08 | M90: 30000 | N90: 30000 | O90: 14700 | P90: Não | Q90: -14.185 | R90: -42.503 | S90: 2011-02-07 | T90: 2046-02-07 | U90: 100% para CAETITE 2 ENERGIA RENOVAVEL S/A - 12.106.989/0001-00 (PIE) | W90: Caetité - BA
A91: 2026-10-01 | B91: Pedra Branca | C91: 030443 | D91: EOL.CV.BA.030443-3.1 | E91: BA | F91: EOL | G91: Operação | H91: Eólica | I91: Cinética do vento | J91: Autorização | K91: Cinética do vento | L91: 2013-03-02 | M91: 30000 | N91: 30000 | O91: 13800 | P91: Não | Q91: -9.8745915 | R91: -41.095715 | S91: 2011-02-18 | T91: 2046-02-18 | U91: 100% para Pedra Branca S.A. - 12.709.996/0001-98 (PIE) | W91: Sento Sé - BA
A92: 2026-10-01 | B92: Caetité 3 | C92: 030448 | D92: EOL.CV.BA.030448-4.1 | E92: BA | F92: EOL | G92: Operação | H92: Eólica | I92: Cinética do vento | J92: Autorização | K92: Cinética do vento | L92: 2014-10-08 | M92: 30000 | N92: 30000 | O92: 11200 | P92: Não | Q92: -14.219444 | R92: -42.507 | S92: 2011-02-24 | T92: 2046-02-24 | U92: 100% para CAETITE 3 ENERGIA RENOVAVEL S/A. - 12.106.879/0001-30 (PIE) | W92: Caetité - BA
A93: 2026-10-01 | B93: Sete Gameleiras | C93: 030455 | D93: EOL.CV.BA.030455-7.1 | E93: BA | F93: EOL | G93: Operação | H93: Eólica | I93: Cinética do vento | J93: Autorização | K93: Cinética do vento | L93: 2013-03-26 | M93: 30000 | N93: 30000 | O93: 12600 | P93: Não | Q93: -9.8638438 | R93: -41.104175 | S93: 2011-02-28 | T93: 2046-02-28 | U93: 100% para SETE GAMELEIRAS S/A - 12.710.327/0001-36 (PIE) | W93: Sento Sé - BA
A94: 2026-10-01 | B94: São Pedro do Lago | C94: 030456 | D94: EOL.CV.BA.030456-5.1 | E94: BA | F94: EOL | G94: Operação | H94: Eólica | I94: Cinética do vento | J94: Autorização | K94: Cinética do vento | L94: 2013-03-02 | M94: 31465 | N94: 31465 | O94: 0 | P94: Não | Q94: -9.8746933 | R94: -41.093011 | S94: 2011-02-28 | T94: 2046-02-28 | U94: 100% para São Pedro do Lago S.A - 12.709.813/0001-34 (PIE) | W94: Sento Sé - BA
A95: 2026-10-01 | B95: Ventos do Nordeste | C95: 030476 | D95: EOL.CV.BA.030476-0.1 | E95: BA | F95: EOL | G95: Operação | H95: Eólica | I95: Cinética do vento | J95: Autorização | K95: Cinética do vento | L95: 2014-10-11 | M95: 23520 | N95: 23520 | O95: 10100 | P95: Não | Q95: -14.119464 | R95: -42.614083 | S95: 2011-03-21 | T95: 2046-03-21 | U95: 100% para CENTRAIS EOLICAS VENTOS DO NORDESTE S/A - 11.204.086/0001-90 (PIE) | W95: Caetité - BA
A96: 2026-10-01 | B96: Da Prata | C96: 030490 | D96: EOL.CV.BA.030490-5.1 | E96: BA | F96: EOL | G96: Operação | H96: Eólica | I96: Cinética do vento | J96: Autorização | K96: Cinética do vento | L96: 2014-10-11 | M96: 21840 | N96: 21840 | O96: 10100 | P96: Não | Q96: -13.964266 | R96: -42.638863 | S96: 2011-03-28 | T96: 2046-03-28 | U96: 100% para CENTRAIS EOLICAS DA PRATA S.A - 11.366.231/0001-30 (PIE) | W96: Igaporã - BA
A97: 2026-10-01 | B97: Dos Araçás | C97: 030495 | D97: EOL.CV.BA.030495-6.1 | E97: BA | F97: EOL | G97: Operação | H97: Eólica | I97: Cinética do vento | J97: Autorização | K97: Cinética do vento | L97: 2014-10-11 | M97: 31860 | N97: 31860 | O97: 15500 | P97: Não | Q97: -14.129593 | R97: -42.559655 | S97: 2011-04-08 | T97: 2046-04-08 | U97: 100% para Centrais Eólicas dos Araçás S.A - 11.201.833/0001-37 (PIE) | W97: Caetité - BA
A98: 2026-10-01 | B98: Morrão | C98: 030506 | D98: EOL.CV.BA.030506-5.1 | E98: BA | F98: EOL | G98: Operação | H98: Eólica | I98: Cinética do vento | J98: Autorização | K98: Cinética do vento | L98: 2014-10-11 | M98: 30240 | N98: 30240 | O98: 16100 | P98: Não | Q98: -14.088509 | R98: -42.682708 | S98: 2011-04-25 | T98: 2046-04-25 | U98: 100% para CENTRAIS EOLICAS MORRAO S/A - 12.049.829/0001-68 (PIE) | W98: Caetité - BA
A99: 2026-10-01 | B99: Tanque | C99: 030544 | D99: EOL.CV.BA.030544-8.1 | E99: BA | F99: EOL | G99: Operação | H99: Eólica | I99: Cinética do vento | J99: Autorização | K99: Cinética do vento | L99: 2014-10-11 | M99: 30000 | N99: 30000 | O99: 13900 | P99: Não | Q99: -14.102598 | R99: -42.610657 | S99: 2011-05-30 | T99: 2046-05-30 | U99: 100% para CENTRAIS EOLICAS TANQUE S.A - 12.048.059/0001-39 (PIE) | W99: Caetité - BA
A100: 2026-10-01 | B100: Seraíma | C100: 030546 | D100: EOL.CV.BA.030546-4.1 | E100: BA | F100: EOL | G100: Operação | H100: Eólica | I100: Cinética do vento | J100: Autorização | K100: Cinética do vento | L100: 2014-10-11 | M100: 30240 | N100: 30240 | O100: 17500 | P100: Não | Q100: -14.147273 | R100: -42.711851 | S100: 2011-05-31 | T100: 2046-05-31 | U100: 100% para CENTRAIS EOLICAS SERAIMA S.A - 12.047.526/0001-06 (PIE) | W100: Guanambi - BA
A101: 2026-10-01 | B101: Dourado | C101: 030578 | D101: CGH.PH.BA.030578-2.1 | E101: BA | F101: CGH | G101: Operação | H101: Hídrica | I101: Potencial hidráulico | J101: Registro | K101: Potencial hidráulico | L101: 1900-01-03 | M101: 980 | N101: 980 | O101: 720 | P101: Não | Q101: -13.997217 | R101: -45.402606 | U101: 100% para Central Geradora Hidráulica Dourado Ltda - 24.426.769/0001-34 (REG) | V101: 45 - Corrente e outros - Sao Francisco | W101: Jaborandi - BA
A102: 2026-10-01 | B102: Pratudão | C102: 030579 | D102: CGH.PH.BA.030579-0.1 | E102: BA | F102: CGH | G102: Operação | H102: Hídrica | I102: Potencial hidráulico | J102: Registro | K102: Potencial hidráulico | L102: 2000-12-20 | M102: 1760 | N102: 1760 | O102: 720 | P102: Não | Q102: -13.997242 | R102: -45.40265 | U102: 100% para Diasa Dourado Irrigação e Agricultura S/A - 24.447.021/0001-18 (REG) | V102: 45 - Corrente e outros - Sao Francisco | W102: Jaborandi - BA
A103: 2026-10-01 | B103: Santa Luzia | C103: 030590 | D103: CGH.PH.BA.030590-1.1 | E103: BA | F103: CGH | G103: Operação | H103: Hídrica | I103: Potencial hidráulico | J103: Registro | K103: Potencial hidráulico | L103: 2011-08-23 | M103: 533.6 | N103: 533 | O103: 0 | P103: Não | Q103: -13.984937 | R103: -39.477067 | U103: 100% para CJ 2 PARTICIPAÇÕES LTDA - 08.933.523/0001-00 (REG) | V103: 52 - Contas | W103: Ibirapitanga - BA
A104: 2026-10-01 | B104: Pedra do Reino III | C104: 030608 | D104: EOL.CV.BA.030608-8.1 | E104: BA | F104: EOL | G104: Operação | H104: Eólica | I104: Cinética do vento | J104: Autorização | K104: Cinética do vento | L104: 2013-06-07 | M104: 18000 | N104: 18000 | O104: 6800 | P104: Não | Q104: -9.4985833 | R104: -40.879 | S104: 2011-08-03 | T104: 2046-08-03 | U104: 100% para EOLICATEC SOBRADINHO S.A. - 12.684.715/0001-90 (PIE) | W104: Sobradinho - BA
A105: 2026-10-01 | B105: Petrorecôncavo | C105: 030630 | D105: UTE.GN.BA.030630-4.1 | E105: BA | F105: UTE | G105: Operação | H105: Fóssil | I105: Gás natural | J105: Registro | K105: Gás Natural | L105: 2011-08-19 | M105: 1000 | N105: 1000 | O105: 0 | P105: Não | Q105: -12.355187 | R105: -38.376294 | U105: 100% para Petrorecôncavo S.A. - 03.342.704/0001-30 (REG) | W105: Catu - BA
A106: 2026-10-01 | B106: Avícola Barreiras | C106: 030651 | D106: UTE.PE.BA.030651-7.1 | E106: BA | F106: UTE | G106: Operação | H106: Fóssil | I106: Petróleo | J106: Registro | K106: Óleo Diesel | L106: 2011-09-21 | M106: 365 | N106: 365 | O106: 0 | P106: Não | Q106: -12.15283 | R106: -44.990053 | U106: 100% para Avícola Barreiras Ltda - 34.122.432/0001-97 (REG) | W106: Barreiras - BA
A107: 2026-10-01 | B107: Complexo de Camaçari | C107: 030676 | D107: UTE.PE.BA.030676-2.1 | E107: BA | F107: UTE | G107: Operação | H107: Fóssil | I107: Petróleo | J107: Registro | K107: Óleo Diesel | L107: 2011-11-01 | M107: 960 | N107: 960 | O107: 0 | P107: Não | Q107: -12.693307 | R107: -38.315151 | U107: 100% para QUIMICA GERAL DO NORDESTE LTDA - 14.727.457/0001-07 (REG) | W107: Camaçari - BA
A108: 2026-10-01 | B108: São Judas | C108: 030725 | D108: EOL.CV.BA.030725-4.1 | E108: BA | F108: EOL | G108: Operação | H108: Eólica | I108: Cinética do vento | J108: Autorização | K108: Cinética do vento | L108: 2017-12-01 | M108: 29900 | N108: 29900 | O108: 15600 | P108: Não | Q108: -11.66425 | R108: -41.362 | S108: 2012-02-01 | T108: 2047-02-01 | U108: 100% para ENEL GREEN POWER SAO JUDAS EOLICA S/A - 12.851.951/0001-53 (PIE) | W108: Morro do Chapéu - BA
A109: 2026-10-01 | B109: Primavera | C109: 030726 | D109: EOL.CV.BA.030726-2.1 | E109: BA | F109: EOL | G109: Operação | H109: Eólica | I109: Cinética do vento | J109: Autorização | K109: Cinética do vento | L109: 2017-11-10 | M109: 29900 | N109: 29900 | O109: 16400 | P109: Não | Q109: -11.733361 | R109: -41.373 | S109: 2012-02-01 | T109: 2047-02-01 | U109: 100% para ENEL GREEN POWER PRIMAVERA EOLICA S/A - 12.851.871/0001-06 (PIE) | W109: Morro do Chapéu - BA
A110: 2026-10-01 | B110: Cristal | C110: 030727 | D110: EOL.CV.BA.030727-0.1 | E110: BA | F110: EOL | G110: Operação | H110: Eólica | I110: Cinética do vento | J110: Autorização | K110: Cinética do vento | L110: 2017-11-10 | M110: 29900 | N110: 29900 | O110: 15700 | P110: Não | Q110: -11.796463 | R110: -41.393384 | S110: 2012-02-01 | T110: 2047-02-01 | U110: 100% para ENEL GREEN POWER CRISTAL EOLICA S/A - 12.851.920/0001-00 (PIE) | W110: Cafarnaum - BA
A111: 2026-10-01 | B111: Pituaçu Solar | C111: 030730 | D111: UFV.RS.BA.030730-0.1 | E111: BA | F111: UFV | G111: Operação | H111: Solar | I111: Radiação solar | J111: Registro | K111: Radiação solar | L111: 1900-01-03 | M111: 404.8 | N111: 404 | O111: 0 | P111: Não | Q111: -12.945833 | R111: -38.417778 | U111: 100% para SUPERINTENDENCIA DE DESPORTOS DO ESTADO DA BAHIA SUDESB - 13.323.001/0001-19 (REG) | W111: Salvador - BA
A112: 2026-10-01 | B112: Teiu | C112: 030731 | D112: EOL.CV.BA.030731-9.1 | E112: BA | F112: EOL | G112: Operação | H112: Eólica | I112: Cinética do vento | J112: Autorização | K112: Cinética do vento | L112: 2016-02-05 | M112: 16650 | N112: 16650 | O112: 8200 | P112: Não | Q112: -14.338138 | R112: -42.591091 | S112: 2012-02-06 | T112: 2047-02-06 | U112: 100% para CENTRAL EOLICA TEIU S/A - 14.570.839/0001-70 (PIE) | W112: Pindaí - BA
A113: 2026-10-01 | B113: Angical | C113: 030732 | D113: EOL.CV.BA.030732-7.1 | E113: BA | F113: EOL | G113: Operação | H113: Eólica | I113: Cinética do vento | J113: Autorização | K113: Cinética do vento | L113: 2016-02-05 | M113: 12950 | N113: 12950 | O113: 6000 | P113: Não | Q113: -14.346057 | R113: -42.613684 | S113: 2012-02-06 | T113: 2047-02-06 | U113: 100% para CENTRAL EOLICA ANGICAL S/A - 14.570.783/0001-53 (PIE) | W113: Pindaí - BA
A114: 2026-10-01 | B114: Coqueirinho | C114: 030738 | D114: EOL.CV.BA.030738-6.1 | E114: BA | F114: EOL | G114: Operação | H114: Eólica | I114: Cinética do vento | J114: Autorização | K114: Cinética do vento | L114: 2016-02-17 | M114: 29600 | N114: 29600 | O114: 13500 | P114: Não | Q114: -14.419889 | R114: -42.62872 | S114: 2012-02-13 | T114: 2047-02-13 | U114: 100% para CENTRAL EOLICA COQUEIRINHO S/A - 14.570.819/0001-07 (PIE) | W114: Pindaí - BA
A115: 2026-10-01 | B115: Caititu | C115: 030739 | D115: EOL.CV.BA.030739-4.1 | E115: BA | F115: EOL | G115: Operação | H115: Eólica | I115: Cinética do vento | J115: Autorização | K115: Cinética do vento | L115: 2016-02-16 | M115: 22200 | N115: 22200 | O115: 10500 | P115: Não | Q115: -14.452802 | R115: -42.640996 | S115: 2012-02-13 | T115: 2047-02-13 | U115: 100% para CENTRAL EOLICA CAITITU S/A - 14.570.861/0001-10 (PIE) | W115: Pindaí - BA
A116: 2026-10-01 | B116: Inhambu | C116: 030751 | D116: EOL.CV.BA.030751-3.1 | E116: BA | F116: EOL | G116: Operação | H116: Eólica | I116: Cinética do vento | J116: Autorização | K116: Cinética do vento | L116: 2016-02-05 | M116: 31450 | N116: 31450 | O116: 15500 | P116: Não | Q116: -14.391171 | R116: -42.593854 | S116: 2012-02-23 | T116: 2047-02-23 | U116: 100% para CENTRAL EOLICA INHAMBU S/A - 14.572.367/0001-94 (PIE) | W116: Caetité - BA
...

Sheet ANEEL_INDGER
A1: ← LEIA-ME | B1: Unidades consumidoras ativas e indicadores comerciais por município e mês | C1: Origem: amostras/aneel_4.3_indger_comercial_BA_amostra.csv
A2: DatGeracaoConjuntoDados | B2: NumCNPJ | C2: SigAgente | D2: NomAgente | E2: NomTipoOutorga | F2: DatReferenciaInformada | G2: CodMunicipioIBGE | H2: QtdUCAtiva | I2: QtdUCAtivaFat | J2: QtdFatura | K2: QtdFaturaSemLeitura | L2: QtdFaturaSemLeituraImpAcesso | M2: QtdFaturaSemLeituraEmergencia | N2: QtdFaturaSemLeituraPlurimensa | O2: QtdFaturaSemLeituraFatEstimad | P2: QtdFaturaSemLeituraFimContrat | Q2: QtdFaturaSemLeituraAusenciaTm | R2: QtdRefaturamento | S2: QtdFaturaAcerto | T2: QtdFaturaAcertoFatIncorreto | U2: QtdFaturaAcertoFatIncorDevDob | V2: QtdFaturaAcertoFatIncorDevSEC | W2: QtdFaturaAcertoFatIncorDevSET | X2: QtdFaturaAcertoFatImpAcesso | Y2: QtdFaturaAcertoFatEmergencia | Z2: QtdFaturaSemLeituraFatMedia | AA2: QtdFaturaSemLeituraFatCustoDi | AB2: QtdFaturaComLeitura | AC2: QtdFaturaComAutoleitura | AD2: QtdConsComLeituraPlurimensal | AE2: QtdConsComAutoleitura | AF2: QtdRestAnteDist | AG2: QtdRestAtrasadoDist | AH2: QtdRestPendenteDist | AI2: QtdRestPendenteAtrasado | AJ2: VlrRestAnte | AK2: VlrRestAtrasado | AL2: VlrRestPendente | AM2: VlrRestPendenteAtrasado | AN2: QtdSolicRessarcimentoDano | AO2: QtdRessarcIndeferido | AP2: VlrPendentePgtRessarcDanoDefe | AQ2: VlrPagoRessarcDano | AR2: QtdUCSubstMedidor | AS2: QtdPostoAtendimento | AT2: QtdDiasNormal | AU2: QtdDiasCasoFortForcMaior | AV2: QtdAtendRealizPosto | AW2: QtdAtendRealizPostoDiaCasoFor | AX2: MdaTempoMedAtendimentoPosto | AY2: MdaTempoMedAtendPostoDiaFort | AZ2: QtdAtendRealizMais30MinDiaNor | BA2: QtdAtendRealizMais30MinDiaFor | BB2: QtdInspecVerifProcIrregular | BC2: QtdTermosOcorrInspecao | BD2: QtdTermosOcorrInspecaoCobr | BE2: QtdTermosOcorrInspecaoEncerr | BF2: QtdProceCobrDefMedidor | BG2: QtdReligCobr | BH2: QtdUCSuspInadimplemento | BI2: QtdSuspIndev | BJ2: VlrTotCompSuspIndevida | BK2: DthCarga
A3: 2026-09-16 | B3: 15139629000194 | C3: Neoenergia Coelba | D3: COMPANHIA DE ELETRICIDADE DO ESTADO DA BAHIA | E3: Concessão | F3: 2026-05-01 | G3: 2930774 | H3: 11557 | I3: 11282 | J3: 11192 | K3: 93 | L3: 8 | M3: 0 | N3: 0 | O3: 1 | P3: 19 | Q3: 65 | R3: 220 | S3: 20 | T3: 17 | U3: 16 | V3: 1 | W3: 0 | X3: 3 | Y3: 0 | Z3: 70 | AA3: 22 | AB3: 11099 | AC3: 0 | AD3: 0 | AE3: 0 | AF3: 0 | AG3: 0 | AH3: 0 | AI3: 0 | AN3: 2 | AO3: 0 | AP3: 0 | AQ3: 0 | AR3: 90 | AS3: 1 | AT3: 22 | AU3: 0 | AV3: 127 | AX3: 0.22 | AY3: 0 | BA3: 0 | BB3: 14 | BC3: 6 | BD3: 4 | BE3: 4 | BG3: 3 | BH3: 119 | BJ3: 0 | BK3: 2026-09-16 04:03:10.020000000
A4: 2026-09-16 | B4: 15139629000194 | C4: Neoenergia Coelba | D4: COMPANHIA DE ELETRICIDADE DO ESTADO DA BAHIA | E4: Concessão | F4: 2026-07-01 | G4: 2920304 | H4: 4749 | I4: 4621 | J4: 4634 | K4: 74 | L4: 31 | M4: 0 | N4: 0 | O4: 1 | P4: 22 | Q4: 20 | R4: 50 | S4: 48 | T4: 18 | U4: 18 | V4: 0 | W4: 0 | X4: 30 | Y4: 0 | Z4: 56 | AA4: 17 | AB4: 4560 | AC4: 0 | AD4: 0 | AE4: 0 | AF4: 0 | AG4: 0 | AH4: 0 | AI4: 0 | AN4: 0 | AO4: 0 | AP4: 0 | AQ4: 0 | AR4: 27 | AS4: 1 | AT4: 22 | AU4: 0 | AV4: 77 | AX4: 0.4 | AY4: 0 | BA4: 0 | BH4: 24 | BJ4: 0 | BK4: 2026-09-16 04:03:10.053000000
A5: 2026-09-16 | B5: 15139629000194 | C5: Neoenergia Coelba | D5: COMPANHIA DE ELETRICIDADE DO ESTADO DA BAHIA | E5: Concessão | F5: 2023-09-01 | G5: 2918555 | H5: 2542 | I5: 2503 | J5: 2523 | K5: 64 | L5: 29 | M5: 0 | N5: 0 | O5: 1 | P5: 26 | Q5: 8 | R5: 18 | S5: 17 | T5: 12 | U5: 12 | V5: 0 | W5: 0 | X5: 1 | Y5: 4 | Z5: 44 | AA5: 19 | AB5: 2459 | AC5: 0 | AD5: 0 | AE5: 0 | AF5: 0 | AG5: 0 | AH5: 0 | AI5: 0 | AN5: 1 | AO5: 0 | AP5: 0 | AQ5: 0 | AR5: 3 | AS5: 1 | AT5: 20 | AU5: 0 | AV5: 150 | AX5: 0.00165409 | AY5: 0 | BA5: 0 | BB5: 11 | BC5: 4 | BD5: 2 | BE5: 2 | BF5: 2 | BH5: 20 | BJ5: 0 | BK5: 2026-09-16 04:03:09.927000000
A6: 2026-09-16 | B6: 15139629000194 | C6: Neoenergia Coelba | D6: COMPANHIA DE ELETRICIDADE DO ESTADO DA BAHIA | E6: Concessão | F6: 2026-05-01 | G6: 2923407 | H6: 11427 | I6: 11095 | J6: 11008 | K6: 383 | L6: 293 | M6: 0 | N6: 0 | O6: 2 | P6: 30 | Q6: 58 | R6: 189 | S6: 221 | T6: 18 | U6: 17 | V6: 1 | W6: 0 | X6: 203 | Y6: 0 | Z6: 241 | AA6: 140 | AB6: 10624 | AC6: 1 | AD6: 0 | AE6: 1 | AF6: 0 | AG6: 0 | AH6: 0 | AI6: 0 | AN6: 0 | AO6: 3 | AP6: 0 | AQ6: 0 | AR6: 73 | AS6: 1 | AT6: 22 | AU6: 0 | AV6: 556 | AX6: 2.7 | AY6: 0 | BA6: 0 | BB6: 3 | BC6: 2 | BH6: 71 | BJ6: 0 | BK6: 2026-09-16 04:03:10.020000000
A7: 2026-09-16 | B7: 15139629000194 | C7: Neoenergia Coelba | D7: COMPANHIA DE ELETRICIDADE DO ESTADO DA BAHIA | E7: Concessão | F7: 2026-07-01 | G7: 2920205 | H7: 7191 | I7: 7001 | J7: 6908 | K7: 136 | L7: 48 | M7: 0 | N7: 0 | O7: 1 | P7: 42 | Q7: 45 | R7: 208 | S7: 77 | T7: 15 | U7: 14 | V7: 1 | W7: 0 | X7: 62 | Y7: 0 | Z7: 101 | AA7: 34 | AB7: 6772 | AC7: 0 | AD7: 0 | AE7: 0 | AF7: 0 | AG7: 0 | AH7: 0 | AI7: 0 | AN7: 0 | AO7: 0 | AP7: 0 | AQ7: 0 | AR7: 21 | AS7: 1 | AT7: 22 | AU7: 0 | AV7: 144 | AX7: 0.3 | AY7: 0 | BA7: 0 | BB7: 3 | BC7: 1 | BH7: 47 | BJ7: 0 | BK7: 2026-09-16 04:03:10.053000000
A8: 2026-09-16 | B8: 15139629000194 | C8: Neoenergia Coelba | D8: COMPANHIA DE ELETRICIDADE DO ESTADO DA BAHIA | E8: Concessão | F8: 2023-09-01 | G8: 2918506 | H8: 7809 | I8: 7622 | J8: 7671 | K8: 170 | L8: 93 | M8: 0 | N8: 0 | O8: 3 | P8: 42 | Q8: 32 | R8: 13 | S8: 35 | T8: 8 | U8: 6 | V8: 2 | W8: 0 | X8: 27 | Y8: 0 | Z8: 128 | AA8: 39 | AB8: 7501 | AC8: 0 | AD8: 0 | AE8: 0 | AF8: 0 | AG8: 0 | AH8: 0 | AI8: 0 | AN8: 0 | AO8: 0 | AP8: 0 | AQ8: 0 | AR8: 25 | AS8: 1 | AT8: 20 | AU8: 0 | AV8: 83 | AX8: 0.00248996 | AY8: 0 | BA8: 0 | BB8: 9 | BC8: 2 | BH8: 71 | BJ8: 0 | BK8: 2026-09-16 04:03:09.927000000
A9: 2026-09-16 | B9: 15139629000194 | C9: Neoenergia Coelba | D9: COMPANHIA DE ELETRICIDADE DO ESTADO DA BAHIA | E9: Concessão | F9: 2026-05-01 | G9: 2923506 | H9: 6286 | I9: 6106 | J9: 6062 | K9: 74 | L9: 41 | M9: 0 | N9: 0 | O9: 1 | P9: 14 | Q9: 18 | R9: 90 | S9: 46 | T9: 25 | U9: 18 | V9: 7 | W9: 0 | X9: 21 | Y9: 0 | Z9: 58 | AA9: 15 | AB9: 5988 | AC9: 0 | AD9: 0 | AE9: 0 | AF9: 0 | AG9: 0 | AH9: 0 | AI9: 0 | AN9: 1 | AO9: 1 | AP9: 0 | AQ9: 0 | AR9: 7 | AS9: 1 | AT9: 22 | AU9: 0 | AV9: 85 | AX9: 0.07 | AY9: 0 | BA9: 0 | BB9: 8 | BC9: 1 | BH9: 7 | BJ9: 0 | BK9: 2026-09-16 04:03:10.020000000
A10: 2026-09-16 | B10: 15139629000194 | C10: Neoenergia Coelba | D10: COMPANHIA DE ELETRICIDADE DO ESTADO DA BAHIA | E10: Concessão | F10: 2026-07-01 | G10: 2918803 | H10: 10711 | I10: 10456 | J10: 10492 | K10: 171 | L10: 7 | M10: 0 | N10: 0 | O10: 1 | P10: 84 | Q10: 79 | R10: 192 | S10: 43 | T10: 35 | U10: 10 | V10: 25 | W10: 0 | X10: 8 | Y10: 0 | Z10: 150 | AA10: 20 | AB10: 10321 | AC10: 0 | AD10: 0 | AE10: 0 | AF10: 0 | AG10: 0 | AH10: 0 | AI10: 0 | AN10: 2 | AO10: 4 | AP10: 0 | AQ10: 0 | AR10: 22 | AS10: 1 | AT10: 22 | AU10: 0 | AV10: 367 | AX10: 0.35 | AY10: 0 | BA10: 0 | BB10: 6 | BC10: 2 | BD10: 7 | BE10: 10 | BH10: 112 | BJ10: 0 | BK10: 2026-09-16 04:03:10.053000000
A11: 2026-09-16 | B11: 15139629000194 | C11: Neoenergia Coelba | D11: COMPANHIA DE ELETRICIDADE DO ESTADO DA BAHIA | E11: Concessão | F11: 2023-09-01 | G11: 2916302 | H11: 4264 | I11: 4227 | J11: 4232 | K11: 56 | L11: 7 | M11: 0 | N11: 0 | O11: 3 | P11: 36 | Q11: 10 | R11: 10 | S11: 22 | T11: 5 | U11: 5 | V11: 0 | W11: 0 | X11: 17 | Y11: 0 | Z11: 47 | AA11: 6 | AB11: 4176 | AC11: 0 | AD11: 0 | AE11: 0 | AF11: 0 | AG11: 0 | AH11: 0 | AI11: 0 | AN11: 1 | AO11: 0 | AP11: 0 | AQ11: 0 | AR11: 2 | AS11: 1 | AT11: 20 | AU11: 0 | AV11: 133 | AX11: 0.000664421 | AY11: 0 | BA11: 0 | BB11: 1 | BD11: 1 | BE11: 1 | BH11: 56 | BJ11: 0 | BK11: 2026-09-16 04:03:09.927000000
A12: 2026-09-16 | B12: 15139629000194 | C12: Neoenergia Coelba | D12: COMPANHIA DE ELETRICIDADE DO ESTADO DA BAHIA | E12: Concessão | F12: 2026-05-01 | G12: 2922409 | H12: 10584 | I12: 10320 | J12: 10338 | K12: 63 | L12: 1 | M12: 0 | N12: 0 | O12: 1 | P12: 28 | Q12: 33 | R12: 104 | S12: 15 | T12: 12 | U12: 10 | V12: 2 | W12: 0 | X12: 3 | Y12: 0 | Z12: 54 | AA12: 8 | AB12: 10275 | AC12: 0 | AD12: 0 | AE12: 0 | AF12: 0 | AG12: 0 | AH12: 0 | AI12: 0 | AN12: 8 | AO12: 4 | AP12: 2483 | AQ12: 3589 | AR12: 33 | AS12: 1 | AT12: 22 | AU12: 0 | AV12: 153 | AX12: 0.52 | AY12: 0 | BA12: 0 | BB12: 3 | BD12: 1 | BE12: 1 | BH12: 85 | BJ12: 0 | BK12: 2026-09-16 04:03:10.020000000
A13: 2026-09-16 | B13: 15139629000194 | C13: Neoenergia Coelba | D13: COMPANHIA DE ELETRICIDADE DO ESTADO DA BAHIA | E13: Concessão | F13: 2026-07-01 | G13: 2918704 | H13: 2502 | I13: 2428 | J13: 2421 | K13: 20 | L13: 0 | M13: 0 | N13: 0 | O13: 1 | P13: 9 | Q13: 10 | R13: 25 | S13: 2 | T13: 1 | U13: 1 | V13: 0 | W13: 0 | X13: 1 | Y13: 0 | Z13: 15 | AA13: 4 | AB13: 2401 | AC13: 0 | AD13: 0 | AE13: 0 | AF13: 0 | AG13: 0 | AH13: 0 | AI13: 0 | AN13: 0 | AO13: 0 | AP13: 0 | AQ13: 0 | AR13: 11 | AS13: 1 | AT13: 22 | AU13: 0 | AV13: 132 | AX13: 0.13 | AY13: 0 | BA13: 0 | BB13: 2 | BC13: 1 | BH13: 27 | BJ13: 0 | BK13: 2026-09-16 04:03:10.053000000
A14: 2026-09-16 | B14: 15139629000194 | C14: Neoenergia Coelba | D14: COMPANHIA DE ELETRICIDADE DO ESTADO DA BAHIA | E14: Concessão | F14: 2023-09-01 | G14: 2918456 | H14: 3448 | I14: 3404 | J14: 3446 | K14: 116 | L14: 46 | M14: 0 | N14: 0 | O14: 1 | P14: 48 | Q14: 21 | R14: 17 | S14: 38 | T14: 1 | U14: 1 | V14: 0 | W14: 0 | X14: 37 | Y14: 0 | Z14: 84 | AA14: 31 | AB14: 3330 | AC14: 0 | AD14: 0 | AE14: 0 | AF14: 0 | AG14: 0 | AH14: 0 | AI14: 0 | AN14: 0 | AO14: 0 | AP14: 0 | AQ14: 0 | AR14: 1 | AS14: 1 | AT14: 20 | AU14: 0 | AV14: 126 | AX14: 0.005267857 | AY14: 0 | BA14: 0 | BB14: 7 | BC14: 2 | BD14: 16 | BE14: 16 | BF14: 7 | BH14: 1 | BJ14: 0 | BK14: 2026-09-16 04:03:09.927000000
A15: 2026-09-16 | B15: 15139629000194 | C15: Neoenergia Coelba | D15: COMPANHIA DE ELETRICIDADE DO ESTADO DA BAHIA | E15: Concessão | F15: 2026-05-01 | G15: 2923605 | H15: 10273 | I15: 9977 | J15: 9838 | K15: 147 | L15: 34 | M15: 0 | N15: 0 | O15: 1 | P15: 36 | Q15: 76 | R15: 183 | S15: 64 | T15: 9 | U15: 5 | V15: 4 | W15: 0 | X15: 55 | Y15: 0 | Z15: 109 | AA15: 37 | AB15: 9691 | AC15: 0 | AD15: 0 | AE15: 0 | AF15: 0 | AG15: 0 | AH15: 0 | AI15: 0 | AN15: 1 | AO15: 1 | AP15: 0 | AQ15: 0 | AR15: 8 | AS15: 1 | AT15: 22 | AU15: 0 | AV15: 178 | AX15: 1.02 | AY15: 0 | BA15: 0 | BB15: 5 | BC15: 4 | BH15: 30 | BJ15: 0 | BK15: 2026-09-16 04:03:10.020000000
A16: 2026-09-16 | B16: 15139629000194 | C16: Neoenergia Coelba | D16: COMPANHIA DE ELETRICIDADE DO ESTADO DA BAHIA | E16: Concessão | F16: 2026-07-01 | G16: 2918605 | H16: 3656 | I16: 3586 | J16: 3598 | K16: 44 | L16: 2 | M16: 0 | N16: 0 | O16: 2 | P16: 10 | Q16: 30 | R16: 2 | S16: 4 | T16: 0 | U16: 0 | V16: 0 | W16: 0 | X16: 4 | Y16: 0 | Z16: 35 | AA16: 7 | AB16: 3554 | AC16: 0 | AD16: 0 | AE16: 0 | AF16: 0 | AG16: 0 | AH16: 0 | AI16: 0 | AN16: 0 | AO16: 0 | AP16: 0 | AQ16: 0 | AR16: 2 | AS16: 1 | AT16: 22 | AU16: 0 | AV16: 105 | AX16: 0.73 | AY16: 0 | BA16: 0 | BB16: 5 | BC16: 2 | BD16: 3 | BE16: 3 | BF16: 3 | BJ16: 0 | BK16: 2026-09-16 04:03:10.053000000
A17: 2026-09-16 | B17: 15139629000194 | C17: Neoenergia Coelba | D17: COMPANHIA DE ELETRICIDADE DO ESTADO DA BAHIA | E17: Concessão | F17: 2023-09-01 | G17: 2918357 | H17: 11149 | I17: 10935 | J17: 11003 | K17: 136 | L17: 27 | M17: 0 | N17: 0 | O17: 6 | P17: 64 | Q17: 39 | R17: 60 | S17: 38 | T17: 29 | U17: 26 | V17: 3 | W17: 0 | X17: 9 | Y17: 0 | Z17: 104 | AA17: 26 | AB17: 10866 | AC17: 1 | AD17: 0 | AE17: 1 | AF17: 2 | AG17: 2 | AH17: 0 | AI17: 0 | AJ17: 106130 | AK17: 106130 | AL17: 0 | AM17: 0 | AN17: 0 | AO17: 0 | AP17: 352.36 | AQ17: 0 | AR17: 21 | AS17: 1 | AT17: 20 | AU17: 0 | AV17: 36 | AX17: 0.002664931 | AY17: 0 | BA17: 0 | BB17: 13 | BC17: 2 | BD17: 11 | BE17: 12 | BF17: 1 | BH17: 88 | BJ17: 0 | BK17: 2026-09-16 04:03:09.927000000
A18: 2026-09-16 | B18: 15139629000194 | C18: Neoenergia Coelba | D18: COMPANHIA DE ELETRICIDADE DO ESTADO DA BAHIA | E18: Concessão | F18: 2026-05-01 | G18: 2923803 | H18: 13447 | I18: 13219 | J18: 13250 | K18: 105 | L18: 4 | M18: 0 | N18: 0 | O18: 1 | P18: 60 | Q18: 40 | R18: 58 | S18: 22 | T18: 10 | U18: 10 | V18: 0 | W18: 0 | X18: 12 | Y18: 0 | Z18: 89 | AA18: 15 | AB18: 13145 | AC18: 0 | AD18: 0 | AE18: 0 | AF18: 0 | AG18: 0 | AH18: 0 | AI18: 0 | AN18: 0 | AO18: 1 | AP18: 0 | AQ18: 0 | AR18: 35 | AS18: 1 | AT18: 22 | AU18: 0 | AV18: 178 | AX18: 0.55 | AY18: 0 | BA18: 0 | BH18: 10 | BJ18: 0 | BK18: 2026-09-16 04:03:10.020000000
A19: 2026-09-16 | B19: 15139629000194 | C19: Neoenergia Coelba | D19: COMPANHIA DE ELETRICIDADE DO ESTADO DA BAHIA | E19: Concessão | F19: 2026-07-01 | G19: 2918555 | H19: 2702 | I19: 2640 | J19: 2636 | K19: 132 | L19: 102 | M19: 0 | N19: 0 | O19: 1 | P19: 23 | Q19: 6 | R19: 74 | S19: 129 | T19: 14 | U19: 13 | V19: 1 | W19: 0 | X19: 109 | Y19: 6 | Z19: 97 | AA19: 34 | AB19: 2504 | AC19: 0 | AD19: 0 | AE19: 0 | AF19: 0 | AG19: 0 | AH19: 0 | AI19: 0 | AN19: 1 | AO19: 1 | AP19: 0 | AQ19: 1400 | AR19: 10 | AS19: 1 | AT19: 22 | AU19: 0 | AV19: 96 | AX19: 0.2 | AY19: 0 | BA19: 0 | BH19: 26 | BJ19: 0 | BK19: 2026-09-16 04:03:10.053000000
A20: 2026-09-16 | B20: 15139629000194 | C20: Neoenergia Coelba | D20: COMPANHIA DE ELETRICIDADE DO ESTADO DA BAHIA | E20: Concessão | F20: 2023-09-01 | G20: 2918308 | H20: 6062 | I20: 5974 | J20: 5985 | K20: 62 | L20: 6 | M20: 0 | N20: 0 | O20: 1 | P20: 35 | Q20: 20 | R20: 16 | S20: 22 | T20: 10 | U20: 10 | V20: 0 | W20: 0 | X20: 12 | Y20: 0 | Z20: 49 | AA20: 12 | AB20: 5923 | AC20: 0 | AD20: 0 | AE20: 0 | AF20: 0 | AG20: 0 | AH20: 0 | AI20: 0 | AN20: 1 | AO20: 0 | AP20: 0 | AQ20: 0 | AR20: 15 | AS20: 1 | AT20: 20 | AU20: 0 | AV20: 180 | AX20: 0.002501479 | AY20: 0 | BA20: 0 | BD20: 1 | BE20: 1 | BH20: 86 | BJ20: 0 | BK20: 2026-09-16 04:03:09.927000000
A21: 2026-09-16 | B21: 15139629000194 | C21: Neoenergia Coelba | D21: COMPANHIA DE ELETRICIDADE DO ESTADO DA BAHIA | E21: Concessão | F21: 2026-05-01 | G21: 2923902 | H21: 4112 | I21: 4032 | J21: 3976 | K21: 151 | L21: 11 | M21: 55 | N21: 0 | O21: 1 | P21: 0 | Q21: 84 | R21: 21 | S21: 26 | T21: 2 | U21: 2 | V21: 0 | W21: 0 | X21: 5 | Y21: 19 | Z21: 117 | AA21: 33 | AB21: 3825 | AC21: 0 | AD21: 0 | AE21: 0 | AF21: 0 | AG21: 0 | AH21: 0 | AI21: 0 | AN21: 1 | AO21: 2 | AP21: 0 | AQ21: 570 | AR21: 12 | AS21: 1 | AT21: 22 | AU21: 0 | AV21: 36 | AX21: 2.85 | AY21: 0 | BA21: 0 | BE21: 1 | BH21: 35 | BJ21: 0 | BK21: 2026-09-16 04:03:10.020000000
A22: 2026-09-16 | B22: 15139629000194 | C22: Neoenergia Coelba | D22: COMPANHIA DE ELETRICIDADE DO ESTADO DA BAHIA | E22: Concessão | F22: 2026-07-01 | G22: 2930709 | H22: 49717 | I22: 48894 | J22: 48841 | K22: 1916 | L22: 5 | M22: 0 | N22: 0 | O22: 5 | P22: 603 | Q22: 1303 | R22: 1481 | S22: 153 | T22: 153 | U22: 136 | V22: 17 | W22: 0 | X22: 0 | Y22: 0 | Z22: 1281 | AA22: 630 | AB22: 46925 | AC22: 0 | AD22: 0 | AE22: 0 | AF22: 0 | AG22: 0 | AH22: 0 | AI22: 0 | AN22: 20 | AO22: 15 | AP22: 16246.91 | AQ22: 37335.33 | AR22: 818 | AS22: 1 | AT22: 22 | AU22: 0 | AV22: 1102 | AX22: 0.73 | AY22: 0 | BA22: 0 | BB22: 10 | BC22: 6 | BE22: 3 | BH22: 883 | BJ22: 0 | BK22: 2026-09-16 04:03:10.053000000
A23: 2026-09-16 | B23: 15139629000194 | C23: Neoenergia Coelba | D23: COMPANHIA DE ELETRICIDADE DO ESTADO DA BAHIA | E23: Concessão | F23: 2023-09-01 | G23: 2918209 | H23: 6230 | I23: 6028 | J23: 6068 | K23: 54 | L23: 0 | M23: 0 | N23: 0 | O23: 1 | P23: 31 | Q23: 22 | R23: 26 | S23: 6 | T23: 6 | U23: 6 | V23: 0 | W23: 0 | X23: 0 | Y23: 0 | Z23: 43 | AA23: 10 | AB23: 6014 | AC23: 0 | AD23: 0 | AE23: 0 | AF23: 0 | AG23: 0 | AH23: 0 | AI23: 0 | AN23: 1 | AO23: 0 | AP23: 0 | AQ23: 1500 | AR23: 9 | AS23: 1 | AT23: 20 | AU23: 0 | AV23: 321 | AX23: 0.001414922 | AY23: 0 | BA23: 0 | BB23: 3 | BC23: 2 | BD23: 4 | BE23: 4 | BF23: 2 | BH23: 15 | BJ23: 0 | BK23: 2026-09-16 04:03:09.927000000
A24: 2026-09-16 | B24: 15139629000194 | C24: Neoenergia Coelba | D24: COMPANHIA DE ELETRICIDADE DO ESTADO DA BAHIA | E24: Concessão | F24: 2026-05-01 | G24: 2924009 | H24: 50800 | I24: 49850 | J24: 49716 | K24: 466 | L24: 147 | M24: 0 | N24: 0 | O24: 2 | P24: 51 | Q24: 266 | R24: 1285 | S24: 125 | T24: 93 | U24: 70 | V24: 23 | W24: 0 | X24: 32 | Y24: 0 | Z24: 384 | AA24: 80 | AB24: 49247 | AC24: 3 | AD24: 0 | AE24: 3 | AF24: 0 | AG24: 0 | AH24: 0 | AI24: 0 | AN24: 8 | AO24: 13 | AP24: 0 | AQ24: 2127 | AR24: 341 | AS24: 1 | AT24: 22 | AU24: 0 | AV24: 2460 | AX24: 5.65 | AY24: 0 | BA24: 0 | BB24: 48 | BC24: 26 | BD24: 58 | BE24: 68 | BF24: 33 | BH24: 691 | BJ24: 0 | BK24: 2026-09-16 04:03:10.020000000
A25: 2026-09-16 | B25: 15139629000194 | C25: Neoenergia Coelba | D25: COMPANHIA DE ELETRICIDADE DO ESTADO DA BAHIA | E25: Concessão | F25: 2026-07-01 | G25: 2930600 | H25: 7592 | I25: 7442 | J25: 7465 | K25: 46 | L25: 4 | M25: 0 | N25: 0 | O25: 1 | P25: 17 | Q25: 24 | R25: 70 | S25: 14 | T25: 9 | U25: 8 | V25: 1 | W25: 0 | X25: 5 | Y25: 0 | Z25: 39 | AA25: 6 | AB25: 7419 | AC25: 0 | AD25: 0 | AE25: 0 | AF25: 0 | AG25: 0 | AH25: 0 | AI25: 0 | AN25: 1 | AO25: 3 | AP25: 0 | AQ25: 0 | AR25: 11 | AS25: 1 | AT25: 22 | AU25: 0 | AV25: 240 | AX25: 0.68 | AY25: 0 | BA25: 0 | BB25: 4 | BE25: 1 | BH25: 65 | BJ25: 0 | BK25: 2026-09-16 04:03:10.053000000
A26: 2026-09-16 | B26: 15139629000194 | C26: Neoenergia Coelba | D26: COMPANHIA DE ELETRICIDADE DO ESTADO DA BAHIA | E26: Concessão | F26: 2023-09-01 | G26: 2918100 | H26: 17385 | I26: 17159 | J26: 17190 | K26: 349 | L26: 113 | M26: 0 | N26: 0 | O26: 2 | P26: 151 | Q26: 83 | R26: 68 | S26: 117 | T26: 14 | U26: 14 | V26: 0 | W26: 0 | X26: 103 | Y26: 0 | Z26: 264 | AA26: 83 | AB26: 16841 | AC26: 0 | AD26: 0 | AE26: 0 | AF26: 0 | AG26: 0 | AH26: 0 | AI26: 0 | AN26: 0 | AO26: 0 | AP26: 0 | AQ26: 0 | AR26: 23 | AS26: 1 | AT26: 20 | AU26: 0 | AV26: 299 | AX26: 0.002445536 | AY26: 0 | BA26: 0 | BB26: 17 | BC26: 3 | BD26: 2 | BE26: 2 | BF26: 2 | BH26: 71 | BJ26: 0 | BK26: 2026-09-16 04:03:09.927000000
A27: 2026-09-16 | B27: 15139629000194 | C27: Neoenergia Coelba | D27: COMPANHIA DE ELETRICIDADE DO ESTADO DA BAHIA | E27: Concessão | F27: 2026-05-01 | G27: 2924058 | H27: 6083 | I27: 5976 | J27: 5970 | K27: 63 | L27: 0 | M27: 0 | N27: 0 | O27: 1 | P27: 20 | Q27: 42 | R27: 65 | S27: 15 | T27: 14 | U27: 14 | V27: 0 | W27: 0 | X27: 1 | Y27: 0 | Z27: 52 | AA27: 10 | AB27: 5907 | AC27: 0 | AD27: 0 | AE27: 0 | AF27: 0 | AG27: 0 | AH27: 0 | AI27: 0 | AN27: 1 | AO27: 1 | AP27: 0 | AQ27: 0 | AR27: 5 | AS27: 1 | AT27: 22 | AU27: 0 | AV27: 228 | AX27: 0.88 | AY27: 0 | BA27: 0 | BB27: 3 | BH27: 14 | BJ27: 0 | BK27: 2026-09-16 04:03:10.020000000
A28: 2026-09-16 | B28: 15139629000194 | C28: Neoenergia Coelba | D28: COMPANHIA DE ELETRICIDADE DO ESTADO DA BAHIA | E28: Concessão | F28: 2026-07-01 | G28: 2930501 | H28: 44798 | I28: 43724 | J28: 43729 | K28: 465 | L28: 13 | M28: 0 | N28: 0 | O28: 3 | P28: 189 | Q28: 260 | R28: 1482 | S28: 378 | T28: 367 | U28: 367 | V28: 0 | W28: 0 | X28: 11 | Y28: 0 | Z28: 393 | AA28: 69 | AB28: 43264 | AC28: 0 | AD28: 0 | AE28: 0 | AF28: 0 | AG28: 0 | AH28: 0 | AI28: 0 | AN28: 19 | AO28: 9 | AP28: 2576.1 | AQ28: 2037 | AR28: 127 | AS28: 1 | AT28: 22 | AU28: 0 | AV28: 882 | AX28: 1.5 | AY28: 0 | BA28: 0 | BB28: 10 | BC28: 9 | BD28: 11 | BE28: 15 | BF28: 5 | BH28: 273 | BI28: 1 | BJ28: 0 | BK28: 2026-09-16 04:03:10.053000000
A29: 2026-09-16 | B29: 15139629000194 | C29: Neoenergia Coelba | D29: COMPANHIA DE ELETRICIDADE DO ESTADO DA BAHIA | E29: Concessão | F29: 2023-09-01 | G29: 2915809 | H29: 9032 | I29: 8943 | J29: 8878 | K29: 51 | L29: 0 | M29: 0 | N29: 0 | O29: 1 | P29: 34 | Q29: 16 | R29: 51 | S29: 27 | T29: 27 | U29: 27 | V29: 0 | W29: 0 | X29: 0 | Y29: 0 | Z29: 38 | AA29: 12 | AB29: 8827 | AC29: 0 | AD29: 0 | AE29: 0 | AF29: 0 | AG29: 0 | AH29: 0 | AI29: 0 | AN29: 1 | AO29: 1 | AP29: 0 | AQ29: 0 | AR29: 36 | AS29: 1 | AT29: 20 | AU29: 0 | AV29: 73 | AX29: 0.008876681 | AY29: 0 | BA29: 0 | BB29: 12 | BD29: 5 | BE29: 5 | BF29: 3 | BH29: 136 | BJ29: 0 | BK29: 2026-09-16 04:03:09.927000000
A30: 2026-09-16 | B30: 15139629000194 | C30: Neoenergia Coelba | D30: COMPANHIA DE ELETRICIDADE DO ESTADO DA BAHIA | E30: Concessão | F30: 2026-05-01 | G30: 2924108 | H30: 3263 | I30: 3210 | J30: 3196 | K30: 34 | L30: 0 | M30: 0 | N30: 0 | O30: 1 | P30: 16 | Q30: 17 | R30: 49 | S30: 10 | T30: 10 | U30: 10 | V30: 0 | W30: 0 | X30: 0 | Y30: 0 | Z30: 28 | AA30: 5 | AB30: 3162 | AC30: 0 | AD30: 0 | AE30: 0 | AF30: 0 | AG30: 0 | AH30: 0 | AI30: 0 | AN30: 0 | AO30: 0 | AP30: 0 | AQ30: 0 | AR30: 7 | AS30: 1 | AT30: 22 | AU30: 0 | AV30: 103 | AX30: 0.05 | AY30: 0 | BA30: 0 | BH30: 20 | BJ30: 0 | BK30: 2026-09-16 04:03:10.020000000
A31: 2026-09-16 | B31: 15139629000194 | C31: Neoenergia Coelba | D31: COMPANHIA DE ELETRICIDADE DO ESTADO DA BAHIA | E31: Concessão | F31: 2026-07-01 | G31: 2930402 | H31: 7892 | I31: 7735 | J31: 7749 | K31: 144 | L31: 20 | M31: 0 | N31: 0 | O31: 1 | P31: 60 | Q31: 63 | R31: 37 | S31: 18 | T31: 1 | U31: 0 | V31: 1 | W31: 0 | X31: 17 | Y31: 0 | Z31: 117 | AA31: 26 | AB31: 7605 | AC31: 0 | AD31: 0 | AE31: 0 | AF31: 0 | AG31: 0 | AH31: 0 | AI31: 0 | AN31: 2 | AO31: 2 | AP31: 0 | AQ31: 0 | AR31: 14 | AS31: 1 | AT31: 22 | AU31: 0 | AV31: 215 | AX31: 0.6 | AY31: 0 | BA31: 0 | BB31: 3 | BD31: 3 | BE31: 3 | BH31: 13 | BJ31: 0 | BK31: 2026-09-16 04:03:10.053000000
A32: 2026-09-16 | B32: 15139629000194 | C32: Neoenergia Coelba | D32: COMPANHIA DE ELETRICIDADE DO ESTADO DA BAHIA | E32: Concessão | F32: 2023-09-01 | G32: 2915908 | H32: 2863 | I32: 2805 | J32: 2826 | K32: 39 | L32: 0 | M32: 0 | N32: 0 | O32: 2 | P32: 22 | Q32: 15 | R32: 13 | S32: 7 | T32: 6 | U32: 6 | V32: 0 | W32: 0 | X32: 1 | Y32: 0 | Z32: 33 | AA32: 4 | AB32: 2786 | AC32: 1 | AD32: 0 | AE32: 1 | AF32: 0 | AG32: 0 | AH32: 0 | AI32: 0 | AN32: 1 | AO32: 0 | AP32: 0 | AQ32: 0 | AR32: 7 | AS32: 1 | AT32: 20 | AU32: 0 | AV32: 112 | AX32: 0.003935289 | AY32: 0 | BA32: 0 | BB32: 8 | BC32: 3 | BD32: 1 | BE32: 1 | BH32: 26 | BJ32: 0 | BK32: 2026-09-16 04:03:09.927000000
A33: 2026-09-16 | B33: 15139629000194 | C33: Neoenergia Coelba | D33: COMPANHIA DE ELETRICIDADE DO ESTADO DA BAHIA | E33: Concessão | F33: 2026-05-01 | G33: 2922102 | H33: 9859 | I33: 9716 | J33: 9694 | K33: 158 | L33: 31 | M33: 0 | N33: 0 | O33: 1 | P33: 53 | Q33: 73 | R33: 85 | S33: 25 | T33: 7 | U33: 7 | V33: 0 | W33: 0 | X33: 18 | Y33: 0 | Z33: 117 | AA33: 40 | AB33: 9536 | AC33: 0 | AD33: 0 | AE33: 0 | AF33: 0 | AG33: 0 | AH33: 0 | AI33: 0 | AN33: 0 | AO33: 0 | AP33: 0 | AQ33: 0 | AR33: 18 | AS33: 1 | AT33: 22 | AU33: 0 | AV33: 208 | AX33: 0.55 | AY33: 0 | BA33: 0 | BH33: 68 | BJ33: 0 | BK33: 2026-09-16 04:03:10.020000000
A34: 2026-09-16 | B34: 15139629000194 | C34: Neoenergia Coelba | D34: COMPANHIA DE ELETRICIDADE DO ESTADO DA BAHIA | E34: Concessão | F34: 2026-07-01 | G34: 2930303 | H34: 8287 | I34: 8127 | J34: 8134 | K34: 148 | L34: 35 | M34: 0 | N34: 0 | O34: 2 | P34: 28 | Q34: 83 | R34: 22 | S34: 19 | T34: 0 | U34: 0 | V34: 0 | W34: 0 | X34: 19 | Y34: 0 | Z34: 111 | AA34: 35 | AB34: 7986 | AC34: 0 | AD34: 0 | AE34: 0 | AF34: 0 | AG34: 0 | AH34: 0 | AI34: 0 | AN34: 0 | AO34: 0 | AP34: 0 | AQ34: 0 | AR34: 12 | AS34: 1 | AT34: 22 | AU34: 0 | AV34: 297 | AX34: 0.43 | AY34: 0 | BA34: 0 | BB34: 3 | BH34: 36 | BJ34: 0 | BK34: 2026-09-16 04:03:10.053000000
A35: 2026-09-16 | B35: 15139629000194 | C35: Neoenergia Coelba | D35: COMPANHIA DE ELETRICIDADE DO ESTADO DA BAHIA | E35: Concessão | F35: 2023-09-01 | G35: 2916005 | H35: 9043 | I35: 8948 | J35: 9028 | K35: 246 | L35: 42 | M35: 0 | N35: 0 | O35: 1 | P35: 151 | Q35: 52 | R35: 61 | S35: 194 | T35: 35 | U35: 32 | V35: 3 | W35: 0 | X35: 159 | Y35: 0 | Z35: 181 | AA35: 64 | AB35: 8782 | AC35: 0 | AD35: 0 | AE35: 0 | AF35: 0 | AG35: 0 | AH35: 0 | AI35: 0 | AN35: 0 | AO35: 0 | AP35: 0 | AQ35: 0 | AR35: 12 | AS35: 1 | AT35: 20 | AU35: 0 | AV35: 97 | AX35: 0.001781811 | AY35: 0 | BA35: 0 | BB35: 19 | BC35: 2 | BD35: 8 | BE35: 11 | BF35: 5 | BH35: 43 | BJ35: 0 | BK35: 2026-09-16 04:03:09.927000000
A36: 2026-09-16 | B36: 15139629000194 | C36: Neoenergia Coelba | D36: COMPANHIA DE ELETRICIDADE DO ESTADO DA BAHIA | E36: Concessão | F36: 2026-05-01 | G36: 2922201 | H36: 3746 | I36: 3666 | J36: 3670 | K36: 31 | L36: 0 | M36: 0 | N36: 0 | O36: 1 | P36: 10 | Q36: 20 | R36: 24 | S36: 2 | T36: 2 | U36: 1 | V36: 1 | W36: 0 | X36: 0 | Y36: 0 | Z36: 21 | AA36: 9 | AB36: 3639 | AC36: 0 | AD36: 0 | AE36: 0 | AF36: 0 | AG36: 0 | AH36: 0 | AI36: 0 | AN36: 1 | AO36: 1 | AP36: 0 | AQ36: 0 | AR36: 11 | AS36: 1 | AT36: 22 | AU36: 0 | AV36: 43 | AX36: 1.28 | AY36: 0 | BA36: 0 | BH36: 11 | BJ36: 0 | BK36: 2026-09-16 04:03:10.020000000
A37: 2026-09-16 | B37: 15139629000194 | C37: Neoenergia Coelba | D37: COMPANHIA DE ELETRICIDADE DO ESTADO DA BAHIA | E37: Concessão | F37: 2026-07-01 | G37: 2930154 | H37: 16957 | I37: 16451 | J37: 16427 | K37: 556 | L37: 297 | M37: 0 | N37: 0 | O37: 1 | P37: 141 | Q37: 117 | R37: 516 | S37: 284 | T37: 66 | U37: 55 | V37: 11 | W37: 0 | X37: 218 | Y37: 0 | Z37: 419 | AA37: 136 | AB37: 15871 | AC37: 0 | AD37: 0 | AE37: 0 | AF37: 0 | AG37: 0 | AH37: 0 | AI37: 0 | AN37: 0 | AO37: 0 | AP37: 0 | AQ37: 0 | AR37: 106 | AS37: 1 | AT37: 22 | AU37: 0 | AV37: 327 | AX37: 0.13 | AY37: 0 | BA37: 0 | BB37: 28 | BC37: 8 | BD37: 3 | BE37: 3 | BH37: 205 | BJ37: 0 | BK37: 2026-09-16 04:03:10.053000000
A38: 2026-09-16 | B38: 15139629000194 | C38: Neoenergia Coelba | D38: COMPANHIA DE ELETRICIDADE DO ESTADO DA BAHIA | E38: Concessão | F38: 2023-09-01 | G38: 2916104 | H38: 11676 | I38: 11531 | J38: 11580 | K38: 165 | L38: 8 | M38: 0 | N38: 0 | O38: 1 | P38: 61 | Q38: 95 | R38: 62 | S38: 25 | T38: 19 | U38: 19 | V38: 0 | W38: 0 | X38: 6 | Y38: 0 | Z38: 128 | AA38: 36 | AB38: 11415 | AC38: 0 | AD38: 0 | AE38: 0 | AF38: 0 | AG38: 0 | AH38: 0 | AI38: 0 | AN38: 2 | AO38: 3 | AP38: 0 | AQ38: 5858 | AR38: 18 | AS38: 1 | AT38: 20 | AU38: 0 | AV38: 184 | AX38: 0.003709868 | AY38: 0 | BA38: 0 | BB38: 22 | BC38: 2 | BD38: 16 | BE38: 16 | BF38: 11 | BH38: 281 | BJ38: 0 | BK38: 2026-09-16 04:03:09.927000000
A39: 2026-09-16 | B39: 15139629000194 | C39: Neoenergia Coelba | D39: COMPANHIA DE ELETRICIDADE DO ESTADO DA BAHIA | E39: Concessão | F39: 2026-05-01 | G39: 2922250 | H39: 5019 | I39: 4925 | J39: 4872 | K39: 87 | L39: 4 | M39: 0 | N39: 0 | O39: 1 | P39: 19 | Q39: 63 | R39: 97 | S39: 10 | T39: 5 | U39: 5 | V39: 0 | W39: 0 | X39: 5 | Y39: 0 | Z39: 64 | AA39: 22 | AB39: 4785 | AC39: 0 | AD39: 0 | AE39: 0 | AF39: 0 | AG39: 0 | AH39: 0 | AI39: 0 | AN39: 0 | AO39: 0 | AP39: 0 | AQ39: 0 | AR39: 10 | AS39: 1 | AT39: 22 | AU39: 0 | AV39: 118 | AX39: 0.28 | AY39: 0 | BA39: 0 | BH39: 30 | BJ39: 0 | BK39: 2026-09-16 04:03:10.020000000
A40: 2026-09-16 | B40: 15139629000194 | C40: Neoenergia Coelba | D40: COMPANHIA DE ELETRICIDADE DO ESTADO DA BAHIA | E40: Concessão | F40: 2026-07-01 | G40: 2930204 | H40: 12566 | I40: 12277 | J40: 12100 | K40: 201 | L40: 32 | M40: 0 | N40: 0 | O40: 1 | P40: 53 | Q40: 115 | R40: 221 | S40: 33 | T40: 13 | U40: 7 | V40: 6 | W40: 0 | X40: 20 | Y40: 0 | Z40: 172 | AA40: 28 | AB40: 11899 | AC40: 0 | AD40: 0 | AE40: 0 | AF40: 0 | AG40: 0 | AH40: 0 | AI40: 0 | AN40: 1 | AO40: 1 | AP40: 0 | AQ40: 1250 | AR40: 62 | AS40: 1 | AT40: 22 | AU40: 0 | AV40: 550 | AX40: 0.72 | AY40: 0 | BA40: 0 | BB40: 1 | BC40: 1 | BH40: 179 | BJ40: 0 | BK40: 2026-09-16 04:03:10.053000000
A41: 2026-09-16 | B41: 15139629000194 | C41: Neoenergia Coelba | D41: COMPANHIA DE ELETRICIDADE DO ESTADO DA BAHIA | E41: Concessão | F41: 2023-09-01 | G41: 2918407 | H41: 101276 | I41: 99321 | J41: 99669 | K41: 1202 | L41: 355 | M41: 0 | N41: 0 | O41: 11 | P41: 433 | Q41: 403 | R41: 571 | S41: 378 | T41: 178 | U41: 171 | V41: 7 | W41: 0 | X41: 200 | Y41: 0 | Z41: 1029 | AA41: 162 | AB41: 98467 | AC41: 0 | AD41: 0 | AE41: 0 | AF41: 0 | AG41: 0 | AH41: 0 | AI41: 0 | AN41: 34 | AO41: 17 | AP41: 6736.46 | AQ41: 12710.28 | AR41: 872 | AS41: 2 | AT41: 20 | AU41: 0 | AV41: 2723 | AX41: 0.007363143 | AY41: 0 | BA41: 0 | BB41: 445 | BC41: 121 | BD41: 202 | BE41: 217 | BF41: 51 | BG41: 2 | BH41: 892 | BJ41: 0 | BK41: 2026-09-16 04:03:09.927000000
A42: 2026-09-16 | B42: 15139629000194 | C42: Neoenergia Coelba | D42: COMPANHIA DE ELETRICIDADE DO ESTADO DA BAHIA | E42: Concessão | F42: 2026-05-01 | G42: 2923704 | H42: 12992 | I42: 12725 | J42: 12704 | K42: 103 | L42: 24 | M42: 0 | N42: 0 | O42: 1 | P42: 11 | Q42: 67 | R42: 64 | S42: 33 | T42: 3 | U42: 3 | V42: 0 | W42: 0 | X42: 30 | Y42: 0 | Z42: 74 | AA42: 28 | AB42: 12601 | AC42: 0 | AD42: 0 | AE42: 0 | AF42: 0 | AG42: 0 | AH42: 0 | AI42: 0 | AN42: 0 | AO42: 0 | AP42: 0 | AQ42: 0 | AR42: 8 | AS42: 1 | AT42: 22 | AU42: 0 | AV42: 238 | AX42: 0.1 | AY42: 0 | BA42: 0 | BB42: 1 | BC42: 1 | BE42: 1 | BH42: 73 | BJ42: 0 | BK42: 2026-09-16 04:03:10.020000000
A43: 2026-09-16 | B43: 15139629000194 | C43: Neoenergia Coelba | D43: COMPANHIA DE ELETRICIDADE DO ESTADO DA BAHIA | E43: Concessão | F43: 2026-07-01 | G43: 2930105 | H43: 39598 | I43: 38657 | J43: 38645 | K43: 347 | L43: 63 | M43: 0 | N43: 0 | O43: 3 | P43: 154 | Q43: 127 | R43: 834 | S43: 84 | T43: 22 | U43: 22 | V43: 0 | W43: 0 | X43: 62 | Y43: 0 | Z43: 268 | AA43: 76 | AB43: 38298 | AC43: 0 | AD43: 0 | AE43: 0 | AF43: 0 | AG43: 0 | AH43: 0 | AI43: 0 | AN43: 4 | AO43: 2 | AP43: 0 | AQ43: 0 | AR43: 169 | AS43: 1 | AT43: 22 | AU43: 0 | AV43: 1350 | AX43: 0.18 | AY43: 0 | BA43: 0 | BE43: 2 | BH43: 471 | BJ43: 0 | BK43: 2026-09-16 04:03:10.053000000
A44: 2026-09-16 | B44: 15139629000194 | C44: Neoenergia Coelba | D44: COMPANHIA DE ELETRICIDADE DO ESTADO DA BAHIA | E44: Concessão | F44: 2023-08-01 | G44: 2912400 | H44: 8149 | I44: 7944 | J44: 8005 | K44: 179 | L44: 47 | M44: 0 | N44: 0 | O44: 1 | P44: 101 | Q44: 30 | R44: 57 | S44: 46 | T44: 24 | U44: 18 | V44: 6 | W44: 0 | X44: 22 | Y44: 0 | Z44: 130 | AA44: 48 | AB44: 7824 | AC44: 2 | AD44: 0 | AE44: 2 | AF44: 0 | AG44: 0 | AH44: 0 | AI44: 0 | AN44: 1 | AO44: 0 | AP44: 0 | AQ44: 0 | AR44: 18 | AS44: 1 | AT44: 23 | AU44: 0 | AV44: 46 | AX44: 2.42 | AY44: 0 | BA44: 0 | BB44: 13 | BC44: 2 | BD44: 3 | BE44: 3 | BF44: 3 | BH44: 79 | BJ44: 0 | BK44: 2026-09-16 04:03:09.927000000
A45: 2026-09-16 | B45: 15139629000194 | C45: Neoenergia Coelba | D45: COMPANHIA DE ELETRICIDADE DO ESTADO DA BAHIA | E45: Concessão | F45: 2026-05-01 | G45: 2931202 | H45: 7692 | I45: 7535 | J45: 7462 | K45: 338 | L45: 188 | M45: 0 | N45: 0 | O45: 1 | P45: 105 | Q45: 44 | R45: 190 | S45: 120 | T45: 9 | U45: 2 | V45: 7 | W45: 0 | X45: 111 | Y45: 0 | Z45: 259 | AA45: 78 | AB45: 7124 | AC45: 0 | AD45: 0 | AE45: 0 | AF45: 0 | AG45: 0 | AH45: 0 | AI45: 0 | AN45: 3 | AO45: 2 | AP45: 0 | AQ45: 0 | AR45: 14 | AS45: 1 | AT45: 22 | AU45: 0 | AV45: 91 | AX45: 0.55 | AY45: 0 | BA45: 0 | BB45: 2 | BC45: 2 | BH45: 154 | BJ45: 0 | BK45: 2026-09-16 04:03:10.020000000
A46: 2026-09-16 | B46: 15139629000194 | C46: Neoenergia Coelba | D46: COMPANHIA DE ELETRICIDADE DO ESTADO DA BAHIA | E46: Concessão | F46: 2026-07-01 | G46: 2930006 | H46: 5041 | I46: 4898 | J46: 4892 | K46: 369 | L46: 161 | M46: 0 | N46: 0 | O46: 1 | P46: 111 | Q46: 96 | R46: 83 | S46: 63 | T46: 7 | U46: 7 | V46: 0 | W46: 0 | X46: 56 | Y46: 0 | Z46: 215 | AA46: 153 | AB46: 4523 | AC46: 0 | AD46: 0 | AE46: 0 | AF46: 0 | AG46: 0 | AH46: 0 | AI46: 0 | AN46: 1 | AO46: 1 | AP46: 0 | AQ46: 0 | AR46: 11 | AS46: 1 | AT46: 22 | AU46: 0 | AV46: 89 | AX46: 0.92 | AY46: 0 | BA46: 0 | BB46: 13 | BC46: 2 | BH46: 6 | BJ46: 0 | BK46: 2026-09-16 04:03:10.053000000
A47: 2026-09-16 | B47: 15139629000194 | C47: Neoenergia Coelba | D47: COMPANHIA DE ELETRICIDADE DO ESTADO DA BAHIA | E47: Concessão | F47: 2023-08-01 | G47: 2912301 | H47: 6977 | I47: 6817 | J47: 6853 | K47: 70 | L47: 34 | M47: 5 | N47: 0 | O47: 1 | P47: 15 | Q47: 15 | R47: 8 | S47: 35 | T47: 7 | U47: 6 | V47: 1 | W47: 0 | X47: 28 | Y47: 0 | Z47: 50 | AA47: 19 | AB47: 6783 | AC47: 0 | AD47: 0 | AE47: 0 | AF47: 0 | AG47: 0 | AH47: 0 | AI47: 0 | AN47: 1 | AO47: 1 | AP47: 0 | AQ47: 0 | AR47: 47 | AS47: 1 | AT47: 23 | AU47: 0 | AV47: 183 | AX47: 6.28 | AY47: 0 | BA47: 0 | BB47: 11 | BC47: 2 | BD47: 4 | BE47: 7 | BF47: 4 | BH47: 89 | BJ47: 0 | BK47: 2026-09-16 04:03:09.927000000
A48: 2026-09-16 | B48: 15139629000194 | C48: Neoenergia Coelba | D48: COMPANHIA DE ELETRICIDADE DO ESTADO DA BAHIA | E48: Concessão | F48: 2026-05-01 | G48: 2931103 | H48: 3426 | I48: 3373 | J48: 3380 | K48: 29 | L48: 0 | M48: 0 | N48: 0 | O48: 1 | P48: 9 | Q48: 19 | R48: 29 | S48: 3 | T48: 2 | U48: 2 | V48: 0 | W48: 0 | X48: 1 | Y48: 0 | Z48: 24 | AA48: 4 | AB48: 3351 | AC48: 0 | AD48: 0 | AE48: 0 | AF48: 0 | AG48: 0 | AH48: 0 | AI48: 0 | AN48: 0 | AO48: 1 | AP48: 0 | AQ48: 0 | AR48: 4 | AS48: 1 | AT48: 22 | AU48: 0 | AV48: 169 | AX48: 0.28 | AY48: 0 | BA48: 0 | BB48: 1 | BH48: 21 | BJ48: 0 | BK48: 2026-09-16 04:03:10.020000000
A49: 2026-09-16 | B49: 15139629000194 | C49: Neoenergia Coelba | D49: COMPANHIA DE ELETRICIDADE DO ESTADO DA BAHIA | E49: Concessão | F49: 2026-07-01 | G49: 2929909 | H49: 25373 | I49: 24791 | J49: 24850 | K49: 159 | L49: 43 | M49: 0 | N49: 0 | O49: 4 | P49: 55 | Q49: 57 | R49: 479 | S49: 52 | T49: 25 | U49: 22 | V49: 3 | W49: 0 | X49: 27 | Y49: 0 | Z49: 123 | AA49: 32 | AB49: 24691 | AC49: 0 | AD49: 0 | AE49: 0 | AF49: 0 | AG49: 0 | AH49: 0 | AI49: 0 | AN49: 1 | AO49: 3 | AP49: 0 | AQ49: 0 | AR49: 27 | AS49: 1 | AT49: 22 | AU49: 0 | AV49: 506 | AX49: 0.08 | AY49: 0 | BA49: 0 | BB49: 35 | BC49: 9 | BD49: 6 | BE49: 9 | BF49: 6 | BH49: 20 | BJ49: 0 | BK49: 2026-09-16 04:03:10.053000000
A50: 2026-09-16 | B50: 15139629000194 | C50: Neoenergia Coelba | D50: COMPANHIA DE ELETRICIDADE DO ESTADO DA BAHIA | E50: Concessão | F50: 2023-08-01 | G50: 2912202 | H50: 9525 | I50: 9347 | J50: 9350 | K50: 61 | L50: 4 | M50: 0 | N50: 0 | O50: 1 | P50: 38 | Q50: 18 | R50: 49 | S50: 88 | T50: 63 | U50: 63 | V50: 0 | W50: 0 | X50: 25 | Y50: 0 | Z50: 39 | AA50: 21 | AB50: 9289 | AC50: 0 | AD50: 0 | AE50: 0 | AF50: 0 | AG50: 0 | AH50: 0 | AI50: 0 | AN50: 0 | AO50: 0 | AP50: 0 | AQ50: 2238.38 | AR50: 36 | AS50: 1 | AT50: 23 | AU50: 0 | AV50: 85 | AX50: 0.84 | AY50: 0 | BA50: 0 | BB50: 23 | BC50: 7 | BD50: 8 | BE50: 11 | BF50: 6 | BH50: 104 | BJ50: 0 | BK50: 2026-09-16 04:03:09.927000000
A51: 2026-09-16 | B51: 15139629000194 | C51: Neoenergia Coelba | D51: COMPANHIA DE ELETRICIDADE DO ESTADO DA BAHIA | E51: Concessão | F51: 2026-05-01 | G51: 2931053 | H51: 9007 | I51: 8753 | J51: 8754 | K51: 171 | L51: 35 | M51: 0 | N51: 0 | O51: 1 | P51: 79 | Q51: 56 | R51: 53 | S51: 42 | T51: 14 | U51: 13 | V51: 1 | W51: 0 | X51: 28 | Y51: 0 | Z51: 107 | AA51: 63 | AB51: 8583 | AC51: 0 | AD51: 0 | AE51: 0 | AF51: 0 | AG51: 0 | AH51: 0 | AI51: 0 | AN51: 0 | AO51: 0 | AP51: 0 | AQ51: 0 | AR51: 9 | AS51: 1 | AT51: 22 | AU51: 0 | AV51: 179 | AX51: 0.4 | AY51: 0 | BA51: 0 | BB51: 7 | BC51: 1 | BE51: 2 | BH51: 23 | BJ51: 0 | BK51: 2026-09-16 04:03:10.020000000
A52: 2026-09-16 | B52: 15139629000194 | C52: Neoenergia Coelba | D52: COMPANHIA DE ELETRICIDADE DO ESTADO DA BAHIA | E52: Concessão | F52: 2026-07-01 | G52: 2929800 | H52: 6229 | I52: 6110 | J52: 6085 | K52: 63 | L52: 17 | M52: 0 | N52: 0 | O52: 1 | P52: 30 | Q52: 15 | R52: 47 | S52: 8 | T52: 8 | U52: 8 | V52: 0 | W52: 0 | X52: 0 | Y52: 0 | Z52: 40 | AA52: 22 | AB52: 6022 | AC52: 0 | AD52: 0 | AE52: 0 | AF52: 0 | AG52: 0 | AH52: 0 | AI52: 0 | AN52: 0 | AO52: 0 | AP52: 0 | AQ52: 0 | AR52: 5 | AS52: 1 | AT52: 22 | AU52: 0 | AV52: 60 | AX52: 0.33 | AY52: 0 | BA52: 0 | BB52: 1 | BC52: 1 | BH52: 59 | BJ52: 0 | BK52: 2026-09-16 04:03:10.053000000
A53: 2026-09-16 | B53: 15139629000194 | C53: Neoenergia Coelba | D53: COMPANHIA DE ELETRICIDADE DO ESTADO DA BAHIA | E53: Concessão | F53: 2023-08-01 | G53: 2929305 | H53: 16700 | I53: 16317 | J53: 16364 | K53: 146 | L53: 26 | M53: 0 | N53: 0 | O53: 2 | P53: 63 | Q53: 55 | R53: 83 | S53: 37 | T53: 22 | U53: 22 | V53: 0 | W53: 0 | X53: 15 | Y53: 0 | Z53: 119 | AA53: 25 | AB53: 16218 | AC53: 0 | AD53: 0 | AE53: 0 | AF53: 0 | AG53: 0 | AH53: 0 | AI53: 0 | AN53: 7 | AO53: 1 | AP53: 4220 | AQ53: 0 | AR53: 139 | AS53: 1 | AT53: 23 | AU53: 0 | AV53: 404 | AX53: 5.5 | AY53: 0 | BA53: 0 | BB53: 57 | BC53: 22 | BD53: 12 | BE53: 18 | BF53: 5 | BH53: 186 | BJ53: 0 | BK53: 2026-09-16 04:03:09.927000000
A54: 2026-09-16 | B54: 15139629000194 | C54: Neoenergia Coelba | D54: COMPANHIA DE ELETRICIDADE DO ESTADO DA BAHIA | E54: Concessão | F54: 2024-06-01 | G54: 2913309 | H54: 2861 | I54: 2800 | J54: 2810 | K54: 17 | L54: 0 | M54: 0 | N54: 0 | O54: 1 | P54: 6 | Q54: 10 | R54: 92 | S54: 13 | T54: 13 | U54: 13 | V54: 0 | W54: 0 | X54: 0 | Y54: 0 | Z54: 10 | AA54: 6 | AB54: 2793 | AC54: 0 | AD54: 0 | AE54: 0 | AF54: 0 | AG54: 0 | AH54: 0 | AI54: 0 | AN54: 1 | AO54: 1 | AP54: 0 | AQ54: 0 | AR54: 21 | AS54: 1 | AT54: 19 | AU54: 0 | AV54: 120 | AX54: 0.0022 | AY54: 0 | BA54: 0 | BB54: 2 | BC54: 1 | BE54: 1 | BH54: 35 | BJ54: 0 | BK54: 2026-09-16 04:03:09.960000000
A55: 2026-09-16 | B55: 15139629000194 | C55: Neoenergia Coelba | D55: COMPANHIA DE ELETRICIDADE DO ESTADO DA BAHIA | E55: Concessão | F55: 2026-05-01 | G55: 2917003 | H55: 16671 | I55: 16279 | J55: 16284 | K55: 139 | L55: 3 | M55: 0 | N55: 0 | O55: 1 | P55: 30 | Q55: 105 | R55: 185 | S55: 10 | T55: 10 | U55: 9 | V55: 1 | W55: 0 | X55: 0 | Y55: 0 | Z55: 114 | AA55: 24 | AB55: 16145 | AC55: 0 | AD55: 0 | AE55: 0 | AF55: 0 | AG55: 0 | AH55: 0 | AI55: 0 | AN55: 1 | AO55: 0 | AP55: 0 | AQ55: 0 | AR55: 27 | AS55: 1 | AT55: 22 | AU55: 0 | AV55: 321 | AX55: 0.25 | AY55: 0 | BA55: 0 | BB55: 7 | BC55: 2 | BE55: 1 | BH55: 93 | BJ55: 0 | BK55: 2026-09-16 04:03:10.020000000
A56: 2026-09-16 | B56: 15139629000194 | C56: Neoenergia Coelba | D56: COMPANHIA DE ELETRICIDADE DO ESTADO DA BAHIA | E56: Concessão | F56: 2026-07-01 | G56: 2930758 | H56: 5576 | I56: 5438 | J56: 5428 | K56: 167 | L56: 97 | M56: 0 | N56: 0 | O56: 1 | P56: 30 | Q56: 39 | R56: 89 | S56: 63 | T56: 7 | U56: 5 | V56: 2 | W56: 0 | X56: 56 | Y56: 0 | Z56: 123 | AA56: 43 | AB56: 5261 | AC56: 0 | AD56: 0 | AE56: 0 | AF56: 0 | AG56: 0 | AH56: 0 | AI56: 0 | AN56: 1 | AO56: 1 | AP56: 0 | AQ56: 0 | AR56: 19 | AS56: 1 | AT56: 22 | AU56: 0 | AV56: 196 | AX56: 0.1 | AY56: 0 | BA56: 0 | BB56: 14 | BC56: 5 | BD56: 2 | BE56: 3 | BF56: 1 | BH56: 53 | BJ56: 0 | BK56: 2026-09-16 04:03:10.053000000
A57: 2026-09-16 | B57: 15139629000194 | C57: Neoenergia Coelba | D57: COMPANHIA DE ELETRICIDADE DO ESTADO DA BAHIA | E57: Concessão | F57: 2023-08-01 | G57: 2929255 | H57: 9654 | I57: 9447 | J57: 9499 | K57: 126 | L57: 51 | M57: 0 | N57: 0 | O57: 4 | P57: 48 | Q57: 23 | R57: 40 | S57: 74 | T57: 24 | U57: 20 | V57: 4 | W57: 0 | X57: 50 | Y57: 0 | Z57: 90 | AA57: 32 | AB57: 9373 | AC57: 0 | AD57: 0 | AE57: 0 | AF57: 0 | AG57: 0 | AH57: 0 | AI57: 0 | AN57: 1 | AO57: 0 | AP57: 0 | AQ57: 0 | AR57: 9 | AS57: 1 | AT57: 23 | AU57: 0 | AV57: 43 | AX57: 1.33 | AY57: 0 | BA57: 0 | BB57: 12 | BC57: 4 | BD57: 1 | BE57: 2 | BF57: 1 | BH57: 97 | BJ57: 0 | BK57: 2026-09-16 04:03:09.927000000
A58: 2026-09-16 | B58: 15139629000194 | C58: Neoenergia Coelba | D58: COMPANHIA DE ELETRICIDADE DO ESTADO DA BAHIA | E58: Concessão | F58: 2024-06-01 | G58: 2910404 | H58: 20010 | I58: 19787 | J58: 19793 | K58: 171 | L58: 0 | M58: 0 | N58: 0 | O58: 5 | P58: 90 | Q58: 76 | R58: 261 | S58: 96 | T58: 96 | U58: 95 | V58: 1 | W58: 0 | X58: 0 | Y58: 0 | Z58: 135 | AA58: 31 | AB58: 19622 | AC58: 0 | AD58: 0 | AE58: 0 | AF58: 0 | AG58: 0 | AH58: 0 | AI58: 0 | AN58: 9 | AO58: 10 | AP58: 0 | AQ58: 1211 | AR58: 43 | AS58: 1 | AT58: 19 | AU58: 0 | AV58: 312 | AX58: 0.0041 | AY58: 0 | BA58: 0 | BB58: 22 | BC58: 5 | BD58: 5 | BE58: 8 | BH58: 129 | BJ58: 0 | BK58: 2026-09-16 04:03:09.960000000
A59: 2026-09-16 | B59: 15139629000194 | C59: Neoenergia Coelba | D59: COMPANHIA DE ELETRICIDADE DO ESTADO DA BAHIA | E59: Concessão | F59: 2026-05-01 | G59: 2916906 | H59: 5683 | I59: 5553 | J59: 5543 | K59: 19 | L59: 2 | M59: 0 | N59: 0 | O59: 1 | P59: 11 | Q59: 5 | R59: 24 | S59: 6 | T59: 2 | U59: 1 | V59: 1 | W59: 0 | X59: 4 | Y59: 0 | Z59: 15 | AA59: 3 | AB59: 5523 | AC59: 1 | AD59: 0 | AE59: 1 | AF59: 0 | AG59: 0 | AH59: 0 | AI59: 0 | AN59: 0 | AO59: 0 | AP59: 0 | AQ59: 0 | AR59: 17 | AS59: 1 | AT59: 22 | AU59: 0 | AV59: 71 | AX59: 0.17 | AY59: 0 | BA59: 0 | BB59: 8 | BH59: 30 | BJ59: 0 | BK59: 2026-09-16 04:03:10.020000000
A60: 2026-09-16 | B60: 15139629000194 | C60: Neoenergia Coelba | D60: COMPANHIA DE ELETRICIDADE DO ESTADO DA BAHIA | E60: Concessão | F60: 2026-07-01 | G60: 2903805 | H60: 9363 | I60: 9189 | J60: 9151 | K60: 262 | L60: 184 | M60: 0 | N60: 0 | O60: 1 | P60: 38 | Q60: 39 | R60: 207 | S60: 132 | T60: 24 | U60: 20 | V60: 4 | W60: 0 | X60: 108 | Y60: 0 | Z60: 175 | AA60: 86 | AB60: 8889 | AC60: 0 | AD60: 0 | AE60: 0 | AF60: 0 | AG60: 0 | AH60: 0 | AI60: 0 | AN60: 0 | AO60: 0 | AP60: 0 | AQ60: 0 | AR60: 16 | AS60: 1 | AT60: 22 | AU60: 0 | AV60: 313 | AX60: 0.62 | AY60: 0 | BA60: 0 | BB60: 2 | BH60: 69 | BJ60: 0 | BK60: 2026-09-16 04:03:10.053000000
A61: 2026-09-16 | B61: 15139629000194 | C61: Neoenergia Coelba | D61: COMPANHIA DE ELETRICIDADE DO ESTADO DA BAHIA | E61: Concessão | F61: 2023-08-01 | G61: 2929206 | H61: 15168 | I61: 14998 | J61: 15035 | K61: 118 | L61: 1 | M61: 0 | N61: 0 | O61: 1 | P61: 55 | Q61: 61 | R61: 70 | S61: 29 | T61: 29 | U61: 29 | V61: 0 | W61: 0 | X61: 0 | Y61: 0 | Z61: 95 | AA61: 22 | AB61: 14917 | AC61: 0 | AD61: 0 | AE61: 0 | AF61: 0 | AG61: 0 | AH61: 0 | AI61: 0 | AN61: 6 | AO61: 8 | AP61: 0 | AQ61: 0 | AR61: 21 | AS61: 1 | AT61: 23 | AU61: 0 | AV61: 106 | AX61: 1.21 | AY61: 0 | BA61: 0 | BB61: 3 | BC61: 2 | BD61: 8 | BE61: 9 | BF61: 1 | BH61: 22 | BJ61: 0 | BK61: 2026-09-16 04:03:09.927000000
A62: 2026-09-16 | B62: 15139629000194 | C62: Neoenergia Coelba | D62: COMPANHIA DE ELETRICIDADE DO ESTADO DA BAHIA | E62: Concessão | F62: 2024-06-01 | G62: 2910305 | H62: 4231 | I62: 4163 | J62: 4169 | K62: 15 | L62: 0 | M62: 0 | N62: 0 | O62: 3 | P62: 5 | Q62: 7 | R62: 42 | S62: 9 | T62: 9 | U62: 2 | V62: 7 | W62: 0 | X62: 0 | Y62: 0 | Z62: 11 | AA62: 1 | AB62: 4154 | AC62: 0 | AD62: 0 | AE62: 0 | AF62: 0 | AG62: 0 | AH62: 0 | AI62: 0 | AN62: 0 | AO62: 0 | AP62: 0 | AQ62: 0 | AR62: 11 | AS62: 1 | AT62: 19 | AU62: 0 | AV62: 48 | AX62: 0.0011 | AY62: 0 | BA62: 0 | BB62: 1 | BH62: 36 | BI62: 1 | BJ62: 0 | BK62: 2026-09-16 04:03:09.960000000
A63: 2026-09-16 | B63: 15139629000194 | C63: Neoenergia Coelba | D63: COMPANHIA DE ELETRICIDADE DO ESTADO DA BAHIA | E63: Concessão | F63: 2026-05-01 | G63: 2916856 | H63: 7770 | I63: 7567 | J63: 7565 | K63: 61 | L63: 20 | M63: 0 | N63: 0 | O63: 1 | P63: 13 | Q63: 27 | R63: 51 | S63: 15 | T63: 2 | U63: 2 | V63: 0 | W63: 0 | X63: 13 | Y63: 0 | Z63: 45 | AA63: 15 | AB63: 7504 | AC63: 0 | AD63: 0 | AE63: 0 | AF63: 0 | AG63: 0 | AH63: 0 | AI63: 0 | AN63: 1 | AO63: 1 | AP63: 0 | AQ63: 650 | AR63: 28 | AS63: 1 | AT63: 22 | AU63: 0 | AV63: 78 | AX63: 0.23 | AY63: 0 | BA63: 0 | BB63: 3 | BC63: 1 | BE63: 1 | BH63: 68 | BJ63: 0 | BK63: 2026-09-16 04:03:10.020000000
A64: 2026-09-16 | B64: 15139629000194 | C64: Neoenergia Coelba | D64: COMPANHIA DE ELETRICIDADE DO ESTADO DA BAHIA | E64: Concessão | F64: 2026-07-01 | G64: 2930766 | H64: 6781 | I64: 6594 | J64: 6623 | K64: 99 | L64: 5 | M64: 0 | N64: 0 | O64: 1 | P64: 65 | Q64: 28 | R64: 77 | S64: 15 | T64: 12 | U64: 12 | V64: 0 | W64: 0 | X64: 3 | Y64: 0 | Z64: 82 | AA64: 16 | AB64: 6524 | AC64: 0 | AD64: 0 | AE64: 0 | AF64: 0 | AG64: 0 | AH64: 0 | AI64: 0 | AN64: 0 | AO64: 0 | AP64: 0 | AQ64: 0 | AR64: 5 | AS64: 1 | AT64: 22 | AU64: 0 | AV64: 173 | AX64: 0.13 | AY64: 0 | BA64: 0 | BB64: 1 | BC64: 1 | BH64: 39 | BJ64: 0 | BK64: 2026-09-16 04:03:10.053000000
A65: 2026-09-16 | B65: 15139629000194 | C65: Neoenergia Coelba | D65: COMPANHIA DE ELETRICIDADE DO ESTADO DA BAHIA | E65: Concessão | F65: 2023-08-01 | G65: 2927606 | H65: 6443 | I65: 6371 | J65: 6407 | K65: 115 | L65: 29 | M65: 0 | N65: 0 | O65: 1 | P65: 55 | Q65: 30 | R65: 3 | S65: 16 | T65: 1 | U65: 1 | V65: 0 | W65: 0 | X65: 15 | Y65: 0 | Z65: 78 | AA65: 36 | AB65: 6292 | AC65: 0 | AD65: 0 | AE65: 0 | AF65: 0 | AG65: 0 | AH65: 0 | AI65: 0 | AN65: 0 | AO65: 0 | AP65: 0 | AQ65: 0 | AR65: 2 | AS65: 1 | AT65: 23 | AU65: 0 | AV65: 166 | AX65: 10.17 | AY65: 0 | BA65: 0 | BB65: 2 | BC65: 2 | BD65: 3 | BE65: 4 | BH65: 39 | BJ65: 0 | BK65: 2026-09-16 04:03:09.927000000
A66: 2026-09-16 | B66: 15139629000194 | C66: Neoenergia Coelba | D66: COMPANHIA DE ELETRICIDADE DO ESTADO DA BAHIA | E66: Concessão | F66: 2024-06-01 | G66: 2910206 | H66: 2107 | I66: 2076 | J66: 2076 | K66: 15 | L66: 0 | M66: 0 | N66: 0 | O66: 1 | P66: 5 | Q66: 9 | R66: 13 | S66: 3 | T66: 3 | U66: 2 | V66: 1 | W66: 0 | X66: 0 | Y66: 0 | Z66: 12 | AA66: 2 | AB66: 2061 | AC66: 0 | AD66: 0 | AE66: 0 | AF66: 0 | AG66: 0 | AH66: 0 | AI66: 0 | AN66: 2 | AO66: 0 | AP66: 540 | AQ66: 0 | AR66: 4 | AS66: 1 | AT66: 19 | AU66: 0 | AV66: 131 | AX66: 0.0056 | AY66: 0 | BA66: 0 | BH66: 24 | BJ66: 0 | BK66: 2026-09-16 04:03:09.960000000
A67: 2026-09-16 | B67: 15139629000194 | C67: Neoenergia Coelba | D67: COMPANHIA DE ELETRICIDADE DO ESTADO DA BAHIA | E67: Concessão | F67: 2026-05-01 | G67: 2916807 | H67: 8031 | I67: 7831 | J67: 7774 | K67: 68 | L67: 13 | M67: 9 | N67: 0 | O67: 1 | P67: 14 | Q67: 31 | R67: 134 | S67: 61 | T67: 29 | U67: 29 | V67: 0 | W67: 0 | X67: 7 | Y67: 25 | Z67: 61 | AA67: 6 | AB67: 7706 | AC67: 0 | AD67: 0 | AE67: 0 | AF67: 1 | AG67: 1 | AH67: 0 | AI67: 0 | AJ67: 12618 | AK67: 12618 | AL67: 0 | AM67: 0 | AN67: 3 | AO67: 3 | AP67: 0 | AQ67: 735 | AR67: 22 | AS67: 1 | AT67: 22 | AU67: 0 | AV67: 447 | AX67: 0.28 | AY67: 0 | BA67: 0 | BB67: 1 | BH67: 83 | BJ67: 0 | BK67: 2026-09-16 04:03:10.020000000
A68: 2026-09-16 | B68: 15139629000194 | C68: Neoenergia Coelba | D68: COMPANHIA DE ELETRICIDADE DO ESTADO DA BAHIA | E68: Concessão | F68: 2026-07-01 | G68: 2930808 | H68: 8120 | I68: 7913 | J68: 7921 | K68: 113 | L68: 25 | M68: 0 | N68: 0 | O68: 2 | P68: 28 | Q68: 58 | R68: 32 | S68: 34 | T68: 12 | U68: 12 | V68: 0 | W68: 0 | X68: 22 | Y68: 0 | Z68: 97 | AA68: 14 | AB68: 7808 | AC68: 0 | AD68: 0 | AE68: 0 | AF68: 0 | AG68: 0 | AH68: 0 | AI68: 0 | AN68: 0 | AO68: 1 | AP68: 0 | AQ68: 0 | AR68: 18 | AS68: 1 | AT68: 22 | AU68: 0 | AV68: 146 | AX68: 0.1 | AY68: 0 | BA68: 0 | BB68: 9 | BC68: 7 | BD68: 3 | BE68: 3 | BF68: 3 | BH68: 56 | BJ68: 0 | BK68: 2026-09-16 04:03:10.053000000
A69: 2026-09-16 | B69: 15139629000194 | C69: Neoenergia Coelba | D69: COMPANHIA DE ELETRICIDADE DO ESTADO DA BAHIA | E69: Concessão | F69: 2023-08-01 | G69: 2927507 | H69: 8614 | I69: 8411 | J69: 8452 | K69: 88 | L69: 1 | M69: 0 | N69: 0 | O69: 5 | P69: 42 | Q69: 40 | R69: 13 | S69: 1 | T69: 0 | U69: 0 | V69: 0 | W69: 0 | X69: 1 | Y69: 0 | Z69: 65 | AA69: 18 | AB69: 8364 | AC69: 0 | AD69: 0 | AE69: 0 | AF69: 0 | AG69: 0 | AH69: 0 | AI69: 0 | AN69: 4 | AO69: 2 | AP69: 0 | AQ69: 0 | AR69: 30 | AS69: 1 | AT69: 23 | AU69: 0 | AV69: 375 | AX69: 4.78 | AY69: 0 | BA69: 0 | BB69: 16 | BC69: 10 | BD69: 12 | BE69: 12 | BF69: 1 | BH69: 100 | BI69: 1 | BJ69: 0 | BK69: 2026-09-16 04:03:09.927000000
A70: 2026-09-16 | B70: 15139629000194 | C70: Neoenergia Coelba | D70: COMPANHIA DE ELETRICIDADE DO ESTADO DA BAHIA | E70: Concessão | F70: 2024-06-01 | G70: 2913002 | H70: 7225 | I70: 7140 | J70: 7127 | K70: 55 | L70: 2 | M70: 0 | N70: 0 | O70: 3 | P70: 9 | Q70: 41 | R70: 208 | S70: 20 | T70: 20 | U70: 20 | V70: 0 | W70: 0 | X70: 0 | Y70: 0 | Z70: 39 | AA70: 13 | AB70: 7072 | AC70: 0 | AD70: 0 | AE70: 0 | AF70: 0 | AG70: 0 | AH70: 0 | AI70: 0 | AN70: 0 | AO70: 0 | AP70: 0 | AQ70: 0 | AR70: 16 | AS70: 1 | AT70: 19 | AU70: 0 | AV70: 85 | AX70: 0.0042 | AY70: 0 | BA70: 0 | BB70: 5 | BD70: 4 | BE70: 16 | BF70: 3 | BH70: 11 | BJ70: 0 | BK70: 2026-09-16 04:03:09.960000000
A71: 2026-09-16 | B71: 15139629000194 | C71: Neoenergia Coelba | D71: COMPANHIA DE ELETRICIDADE DO ESTADO DA BAHIA | E71: Concessão | F71: 2026-05-01 | G71: 2916708 | H71: 3865 | I71: 3788 | J71: 3793 | K71: 30 | L71: 1 | M71: 0 | N71: 0 | O71: 1 | P71: 16 | Q71: 12 | R71: 18 | S71: 1 | T71: 1 | U71: 1 | V71: 0 | W71: 0 | X71: 0 | Y71: 0 | Z71: 24 | AA71: 5 | AB71: 3763 | AC71: 0 | AD71: 0 | AE71: 0 | AF71: 0 | AG71: 0 | AH71: 0 | AI71: 0 | AN71: 0 | AO71: 0 | AP71: 0 | AQ71: 0 | AR71: 9 | AS71: 1 | AT71: 22 | AU71: 0 | AV71: 89 | AX71: 0.08 | AY71: 0 | BA71: 0 | BB71: 4 | BH71: 3 | BJ71: 0 | BK71: 2026-09-16 04:03:10.020000000
A72: 2026-09-16 | B72: 15139629000194 | C72: Neoenergia Coelba | D72: COMPANHIA DE ELETRICIDADE DO ESTADO DA BAHIA | E72: Concessão | F72: 2026-07-01 | G72: 2918506 | H72: 8571 | I72: 8341 | J72: 8334 | K72: 290 | L72: 148 | M72: 0 | N72: 0 | O72: 1 | P72: 57 | Q72: 84 | R72: 118 | S72: 83 | T72: 9 | U72: 6 | V72: 3 | W72: 0 | X72: 74 | Y72: 0 | Z72: 185 | AA72: 104 | AB72: 8043 | AC72: 1 | AD72: 0 | AE72: 1 | AF72: 0 | AG72: 0 | AH72: 0 | AI72: 0 | AN72: 0 | AO72: 1 | AP72: 0 | AQ72: 0 | AR72: 25 | AS72: 1 | AT72: 22 | AU72: 0 | AV72: 71 | AX72: 0.03 | AY72: 0 | BA72: 0 | BH72: 29 | BJ72: 0 | BK72: 2026-09-16 04:03:10.053000000
A73: 2026-09-16 | B73: 15139629000194 | C73: Neoenergia Coelba | D73: COMPANHIA DE ELETRICIDADE DO ESTADO DA BAHIA | E73: Concessão | F73: 2023-08-01 | G73: 2927408 | H73: 1132664 | I73: 1110995 | J73: 1116940 | K73: 20461 | L73: 1422 | M73: 0 | N73: 0 | O73: 485 | P73: 5994 | Q73: 12560 | R73: 6789 | S73: 3674 | T73: 2697 | U73: 2612 | V73: 85 | W73: 0 | X73: 977 | Y73: 0 | Z73: 15190 | AA73: 4786 | AB73: 1096464 | AC73: 15 | AD73: 0 | AE73: 15 | AF73: 1 | AG73: 1 | AH73: 0 | AI73: 0 | AJ73: 10845 | AK73: 10845 | AL73: 0 | AM73: 0 | AN73: 1310 | AO73: 471 | AP73: 90288.87 | AQ73: 164478.2 | AR73: 2694 | AS73: 7 | AT73: 23 | AU73: 0 | AV73: 28910 | AX73: 8.42 | AY73: 0 | BA73: 0 | BB73: 944 | BC73: 299 | BD73: 610 | BE73: 810 | BF73: 320 | BG73: 23 | BH73: 5727 | BI73: 18 | BJ73: 0 | BK73: 2026-09-16 04:03:09.927000000
A74: 2026-09-16 | B74: 15139629000194 | C74: Neoenergia Coelba | D74: COMPANHIA DE ELETRICIDADE DO ESTADO DA BAHIA | E74: Concessão | F74: 2024-06-01 | G74: 2913101 | H74: 8904 | I74: 8740 | J74: 8757 | K74: 246 | L74: 148 | M74: 0 | N74: 0 | O74: 7 | P74: 55 | Q74: 36 | R74: 48 | S74: 63 | T74: 10 | U74: 9 | V74: 1 | W74: 0 | X74: 53 | Y74: 0 | Z74: 184 | AA74: 55 | AB74: 8511 | AC74: 0 | AD74: 0 | AE74: 0 | AF74: 0 | AG74: 0 | AH74: 0 | AI74: 0 | AN74: 1 | AO74: 0 | AP74: 0 | AQ74: 0 | AR74: 37 | AS74: 1 | AT74: 19 | AU74: 0 | AV74: 87 | AX74: 0.0065 | AY74: 0 | BA74: 0 | BB74: 21 | BC74: 6 | BD74: 11 | BE74: 12 | BF74: 10 | BH74: 73 | BJ74: 0 | BK74: 2026-09-16 04:03:09.960000000
A75: 2026-09-16 | B75: 15139629000194 | C75: Neoenergia Coelba | D75: COMPANHIA DE ELETRICIDADE DO ESTADO DA BAHIA | E75: Concessão | F75: 2026-05-01 | G75: 2916609 | H75: 3372 | I75: 3323 | J75: 3307 | K75: 48 | L75: 16 | M75: 0 | N75: 0 | O75: 1 | P75: 20 | Q75: 11 | R75: 51 | S75: 11 | T75: 0 | U75: 0 | V75: 0 | W75: 0 | X75: 11 | Y75: 0 | Z75: 32 | AA75: 15 | AB75: 3259 | AC75: 0 | AD75: 0 | AE75: 0 | AF75: 0 | AG75: 0 | AH75: 0 | AI75: 0 | AN75: 0 | AO75: 0 | AP75: 0 | AQ75: 0 | AR75: 6 | AS75: 1 | AT75: 22 | AU75: 0 | AV75: 99 | AX75: 0.28 | AY75: 0 | BA75: 0 | BJ75: 0 | BK75: 2026-09-16 04:03:10.020000000
A76: 2026-09-16 | B76: 15139629000194 | C76: Neoenergia Coelba | D76: COMPANHIA DE ELETRICIDADE DO ESTADO DA BAHIA | E76: Concessão | F76: 2026-07-01 | G76: 2918456 | H76: 3581 | I76: 3544 | J76: 3550 | K76: 141 | L76: 79 | M76: 0 | N76: 0 | O76: 1 | P76: 24 | Q76: 37 | R76: 61 | S76: 71 | T76: 12 | U76: 10 | V76: 2 | W76: 0 | X76: 59 | Y76: 0 | Z76: 102 | AA76: 38 | AB76: 3409 | AC76: 0 | AD76: 0 | AE76: 0 | AF76: 0 | AG76: 0 | AH76: 0 | AI76: 0 | AN76: 0 | AO76: 0 | AP76: 0 | AQ76: 0 | AR76: 0 | AS76: 1 | AT76: 22 | AU76: 0 | AV76: 44 | AX76: 0.07 | AY76: 0 | BA76: 0 | BB76: 2 | BH76: 1 | BJ76: 0 | BK76: 2026-09-16 04:03:10.053000000
A77: 2026-09-16 | B77: 15139629000194 | C77: Neoenergia Coelba | D77: COMPANHIA DE ELETRICIDADE DO ESTADO DA BAHIA | E77: Concessão | F77: 2023-08-01 | G77: 2927309 | H77: 7866 | I77: 7758 | J77: 7768 | K77: 50 | L77: 0 | M77: 0 | N77: 0 | O77: 2 | P77: 13 | Q77: 35 | R77: 52 | S77: 23 | T77: 22 | U77: 22 | V77: 0 | W77: 0 | X77: 1 | Y77: 0 | Z77: 39 | AA77: 9 | AB77: 7718 | AC77: 0 | AD77: 0 | AE77: 0 | AF77: 0 | AG77: 0 | AH77: 0 | AI77: 0 | AN77: 9 | AO77: 2 | AP77: 0 | AQ77: 649 | AR77: 6 | AS77: 1 | AT77: 23 | AU77: 0 | AV77: 39 | AX77: 1.39 | AY77: 0 | BA77: 0 | BB77: 10 | BC77: 5 | BD77: 31 | BE77: 31 | BF77: 1 | BH77: 21 | BJ77: 0 | BK77: 2026-09-16 04:03:09.927000000
A78: 2026-09-16 | B78: 15139629000194 | C78: Neoenergia Coelba | D78: COMPANHIA DE ELETRICIDADE DO ESTADO DA BAHIA | E78: Concessão | F78: 2024-06-01 | G78: 2913200 | H78: 13446 | I78: 13187 | J78: 13046 | K78: 75 | L78: 8 | M78: 0 | N78: 0 | O78: 2 | P78: 29 | Q78: 36 | R78: 46 | S78: 17 | T78: 16 | U78: 16 | V78: 0 | W78: 0 | X78: 1 | Y78: 0 | Z78: 58 | AA78: 15 | AB78: 12971 | AC78: 0 | AD78: 0 | AE78: 0 | AF78: 0 | AG78: 0 | AH78: 0 | AI78: 0 | AN78: 0 | AO78: 1 | AP78: 0 | AQ78: 0 | AR78: 67 | AS78: 1 | AT78: 19 | AU78: 0 | AV78: 1385 | AX78: 0.0032 | AY78: 0 | BA78: 0 | BB78: 27 | BC78: 8 | BD78: 3 | BE78: 19 | BF78: 2 | BH78: 111 | BJ78: 0 | BK78: 2026-09-16 04:03:09.960000000
A79: 2026-09-16 | B79: 15139629000194 | C79: Neoenergia Coelba | D79: COMPANHIA DE ELETRICIDADE DO ESTADO DA BAHIA | E79: Concessão | F79: 2026-05-01 | G79: 2915908 | H79: 3666 | I79: 3374 | J79: 3381 | K79: 43 | L79: 3 | M79: 0 | N79: 0 | O79: 1 | P79: 13 | Q79: 26 | R79: 70 | S79: 32 | T79: 32 | U79: 32 | V79: 0 | W79: 0 | X79: 0 | Y79: 0 | Z79: 29 | AA79: 13 | AB79: 3338 | AC79: 0 | AD79: 0 | AE79: 0 | AF79: 0 | AG79: 0 | AH79: 0 | AI79: 0 | AN79: 1 | AO79: 0 | AP79: 0 | AQ79: 1220 | AR79: 5 | AS79: 1 | AT79: 22 | AU79: 0 | AV79: 75 | AX79: 0.73 | AY79: 0 | BA79: 0 | BH79: 4 | BJ79: 0 | BK79: 2026-09-16 04:03:10.020000000
A80: 2026-09-16 | B80: 15139629000194 | C80: Neoenergia Coelba | D80: COMPANHIA DE ELETRICIDADE DO ESTADO DA BAHIA | E80: Concessão | F80: 2026-07-01 | G80: 2918407 | H80: 108537 | I80: 105888 | J80: 105292 | K80: 1251 | L80: 224 | M80: 0 | N80: 0 | O80: 13 | P80: 364 | Q80: 650 | R80: 3425 | S80: 502 | T80: 364 | U80: 189 | V80: 175 | W80: 0 | X80: 138 | Y80: 0 | Z80: 1055 | AA80: 183 | AB80: 104039 | AC80: 2 | AD80: 0 | AE80: 2 | AF80: 0 | AG80: 0 | AH80: 0 | AI80: 0 | AN80: 9 | AO80: 26 | AP80: 2190 | AQ80: 1170 | AR80: 883 | AS80: 1 | AT80: 22 | AU80: 0 | AV80: 3206 | AX80: 5.38 | AY80: 0 | BA80: 0 | BB80: 37 | BC80: 15 | BD80: 20 | BE80: 40 | BF80: 8 | BH80: 1155 | BJ80: 0 | BK80: 2026-09-16 04:03:10.053000000
A81: 2026-09-16 | B81: 15139629000194 | C81: Neoenergia Coelba | D81: COMPANHIA DE ELETRICIDADE DO ESTADO DA BAHIA | E81: Concessão | F81: 2023-08-01 | G81: 2927200 | H81: 14175 | I81: 13882 | J81: 13850 | K81: 203 | L81: 53 | M81: 0 | N81: 0 | O81: 3 | P81: 118 | Q81: 29 | R81: 12 | S81: 46 | T81: 5 | U81: 2 | V81: 3 | W81: 0 | X81: 41 | Y81: 0 | Z81: 156 | AA81: 44 | AB81: 13647 | AC81: 0 | AD81: 0 | AE81: 0 | AF81: 0 | AG81: 0 | AH81: 0 | AI81: 0 | AN81: 5 | AO81: 0 | AP81: 0 | AQ81: 1480 | AR81: 26 | AS81: 1 | AT81: 23 | AU81: 0 | AV81: 213 | AX81: 4.18 | AY81: 0 | BA81: 0 | BB81: 42 | BC81: 1 | BH81: 149 | BJ81: 0 | BK81: 2026-09-16 04:03:09.927000000
A82: 2026-09-16 | B82: 15139629000194 | C82: Neoenergia Coelba | D82: COMPANHIA DE ELETRICIDADE DO ESTADO DA BAHIA | E82: Concessão | F82: 2024-06-01 | G82: 2910008 | H82: 4842 | I82: 4758 | J82: 4758 | K82: 114 | L82: 97 | M82: 0 | N82: 0 | O82: 1 | P82: 1 | Q82: 15 | R82: 82 | S82: 54 | T82: 27 | U82: 27 | V82: 0 | W82: 0 | X82: 27 | Y82: 0 | Z82: 86 | AA82: 27 | AB82: 4644 | AC82: 0 | AD82: 0 | AE82: 0 | AF82: 0 | AG82: 0 | AH82: 0 | AI82: 0 | AN82: 1 | AO82: 0 | AP82: 0 | AQ82: 0 | AR82: 19 | AS82: 1 | AT82: 19 | AU82: 0 | AV82: 478 | AX82: 0.0026 | AY82: 0 | BA82: 0 | BB82: 4 | BD82: 3 | BE82: 3 | BF82: 3 | BH82: 60 | BJ82: 0 | BK82: 2026-09-16 04:03:09.960000000
A83: 2026-09-16 | B83: 15139629000194 | C83: Neoenergia Coelba | D83: COMPANHIA DE ELETRICIDADE DO ESTADO DA BAHIA | E83: Concessão | F83: 2026-05-01 | G83: 2915809 | H83: 9404 | I83: 9228 | J83: 9178 | K83: 100 | L83: 11 | M83: 0 | N83: 0 | O83: 2 | P83: 56 | Q83: 31 | R83: 49 | S83: 23 | T83: 7 | U83: 5 | V83: 2 | W83: 0 | X83: 16 | Y83: 0 | Z83: 75 | AA83: 23 | AB83: 9078 | AC83: 0 | AD83: 0 | AE83: 0 | AF83: 0 | AG83: 0 | AH83: 0 | AI83: 0 | AN83: 1 | AO83: 0 | AP83: 0 | AQ83: 4890 | AR83: 17 | AS83: 1 | AT83: 22 | AU83: 0 | AV83: 68 | AX83: 1.57 | AY83: 0 | BA83: 0 | BH83: 129 | BJ83: 0 | BK83: 2026-09-16 04:03:10.020000000
A84: 2026-09-16 | B84: 15139629000194 | C84: Neoenergia Coelba | D84: COMPANHIA DE ELETRICIDADE DO ESTADO DA BAHIA | E84: Concessão | F84: 2026-07-01 | G84: 2918357 | H84: 12865 | I84: 12544 | J84: 12566 | K84: 346 | L84: 129 | M84: 0 | N84: 0 | O84: 2 | P84: 121 | Q84: 94 | R84: 126 | S84: 101 | T84: 14 | U84: 10 | V84: 4 | W84: 0 | X84: 87 | Y84: 0 | Z84: 244 | AA84: 100 | AB84: 12220 | AC84: 0 | AD84: 0 | AE84: 0 | AF84: 0 | AG84: 0 | AH84: 0 | AI84: 0 | AN84: 0 | AO84: 1 | AP84: 0 | AQ84: 0 | AR84: 28 | AS84: 1 | AT84: 22 | AU84: 0 | AV84: 236 | AX84: 0.07 | AY84: 0 | BA84: 0 | BB84: 4 | BC84: 2 | BD84: 1 | BE84: 1 | BF84: 1 | BH84: 113 | BJ84: 0 | BK84: 2026-09-16 04:03:10.053000000
A85: 2026-09-16 | B85: 15139629000194 | C85: Neoenergia Coelba | D85: COMPANHIA DE ELETRICIDADE DO ESTADO DA BAHIA | E85: Concessão | F85: 2023-08-01 | G85: 2927101 | H85: 3923 | I85: 3879 | J85: 3888 | K85: 67 | L85: 1 | M85: 0 | N85: 0 | O85: 1 | P85: 32 | Q85: 33 | R85: 23 | S85: 4 | T85: 4 | U85: 3 | V85: 1 | W85: 0 | X85: 0 | Y85: 0 | Z85: 50 | AA85: 16 | AB85: 3821 | AC85: 0 | AD85: 0 | AE85: 0 | AF85: 0 | AG85: 0 | AH85: 0 | AI85: 0 | AN85: 1 | AO85: 0 | AP85: 0 | AQ85: 0 | AR85: 4 | AS85: 1 | AT85: 23 | AU85: 0 | AV85: 6 | AX85: 1.24 | AY85: 0 | BA85: 0 | BB85: 7 | BC85: 7 | BD85: 9 | BE85: 10 | BF85: 6 | BH85: 67 | BJ85: 0 | BK85: 2026-09-16 04:03:09.927000000
A86: 2026-09-16 | B86: 15139629000194 | C86: Neoenergia Coelba | D86: COMPANHIA DE ELETRICIDADE DO ESTADO DA BAHIA | E86: Concessão | F86: 2024-06-01 | G86: 2910057 | H86: 28821 | I86: 28423 | J86: 28476 | K86: 835 | L86: 5 | M86: 0 | N86: 0 | O86: 4 | P86: 154 | Q86: 672 | R86: 629 | S86: 246 | T86: 242 | U86: 242 | V86: 0 | W86: 0 | X86: 4 | Y86: 0 | Z86: 391 | AA86: 440 | AB86: 27641 | AC86: 0 | AD86: 0 | AE86: 0 | AF86: 0 | AG86: 0 | AH86: 0 | AI86: 0 | AN86: 21 | AO86: 26 | AP86: 1755 | AQ86: 8882.86 | AR86: 153 | AS86: 1 | AT86: 19 | AU86: 0 | AV86: 939 | AX86: 0.0041 | AY86: 0 | BA86: 0 | BB86: 67 | BC86: 44 | BD86: 5 | BE86: 9 | BF86: 2 | BG86: 2 | BH86: 297 | BJ86: 0 | BK86: 2026-09-16 04:03:09.960000000
A87: 2026-09-16 | B87: 15139629000194 | C87: Neoenergia Coelba | D87: COMPANHIA DE ELETRICIDADE DO ESTADO DA BAHIA | E87: Concessão | F87: 2026-05-01 | G87: 2915700 | H87: 3576 | I87: 3486 | J87: 3492 | K87: 145 | L87: 113 | M87: 0 | N87: 0 | O87: 1 | P87: 27 | Q87: 4 | R87: 17 | S87: 118 | T87: 5 | U87: 5 | V87: 0 | W87: 0 | X87: 113 | Y87: 0 | Z87: 81 | AA87: 63 | AB87: 3346 | AC87: 1 | AD87: 0 | AE87: 1 | AF87: 0 | AG87: 0 | AH87: 0 | AI87: 0 | AN87: 0 | AO87: 0 | AP87: 0 | AQ87: 0 | AR87: 11 | AS87: 1 | AT87: 22 | AU87: 0 | AV87: 42 | AX87: 0.33 | AY87: 0 | BA87: 0 | BH87: 45 | BJ87: 0 | BK87: 2026-09-16 04:03:10.020000000
A88: 2026-09-16 | B88: 15139629000194 | C88: Neoenergia Coelba | D88: COMPANHIA DE ELETRICIDADE DO ESTADO DA BAHIA | E88: Concessão | F88: 2026-07-01 | G88: 2918308 | H88: 6612 | I88: 6437 | J88: 6439 | K88: 93 | L88: 60 | M88: 0 | N88: 0 | O88: 1 | P88: 24 | Q88: 8 | R88: 98 | S88: 53 | T88: 4 | U88: 3 | V88: 1 | W88: 0 | X88: 49 | Y88: 0 | Z88: 66 | AA88: 26 | AB88: 6346 | AC88: 0 | AD88: 0 | AE88: 0 | AF88: 0 | AG88: 0 | AH88: 0 | AI88: 0 | AN88: 2 | AO88: 3 | AP88: 0 | AQ88: 0 | AR88: 24 | AS88: 1 | AT88: 22 | AU88: 0 | AV88: 205 | AX88: 0.25 | AY88: 0 | BA88: 0 | BB88: 3 | BC88: 1 | BD88: 3 | BE88: 4 | BH88: 91 | BJ88: 0 | BK88: 2026-09-16 04:03:10.053000000
A89: 2026-09-16 | B89: 15139629000194 | C89: Neoenergia Coelba | D89: COMPANHIA DE ELETRICIDADE DO ESTADO DA BAHIA | E89: Concessão | F89: 2023-08-01 | G89: 2929057 | H89: 7096 | I89: 6946 | J89: 6942 | K89: 37 | L89: 0 | M89: 0 | N89: 0 | O89: 2 | P89: 11 | Q89: 24 | R89: 16 | S89: 6 | T89: 5 | U89: 5 | V89: 0 | W89: 0 | X89: 1 | Y89: 0 | Z89: 31 | AA89: 4 | AB89: 6905 | AC89: 0 | AD89: 0 | AE89: 0 | AF89: 0 | AG89: 0 | AH89: 0 | AI89: 0 | AN89: 0 | AO89: 0 | AP89: 0 | AQ89: 0 | AR89: 16 | AS89: 1 | AT89: 23 | AU89: 0 | AV89: 88 | AX89: 3.21 | AY89: 0 | BA89: 0 | BB89: 4 | BC89: 2 | BD89: 5 | BE89: 7 | BF89: 5 | BH89: 50 | BJ89: 0 | BK89: 2026-09-16 04:03:09.927000000
A90: 2026-09-16 | B90: 15139629000194 | C90: Neoenergia Coelba | D90: COMPANHIA DE ELETRICIDADE DO ESTADO DA BAHIA | E90: Concessão | F90: 2024-06-01 | G90: 2910107 | H90: 6184 | I90: 6026 | J90: 6035 | K90: 42 | L90: 7 | M90: 0 | N90: 0 | O90: 3 | P90: 11 | Q90: 21 | R90: 58 | S90: 6 | T90: 5 | U90: 5 | V90: 0 | W90: 0 | X90: 1 | Y90: 0 | Z90: 33 | AA90: 6 | AB90: 5993 | AC90: 0 | AD90: 0 | AE90: 0 | AF90: 0 | AG90: 0 | AH90: 0 | AI90: 0 | AN90: 1 | AO90: 1 | AP90: 0 | AQ90: 0 | AR90: 74 | AS90: 1 | AT90: 19 | AU90: 0 | AV90: 93 | AX90: 0.0027 | AY90: 0 | BA90: 0 | BB90: 19 | BC90: 4 | BD90: 4 | BE90: 13 | BF90: 4 | BH90: 28 | BJ90: 0 | BK90: 2026-09-16 04:03:09.960000000
A91: 2026-09-16 | B91: 15139629000194 | C91: Neoenergia Coelba | D91: COMPANHIA DE ELETRICIDADE DO ESTADO DA BAHIA | E91: Concessão | F91: 2026-05-01 | G91: 2915601 | H91: 27056 | I91: 26472 | J91: 26274 | K91: 777 | L91: 582 | M91: 0 | N91: 0 | O91: 8 | P91: 70 | Q91: 117 | R91: 525 | S91: 128 | T91: 27 | U91: 26 | V91: 1 | W91: 0 | X91: 101 | Y91: 0 | Z91: 596 | AA91: 173 | AB91: 25497 | AC91: 0 | AD91: 0 | AE91: 0 | AF91: 0 | AG91: 0 | AH91: 0 | AI91: 0 | AN91: 9 | AO91: 4 | AP91: 0 | AQ91: 1230 | AR91: 71 | AS91: 2 | AT91: 22 | AU91: 0 | AV91: 362 | AX91: 0.67 | AY91: 0 | BA91: 0 | BB91: 13 | BC91: 4 | BD91: 2 | BE91: 2 | BH91: 220 | BJ91: 0 | BK91: 2026-09-16 04:03:10.020000000
A92: 2026-09-16 | B92: 15139629000194 | C92: Neoenergia Coelba | D92: COMPANHIA DE ELETRICIDADE DO ESTADO DA BAHIA | E92: Concessão | F92: 2026-07-01 | G92: 2918100 | H92: 18629 | I92: 18260 | J92: 18212 | K92: 221 | L92: 28 | M92: 0 | N92: 0 | O92: 1 | P92: 109 | Q92: 83 | R92: 191 | S92: 43 | T92: 17 | U92: 17 | V92: 0 | W92: 0 | X92: 26 | Y92: 0 | Z92: 166 | AA92: 54 | AB92: 17991 | AC92: 0 | AD92: 0 | AE92: 0 | AF92: 0 | AG92: 0 | AH92: 0 | AI92: 0 | AN92: 0 | AO92: 1 | AP92: 0 | AQ92: 0 | AR92: 76 | AS92: 1 | AT92: 22 | AU92: 0 | AV92: 310 | AX92: 0.2 | AY92: 0 | BA92: 0 | BB92: 51 | BC92: 19 | BD92: 10 | BE92: 11 | BF92: 2 | BH92: 238 | BJ92: 0 | BK92: 2026-09-16 04:03:10.053000000
A93: 2026-09-16 | B93: 15139629000194 | C93: Neoenergia Coelba | D93: COMPANHIA DE ELETRICIDADE DO ESTADO DA BAHIA | E93: Concessão | F93: 2023-08-01 | G93: 2929008 | H93: 4285 | I93: 4227 | J93: 4257 | K93: 61 | L93: 12 | M93: 0 | N93: 0 | O93: 3 | P93: 25 | Q93: 21 | R93: 17 | S93: 7 | T93: 5 | U93: 5 | V93: 0 | W93: 0 | X93: 2 | Y93: 0 | Z93: 43 | AA93: 15 | AB93: 4196 | AC93: 0 | AD93: 0 | AE93: 0 | AF93: 0 | AG93: 0 | AH93: 0 | AI93: 0 | AN93: 2 | AO93: 1 | AP93: 0 | AQ93: 0 | AR93: 19 | AS93: 1 | AT93: 23 | AU93: 0 | AV93: 186 | AX93: 9.81 | AY93: 0 | BA93: 0 | BB93: 10 | BC93: 2 | BE93: 1 | BH93: 20 | BJ93: 0 | BK93: 2026-09-16 04:03:09.927000000
A94: 2026-09-16 | B94: 15139629000194 | C94: Neoenergia Coelba | D94: COMPANHIA DE ELETRICIDADE DO ESTADO DA BAHIA | E94: Concessão | F94: 2024-06-01 | G94: 2908200 | H94: 8811 | I94: 8650 | J94: 8650 | K94: 103 | L94: 33 | M94: 0 | N94: 0 | O94: 2 | P94: 31 | Q94: 37 | R94: 159 | S94: 43 | T94: 35 | U94: 33 | V94: 2 | W94: 0 | X94: 8 | Y94: 0 | Z94: 81 | AA94: 20 | AB94: 8547 | AC94: 0 | AD94: 0 | AE94: 0 | AF94: 0 | AG94: 0 | AH94: 0 | AI94: 0 | AN94: 0 | AO94: 2 | AP94: 0 | AQ94: 0 | AR94: 33 | AS94: 1 | AT94: 19 | AU94: 0 | AV94: 53 | AX94: 0.0089 | AY94: 0 | BA94: 0 | BB94: 1 | BD94: 6 | BE94: 8 | BF94: 6 | BH94: 201 | BJ94: 0 | BK94: 2026-09-16 04:03:09.960000000
A95: 2026-09-16 | B95: 15139629000194 | C95: Neoenergia Coelba | D95: COMPANHIA DE ELETRICIDADE DO ESTADO DA BAHIA | E95: Concessão | F95: 2026-05-01 | G95: 2915502 | H95: 9244 | I95: 9054 | J95: 9084 | K95: 129 | L95: 33 | M95: 0 | N95: 0 | O95: 1 | P95: 56 | Q95: 39 | R95: 118 | S95: 63 | T95: 39 | U95: 38 | V95: 1 | W95: 0 | X95: 24 | Y95: 0 | Z95: 101 | AA95: 27 | AB95: 8955 | AC95: 0 | AD95: 0 | AE95: 0 | AF95: 0 | AG95: 0 | AH95: 0 | AI95: 0 | AN95: 3 | AO95: 2 | AP95: 0 | AQ95: 0 | AR95: 49 | AS95: 1 | AT95: 22 | AU95: 0 | AV95: 241 | AX95: 0.12 | AY95: 0 | BA95: 0 | BB95: 1 | BH95: 78 | BJ95: 0 | BK95: 2026-09-16 04:03:10.020000000
A96: 2026-09-16 | B96: 15139629000194 | C96: Neoenergia Coelba | D96: COMPANHIA DE ELETRICIDADE DO ESTADO DA BAHIA | E96: Concessão | F96: 2026-07-01 | G96: 2918209 | H96: 7031 | I96: 6806 | J96: 6828 | K96: 67 | L96: 1 | M96: 0 | N96: 0 | O96: 1 | P96: 37 | Q96: 28 | R96: 54 | S96: 20 | T96: 16 | U96: 13 | V96: 3 | W96: 0 | X96: 4 | Y96: 0 | Z96: 56 | AA96: 10 | AB96: 6761 | AC96: 0 | AD96: 0 | AE96: 0 | AF96: 0 | AG96: 0 | AH96: 0 | AI96: 0 | AN96: 1 | AO96: 3 | AP96: 0 | AQ96: 0 | AR96: 8 | AS96: 1 | AT96: 22 | AU96: 0 | AV96: 111 | AX96: 0.85 | AY96: 0 | BA96: 0 | BB96: 2 | BC96: 1 | BD96: 1 | BE96: 1 | BH96: 31 | BJ96: 0 | BK96: 2026-09-16 04:03:10.053000000
A97: 2026-09-16 | B97: 15139629000194 | C97: Neoenergia Coelba | D97: COMPANHIA DE ELETRICIDADE DO ESTADO DA BAHIA | E97: Concessão | F97: 2023-08-01 | G97: 2929107 | H97: 8574 | I97: 8362 | J97: 8377 | K97: 53 | L97: 24 | M97: 0 | N97: 0 | O97: 4 | P97: 0 | Q97: 25 | R97: 21 | S97: 9 | T97: 9 | U97: 9 | V97: 0 | W97: 0 | X97: 0 | Y97: 0 | Z97: 40 | AA97: 9 | AB97: 8324 | AC97: 0 | AD97: 0 | AE97: 0 | AF97: 0 | AG97: 0 | AH97: 0 | AI97: 0 | AN97: 4 | AO97: 2 | AP97: 0 | AQ97: 0 | AR97: 8 | AS97: 1 | AT97: 23 | AU97: 0 | AV97: 200 | AX97: 12.35 | AY97: 0 | BA97: 0 | BB97: 3 | BC97: 1 | BE97: 1 | BH97: 2 | BJ97: 0 | BK97: 2026-09-16 04:03:09.927000000
A98: 2026-09-16 | B98: 15139629000194 | C98: Neoenergia Coelba | D98: COMPANHIA DE ELETRICIDADE DO ESTADO DA BAHIA | E98: Concessão | F98: 2024-06-01 | G98: 2908309 | H98: 7616 | I98: 7532 | J98: 7531 | K98: 45 | L98: 1 | M98: 0 | N98: 0 | O98: 7 | P98: 18 | Q98: 19 | R98: 46 | S98: 14 | T98: 12 | U98: 2 | V98: 10 | W98: 0 | X98: 2 | Y98: 0 | Z98: 32 | AA98: 6 | AB98: 7486 | AC98: 0 | AD98: 0 | AE98: 0 | AF98: 0 | AG98: 0 | AH98: 0 | AI98: 0 | AN98: 4 | AO98: 4 | AP98: 0 | AQ98: 0 | AR98: 22 | AS98: 1 | AT98: 19 | AU98: 0 | AV98: 79 | AX98: 0.0088 | AY98: 0 | BA98: 0 | BB98: 6 | BC98: 1 | BD98: 3 | BE98: 4 | BF98: 2 | BH98: 152 | BJ98: 0 | BK98: 2026-09-16 04:03:09.960000000
A99: 2026-09-16 | B99: 15139629000194 | C99: Neoenergia Coelba | D99: COMPANHIA DE ELETRICIDADE DO ESTADO DA BAHIA | E99: Concessão | F99: 2026-05-01 | G99: 2915403 | H99: 2632 | I99: 2602 | J99: 2577 | K99: 51 | L99: 23 | M99: 0 | N99: 0 | O99: 1 | P99: 19 | Q99: 8 | R99: 8 | S99: 47 | T99: 2 | U99: 2 | V99: 0 | W99: 0 | X99: 45 | Y99: 0 | Z99: 36 | AA99: 14 | AB99: 2526 | AC99: 0 | AD99: 0 | AE99: 0 | AF99: 0 | AG99: 0 | AH99: 0 | AI99: 0 | AN99: 1 | AO99: 0 | AP99: 0 | AQ99: 0 | AR99: 9 | AS99: 1 | AT99: 22 | AU99: 0 | AV99: 77 | AX99: 0.55 | AY99: 0 | BA99: 0 | BB99: 1 | BH99: 24 | BJ99: 0 | BK99: 2026-09-16 04:03:10.020000000
A100: 2026-09-16 | B100: 15139629000194 | C100: Neoenergia Coelba | D100: COMPANHIA DE ELETRICIDADE DO ESTADO DA BAHIA | E100: Concessão | F100: 2026-07-01 | G100: 2918001 | H100: 78424 | I100: 76877 | J100: 76872 | K100: 747 | L100: 44 | M100: 0 | N100: 0 | O100: 25 | P100: 417 | Q100: 261 | R100: 1874 | S100: 232 | T100: 187 | U100: 185 | V100: 2 | W100: 0 | X100: 45 | Y100: 0 | Z100: 645 | AA100: 77 | AB100: 76124 | AC100: 1 | AD100: 0 | AE100: 1 | AF100: 0 | AG100: 0 | AH100: 0 | AI100: 0 | AN100: 23 | AO100: 21 | AP100: 7979.85 | AQ100: 2880 | AR100: 401 | AS100: 1 | AT100: 22 | AU100: 0 | AV100: 2427 | AX100: 4.57 | AY100: 0 | BA100: 0 | BB100: 125 | BC100: 27 | BD100: 22 | BE100: 31 | BF100: 7 | BH100: 341 | BJ100: 0 | BK100: 2026-09-16 04:03:10.053000000
...

Sheet ANEEL_SAMP
A1: ← LEIA-ME | B1: Mercado de energia por classe de consumo (kWh, kW, R$); sem município | C1: Origem: amostras/aneel_4.3_samp_mercado_COELBA_amostra.csv
A2: DatGeracaoConjuntoDados | B2: NumCNPJAgenteDistribuidora | C2: SigAgenteDistribuidora | D2: NomAgenteDistribuidora | E2: NomTipoMercado | F2: DscModalidadeTarifaria | G2: DscSubGrupoTarifario | H2: DscClasseConsumoMercado | I2: DscSubClasseConsumidor | J2: DscDetalheConsumidor | K2: IdeNucleoCeg | L2: NumCNPJAgenteAcessante | M2: NomAgenteAcessante | N2: DscPostoTarifario | O2: DscOpcaoEnergia | P2: DscDetalheMercado | Q2: DatCompetencia | R2: VlrMercado
A3: 2026-09-15T00:00:00.000 | B3: 15139629000194 | C3: COELBA | D3: COMPANHIA DE ELETRICIDADE DO ESTADO DA BAHIA COELBA | E3: Sistema Individual - Regular | F3: Energia Fotovoltaica (Res. 083/2004) | G3: B1 | H3: Residencial | I3: Residencial | J3: Não se aplica | K3: 0 | L3: 37121669900.0 | M3: Não se aplica | N3: Não se aplica | O3: CATIVO | P3: ICMS (R$) | Q3: 2024-01-01T00:00:00.000 | R3: 31581.32
A4: 2026-09-15T00:00:00.000 | B4: 15139629000194 | C4: COELBA | D4: COMPANHIA DE ELETRICIDADE DO ESTADO DA BAHIA COELBA | E4: Regular | F4: Convencional | G4: B1 | H4: Residencial | I4: Residencial baixa renda – faixa 01 | J4: Não se aplica | K4: 0 | L4: 37121669900.0 | M4: Não se aplica | N4: Não se aplica | O4: CATIVO | P4: ICMS (R$) | Q4: 2024-01-01T00:00:00.000 | R4: 10278774
A5: 2026-09-15T00:00:00.000 | B5: 15139629000194 | C5: COELBA | D5: COMPANHIA DE ELETRICIDADE DO ESTADO DA BAHIA COELBA | E5: Refaturamento - Regular | F5: Azul | G5: A3 | H5: Industrial | I5: Não se aplica | J5: Fonte incentivada | K5: 0 | M5: Não se aplica | N5: Fora ponta | O5: LIVRE | P5: Demanda Faturada (kW) | Q5: 2024-01-01T00:00:00.000 | R5: -12810
A6: 2026-09-15T00:00:00.000 | B6: 15139629000194 | C6: COELBA | D6: COMPANHIA DE ELETRICIDADE DO ESTADO DA BAHIA COELBA | E6: Regular | F6: Geração | G6: A3a | H6: Não se aplica | I6: Não se aplica | J6: Não se aplica | K6: 35426 | L6: 0.0 | M6: TAPUIAS | N6: Não se aplica | O6: GERAÇÃO | P6: Demanda Faturada (kW) | Q6: 2024-01-01T00:00:00.000 | R6: 1800
A7: 2026-09-15T00:00:00.000 | B7: 15139629000194 | C7: COELBA | D7: COMPANHIA DE ELETRICIDADE DO ESTADO DA BAHIA COELBA | E7: Sistema Individual - Refaturamento | F7: Energia Fotovoltaica (Res. 083/2004) | G7: B1 | H7: Residencial | I7: Residencial | J7: Não se aplica | K7: 0 | L7: 37121669900.0 | M7: Não se aplica | N7: Não se aplica | O7: CATIVO | P7: COFINS (R$) | Q7: 2024-01-01T00:00:00.000 | R7: -22.45
A8: 2026-09-15T00:00:00.000 | B8: 15139629000194 | C8: COELBA | D8: COMPANHIA DE ELETRICIDADE DO ESTADO DA BAHIA COELBA | E8: Refaturamento - Regular | F8: Convencional | G8: B1 | H8: Residencial | I8: Residencial baixa renda – faixa 04 | J8: Não se aplica | K8: 0 | L8: 37121669900.0 | M8: Não se aplica | N8: Não se aplica | O8: CATIVO | P8: COFINS (R$) | Q8: 2024-01-01T00:00:00.000 | R8: -2060.06
A9: 2026-09-15T00:00:00.000 | B9: 15139629000194 | C9: COELBA | D9: COMPANHIA DE ELETRICIDADE DO ESTADO DA BAHIA COELBA | E9: Refaturamento - Regular | F9: Azul | G9: A3 | H9: Industrial | I9: Não se aplica | J9: Fonte incentivada | K9: 0 | M9: Não se aplica | N9: Ponta | O9: LIVRE | P9: Receita Demanda (R$) | Q9: 2024-01-01T00:00:00.000 | R9: -299552.59
A10: 2026-09-15T00:00:00.000 | B10: 15139629000194 | C10: COELBA | D10: COMPANHIA DE ELETRICIDADE DO ESTADO DA BAHIA COELBA | E10: Regular | F10: Geração | G10: A3a | H10: Não se aplica | I10: Não se aplica | J10: Não se aplica | K10: 35426 | L10: 0.0 | M10: TAPUIAS | N10: Não se aplica | O10: GERAÇÃO | P10: Demanda Contratada kW | Q10: 2024-01-01T00:00:00.000 | R10: 1800
A11: 2026-09-15T00:00:00.000 | B11: 15139629000194 | C11: COELBA | D11: COMPANHIA DE ELETRICIDADE DO ESTADO DA BAHIA COELBA | E11: Sistema Individual - Regular | F11: Energia Fotovoltaica (Res. 083/2004) | G11: B1 | H11: Residencial | I11: Residencial baixa renda – faixa 01 | J11: Não se aplica | K11: 0 | L11: 37121669900.0 | M11: Não se aplica | N11: Não se aplica | O11: CATIVO | P11: Energia TE (kWh) | Q11: 2024-01-01T00:00:00.000 | R11: 20323
A12: 2026-09-15T00:00:00.000 | B12: 15139629000194 | C12: COELBA | D12: COMPANHIA DE ELETRICIDADE DO ESTADO DA BAHIA COELBA | E12: Sistema de Compensação GD I | F12: Convencional | G12: B1 | H12: Residencial | I12: Residencial baixa renda – faixa 04 | J12: Não se aplica | K12: 0 | L12: 37121669900.0 | M12: Não se aplica | N12: Não se aplica | O12: CATIVO | P12: PIS/PASEP (R$) | Q12: 2024-01-01T00:00:00.000 | R12: 2828
A13: 2026-09-15T00:00:00.000 | B13: 15139629000194 | C13: COELBA | D13: COMPANHIA DE ELETRICIDADE DO ESTADO DA BAHIA COELBA | E13: Refaturamento - Regular | F13: Azul | G13: A3 | H13: Industrial | I13: Não se aplica | J13: Fonte incentivada | K13: 0 | M13: Não se aplica | N13: Fora ponta | O13: LIVRE | P13: Desconto Demanda % | Q13: 2024-01-01T00:00:00.000 | R13: 33.073049
A14: 2026-09-15T00:00:00.000 | B14: 15139629000194 | C14: COELBA | D14: COMPANHIA DE ELETRICIDADE DO ESTADO DA BAHIA COELBA | E14: Regular | F14: Geração | G14: A2 | H14: Não se aplica | I14: Não se aplica | J14: Não se aplica | K14: 31771 | L14: 0.0 | M14: Ventos da Bahia VIII | N14: Não se aplica | O14: GERAÇÃO | P14: Desconto Demanda % | Q14: 2024-01-01T00:00:00.000 | R14: 50
A15: 2026-09-15T00:00:00.000 | B15: 15139629000194 | C15: COELBA | D15: COMPANHIA DE ELETRICIDADE DO ESTADO DA BAHIA COELBA | E15: Sistema Individual - Regular | F15: Energia Fotovoltaica (Res. 083/2004) | G15: B1 | H15: Residencial | I15: Residencial baixa renda – faixa 01 | J15: Não se aplica | K15: 0 | L15: 37121669900.0 | M15: Não se aplica | N15: Não se aplica | O15: CATIVO | P15: Receita Energia (R$) | Q15: 2024-01-01T00:00:00.000 | R15: 5108.68
A16: 2026-09-15T00:00:00.000 | B16: 15139629000194 | C16: COELBA | D16: COMPANHIA DE ELETRICIDADE DO ESTADO DA BAHIA COELBA | E16: Refaturamento - Regular | F16: Branca | G16: B1 | H16: Residencial | I16: Residencial | J16: Não se aplica | K16: 0 | L16: 37121669900.0 | M16: Não se aplica | N16: Ponta | O16: CATIVO | P16: Energia TE (kWh) | Q16: 2024-01-01T00:00:00.000 | R16: -2895
A17: 2026-09-15T00:00:00.000 | B17: 15139629000194 | C17: COELBA | D17: COMPANHIA DE ELETRICIDADE DO ESTADO DA BAHIA COELBA | E17: Refaturamento - Regular | F17: Azul | G17: A3 | H17: Industrial | I17: Não se aplica | J17: Fonte incentivada | K17: 0 | M17: Não se aplica | N17: Não se aplica | O17: LIVRE | P17: Energia TUSD (kWh) | Q17: 2024-01-01T00:00:00.000 | R17: -6199780
A18: 2026-09-15T00:00:00.000 | B18: 15139629000194 | C18: COELBA | D18: COMPANHIA DE ELETRICIDADE DO ESTADO DA BAHIA COELBA | E18: Regular | F18: Geração | G18: A2 | H18: Não se aplica | I18: Não se aplica | J18: Não se aplica | K18: 31771 | L18: 0.0 | M18: Ventos da Bahia VIII | N18: Não se aplica | O18: GERAÇÃO | P18: PIS/COFINS (R$) | Q18: 2024-01-01T00:00:00.000 | R18: 4167.59
A19: 2026-09-15T00:00:00.000 | B19: 15139629000194 | C19: COELBA | D19: COMPANHIA DE ELETRICIDADE DO ESTADO DA BAHIA COELBA | E19: Sistema Individual - Regular | F19: Energia Fotovoltaica (Res. 083/2004) | G19: B1 | H19: Residencial | I19: Residencial baixa renda – faixa 01 | J19: Não se aplica | K19: 0 | L19: 37121669900.0 | M19: Não se aplica | N19: Não se aplica | O19: CATIVO | P19: ICMS (R$) | Q19: 2024-01-01T00:00:00.000 | R19: 37.91
A20: 2026-09-15T00:00:00.000 | B20: 15139629000194 | C20: COELBA | D20: COMPANHIA DE ELETRICIDADE DO ESTADO DA BAHIA COELBA | E20: Sistema Individual - Regular | F20: Energia Fotovoltaica (Res. 083/2004) | G20: B1 | H20: Residencial | I20: Residencial | J20: Não se aplica | K20: 0 | L20: 37121669900.0 | M20: Não se aplica | N20: Não se aplica | O20: CATIVO | P20: Número de consumidores | Q20: 2024-01-01T00:00:00.000 | R20: 8789
A21: 2026-09-15T00:00:00.000 | B21: 15139629000194 | C21: COELBA | D21: COMPANHIA DE ELETRICIDADE DO ESTADO DA BAHIA COELBA | E21: Refaturamento - Regular | F21: Azul | G21: A4 | H21: Industrial | I21: Não se aplica | J21: Fonte incentivada | K21: 0 | M21: Não se aplica | N21: Não se aplica | O21: LIVRE | P21: ICMS (R$) | Q21: 2024-01-01T00:00:00.000 | R21: -66174.23
A22: 2026-09-15T00:00:00.000 | B22: 15139629000194 | C22: COELBA | D22: COMPANHIA DE ELETRICIDADE DO ESTADO DA BAHIA COELBA | E22: Regular | F22: Geração | G22: A2 | H22: Não se aplica | I22: Não se aplica | J22: Não se aplica | K22: 31771 | L22: 0.0 | M22: Ventos da Bahia VIII | N22: Não se aplica | O22: GERAÇÃO | P22: Demanda Faturada (kW) | Q22: 2024-01-01T00:00:00.000 | R22: 26374
A23: 2026-09-15T00:00:00.000 | B23: 15139629000194 | C23: COELBA | D23: COMPANHIA DE ELETRICIDADE DO ESTADO DA BAHIA COELBA | E23: Sistema de Compensação GD I | F23: Branca | G23: B1 | H23: Residencial | I23: Residencial | J23: Não se aplica | K23: 0 | L23: 37121669900.0 | M23: Não se aplica | N23: Ponta | O23: CATIVO | P23: Energia TE (kWh) | Q23: 2024-01-01T00:00:00.000 | R23: 8115
A24: 2026-09-15T00:00:00.000 | B24: 15139629000194 | C24: COELBA | D24: COMPANHIA DE ELETRICIDADE DO ESTADO DA BAHIA COELBA | E24: Sistema Individual - Regular | F24: Energia Fotovoltaica (Res. 083/2004) | G24: B1 | H24: Residencial | I24: Residencial | J24: Não se aplica | K24: 0 | L24: 37121669900.0 | M24: Não se aplica | N24: Não se aplica | O24: CATIVO | P24: PIS/PASEP (R$) | Q24: 2024-01-01T00:00:00.000 | R24: 1117.13
A25: 2026-09-15T00:00:00.000 | B25: 15139629000194 | C25: COELBA | D25: COMPANHIA DE ELETRICIDADE DO ESTADO DA BAHIA COELBA | E25: Refaturamento - Regular | F25: Verde | G25: A4 | H25: Industrial | I25: Não se aplica | J25: Fonte incentivada | K25: 0 | M25: Não se aplica | N25: Não se aplica | O25: LIVRE | P25: Número de Consumidores | Q25: 2024-01-01T00:00:00.000 | R25: 12
A26: 2026-09-15T00:00:00.000 | B26: 15139629000194 | C26: COELBA | D26: COMPANHIA DE ELETRICIDADE DO ESTADO DA BAHIA COELBA | E26: Regular | F26: Geração | G26: A2 | H26: Não se aplica | I26: Não se aplica | J26: Não se aplica | K26: 31771 | L26: 0.0 | M26: Ventos da Bahia VIII | N26: Não se aplica | O26: GERAÇÃO | P26: Demanda Contratada kW | Q26: 2024-01-01T00:00:00.000 | R26: 26210
A27: 2026-09-15T00:00:00.000 | B27: 15139629000194 | C27: COELBA | D27: COMPANHIA DE ELETRICIDADE DO ESTADO DA BAHIA COELBA | E27: Sistema de Compensação GD I | F27: Branca | G27: B1 | H27: Residencial | I27: Residencial | J27: Não se aplica | K27: 0 | L27: 37121669900.0 | M27: Não se aplica | N27: Não se aplica | O27: CATIVO | P27: Número de consumidores | Q27: 2024-01-01T00:00:00.000 | R27: 255
A28: 2026-09-15T00:00:00.000 | B28: 15139629000194 | C28: COELBA | D28: COMPANHIA DE ELETRICIDADE DO ESTADO DA BAHIA COELBA | E28: Sistema Individual - Regular | F28: Energia Fotovoltaica (Res. 083/2004) | G28: B1 | H28: Residencial | I28: Residencial baixa renda – faixa 01 | J28: Não se aplica | K28: 0 | L28: 37121669900.0 | M28: Não se aplica | N28: Não se aplica | O28: CATIVO | P28: Número de consumidores | Q28: 2024-01-01T00:00:00.000 | R28: 1544
A29: 2026-09-15T00:00:00.000 | B29: 15139629000194 | C29: COELBA | D29: COMPANHIA DE ELETRICIDADE DO ESTADO DA BAHIA COELBA | E29: Refaturamento - Regular | F29: Verde | G29: A4 | H29: Industrial | I29: Não se aplica | J29: Fonte incentivada | K29: 0 | M29: Não se aplica | N29: Ponta | O29: LIVRE | P29: Receita Energia (R$) | Q29: 2024-01-01T00:00:00.000 | R29: -264960.43
A30: 2026-09-15T00:00:00.000 | B30: 15139629000194 | C30: COELBA | D30: COMPANHIA DE ELETRICIDADE DO ESTADO DA BAHIA COELBA | E30: Regular | F30: Geração | G30: A2 | H30: Não se aplica | I30: Não se aplica | J30: Não se aplica | K30: 31771 | L30: 0.0 | M30: Ventos da Bahia VIII | N30: Não se aplica | O30: GERAÇÃO | P30: Receita Demanda (R$) | Q30: 2024-01-01T00:00:00.000 | R30: 75824.82
A31: 2026-09-15T00:00:00.000 | B31: 15139629000194 | C31: COELBA | D31: COMPANHIA DE ELETRICIDADE DO ESTADO DA BAHIA COELBA | E31: Refaturamento - Regular | F31: Convencional | G31: B1 | H31: Residencial | I31: Residencial baixa renda – faixa 04 | J31: Não se aplica | K31: 0 | L31: 37121669900.0 | M31: Não se aplica | N31: Não se aplica | O31: CATIVO | P31: Receita Bandeiras (R$) | Q31: 2024-01-01T00:00:00.000 | R31: -811.26
A32: 2026-09-15T00:00:00.000 | B32: 15139629000194 | C32: COELBA | D32: COMPANHIA DE ELETRICIDADE DO ESTADO DA BAHIA COELBA | E32: Refaturamento - Regular | F32: Branca | G32: B1 | H32: Residencial | I32: Residencial | J32: Não se aplica | K32: 0 | L32: 37121669900.0 | M32: Não se aplica | N32: Não se aplica | O32: CATIVO | P32: Número de consumidores | Q32: 2024-01-01T00:00:00.000 | R32: 7
A33: 2026-09-15T00:00:00.000 | B33: 15139629000194 | C33: COELBA | D33: COMPANHIA DE ELETRICIDADE DO ESTADO DA BAHIA COELBA | E33: Refaturamento - Regular | F33: Verde | G33: A4 | H33: Industrial | I33: Não se aplica | J33: Fonte incentivada | K33: 0 | M33: Não se aplica | N33: Ponta | O33: LIVRE | P33: Desconto Energia TUSD % | Q33: 2024-01-01T00:00:00.000 | R33: 31.864574
A34: 2026-09-15T00:00:00.000 | B34: 15139629000194 | C34: COELBA | D34: COMPANHIA DE ELETRICIDADE DO ESTADO DA BAHIA COELBA | E34: Regular | F34: Geração | G34: A3 | H34: Não se aplica | I34: Não se aplica | J34: Não se aplica | K34: 34387 | L34: 0.0 | M34: Sobrado 1 | N34: Não se aplica | O34: GERAÇÃO | P34: Demanda Faturada (kW) | Q34: 2024-01-01T00:00:00.000 | R34: 29900
A35: 2026-09-15T00:00:00.000 | B35: 15139629000194 | C35: COELBA | D35: COMPANHIA DE ELETRICIDADE DO ESTADO DA BAHIA COELBA | E35: Sistema de Compensação GD II | F35: Convencional | G35: B1 | H35: Residencial | I35: Residencial baixa renda – faixa 04 | J35: Não se aplica | K35: 0 | L35: 37121669900.0 | M35: Não se aplica | N35: Não se aplica | O35: CATIVO | P35: Energia Consumida (kWh) | Q35: 2024-01-01T00:00:00.000 | R35: 3123
A36: 2026-09-15T00:00:00.000 | B36: 15139629000194 | C36: COELBA | D36: COMPANHIA DE ELETRICIDADE DO ESTADO DA BAHIA COELBA | E36: Sistema de Compensação GD I | F36: Verde | G36: A4 | H36: Residencial | I36: Residencial | J36: Não se aplica | K36: 0 | L36: 37121669900.0 | M36: Não se aplica | N36: Fora ponta | O36: CATIVO | P36: Energia compensada (kWh) | Q36: 2024-01-01T00:00:00.000 | R36: 1797
A37: 2026-09-15T00:00:00.000 | B37: 15139629000194 | C37: COELBA | D37: COMPANHIA DE ELETRICIDADE DO ESTADO DA BAHIA COELBA | E37: Regular | F37: Verde | G37: A4 | H37: Industrial | I37: Não se aplica | J37: Fonte incentivada | K37: 0 | M37: Não se aplica | N37: Não se aplica | O37: LIVRE | P37: Número de Consumidores | Q37: 2024-01-01T00:00:00.000 | R37: 898
A38: 2026-09-15T00:00:00.000 | B38: 15139629000194 | C38: COELBA | D38: COMPANHIA DE ELETRICIDADE DO ESTADO DA BAHIA COELBA | E38: Regular | F38: Geração | G38: A3 | H38: Não se aplica | I38: Não se aplica | J38: Não se aplica | K38: 34387 | L38: 0.0 | M38: Sobrado 1 | N38: Não se aplica | O38: GERAÇÃO | P38: Desconto Demanda % | Q38: 2024-01-01T00:00:00.000 | R38: 50
A39: 2026-09-15T00:00:00.000 | B39: 15139629000194 | C39: COELBA | D39: COMPANHIA DE ELETRICIDADE DO ESTADO DA BAHIA COELBA | E39: Sistema de Compensação GD I | F39: Convencional | G39: B1 | H39: Residencial | I39: Residencial baixa renda – faixa 04 | J39: Não se aplica | K39: 0 | L39: 37121669900.0 | M39: Não se aplica | N39: Não se aplica | O39: CATIVO | P39: Energia compensada (kWh) | Q39: 2024-01-01T00:00:00.000 | R39: 1197758
A40: 2026-09-15T00:00:00.000 | B40: 15139629000194 | C40: COELBA | D40: COMPANHIA DE ELETRICIDADE DO ESTADO DA BAHIA COELBA | E40: Regular | F40: Branca | G40: B1 | H40: Residencial | I40: Residencial | J40: Não se aplica | K40: 0 | L40: 37121669900.0 | M40: Não se aplica | N40: Ponta | O40: CATIVO | P40: Energia TE (kWh) | Q40: 2024-01-01T00:00:00.000 | R40: 55103
A41: 2026-09-15T00:00:00.000 | B41: 15139629000194 | C41: COELBA | D41: COMPANHIA DE ELETRICIDADE DO ESTADO DA BAHIA COELBA | E41: Regular | F41: Verde | G41: A4 | H41: Industrial | I41: Não se aplica | J41: Fonte incentivada | K41: 0 | M41: Não se aplica | N41: Não se aplica | O41: LIVRE | P41: PIS/COFINS (R$) | Q41: 2024-01-01T00:00:00.000 | R41: 1724444.1
A42: 2026-09-15T00:00:00.000 | B42: 15139629000194 | C42: COELBA | D42: COMPANHIA DE ELETRICIDADE DO ESTADO DA BAHIA COELBA | E42: Regular | F42: Geração | G42: A3 | H42: Não se aplica | I42: Não se aplica | J42: Não se aplica | K42: 34387 | L42: 0.0 | M42: Sobrado 1 | N42: Não se aplica | O42: GERAÇÃO | P42: PIS/COFINS (R$) | Q42: 2024-01-01T00:00:00.000 | R42: 8028.17
A43: 2026-09-15T00:00:00.000 | B43: 15139629000194 | C43: COELBA | D43: COMPANHIA DE ELETRICIDADE DO ESTADO DA BAHIA COELBA | E43: Sistema de Compensação GD I | F43: Branca | G43: B1 | H43: Residencial | I43: Residencial | J43: Não se aplica | K43: 0 | L43: 37121669900.0 | M43: Não se aplica | N43: Intermediário | O43: CATIVO | P43: Receita Energia (R$) | Q43: 2024-01-01T00:00:00.000 | R43: 3081
A44: 2026-09-15T00:00:00.000 | B44: 15139629000194 | C44: COELBA | D44: COMPANHIA DE ELETRICIDADE DO ESTADO DA BAHIA COELBA | E44: Refaturamento - Regular | F44: Branca | G44: B1 | H44: Residencial | I44: Residencial | J44: Não se aplica | K44: 0 | L44: 37121669900.0 | M44: Não se aplica | N44: Fora ponta | O44: CATIVO | P44: Energia TE (kWh) | Q44: 2024-01-01T00:00:00.000 | R44: -3311
A45: 2026-09-15T00:00:00.000 | B45: 15139629000194 | C45: COELBA | D45: COMPANHIA DE ELETRICIDADE DO ESTADO DA BAHIA COELBA | E45: Regular | F45: Geração | G45: A3a | H45: Não se aplica | I45: Não se aplica | J45: Não se aplica | L45: 0.0 | M45: GD (GRUPO A) | N45: Não se aplica | O45: GERAÇÃO | P45: ICMS (R$) | Q45: 2024-01-01T00:00:00.000 | R45: 10929.91
A46: 2026-09-15T00:00:00.000 | B46: 15139629000194 | C46: COELBA | D46: COMPANHIA DE ELETRICIDADE DO ESTADO DA BAHIA COELBA | E46: Regular | F46: Geração | G46: A3 | H46: Não se aplica | I46: Não se aplica | J46: Não se aplica | K46: 34387 | L46: 0.0 | M46: Sobrado 1 | N46: Não se aplica | O46: GERAÇÃO | P46: Demanda Contratada kW | Q46: 2024-01-01T00:00:00.000 | R46: 29900
A47: 2026-09-15T00:00:00.000 | B47: 15139629000194 | C47: COELBA | D47: COMPANHIA DE ELETRICIDADE DO ESTADO DA BAHIA COELBA | E47: Refaturamento - Regular | F47: Branca | G47: B1 | H47: Residencial | I47: Residencial | J47: Não se aplica | K47: 0 | L47: 37121669900.0 | M47: Não se aplica | N47: Intermediário | O47: CATIVO | P47: Energia TE (kWh) | Q47: 2024-01-01T00:00:00.000 | R47: -1387
A48: 2026-09-15T00:00:00.000 | B48: 15139629000194 | C48: COELBA | D48: COMPANHIA DE ELETRICIDADE DO ESTADO DA BAHIA COELBA | E48: Refaturamento - Regular | F48: Convencional | G48: B1 | H48: Residencial | I48: Residencial baixa renda – faixa 04 | J48: Não se aplica | K48: 0 | L48: 37121669900.0 | M48: Não se aplica | N48: Não se aplica | O48: CATIVO | P48: ICMS (R$) | Q48: 2024-01-01T00:00:00.000 | R48: -14594.45
A49: 2026-09-15T00:00:00.000 | B49: 15139629000194 | C49: COELBA | D49: COMPANHIA DE ELETRICIDADE DO ESTADO DA BAHIA COELBA | E49: Regular | F49: Distribuição | G49: A4 | H49: Não se aplica | I49: Não se aplica | J49: Não se aplica | K49: 0 | L49: 6981180000116.0 | M49: CEMIG DISTRIBUIÇÃO S.A | N49: Fora ponta | O49: DISTRIBUIÇÃO | P49: Demanda Faturada (kW) | Q49: 2024-01-01T00:00:00.000 | R49: 80
A50: 2026-09-15T00:00:00.000 | B50: 15139629000194 | C50: COELBA | D50: COMPANHIA DE ELETRICIDADE DO ESTADO DA BAHIA COELBA | E50: Regular | F50: Geração | G50: A3 | H50: Não se aplica | I50: Não se aplica | J50: Não se aplica | K50: 34387 | L50: 0.0 | M50: Sobrado 1 | N50: Não se aplica | O50: GERAÇÃO | P50: Receita Demanda (R$) | Q50: 2024-01-01T00:00:00.000 | R50: 146063.6
A51: 2026-09-15T00:00:00.000 | B51: 15139629000194 | C51: COELBA | D51: COMPANHIA DE ELETRICIDADE DO ESTADO DA BAHIA COELBA | E51: Regular | F51: Verde | G51: A4 | H51: Comercial | I51: Não se aplica | J51: Não se aplica | K51: 0 | L51: 37121669900.0 | M51: Não se aplica | N51: Não se aplica | O51: CATIVO | P51: ICMS (R$) | Q51: 2024-01-01T00:00:00.000 | R51: 10478041
A52: 2026-09-15T00:00:00.000 | B52: 15139629000194 | C52: COELBA | D52: COMPANHIA DE ELETRICIDADE DO ESTADO DA BAHIA COELBA | E52: Regular | F52: Convencional | G52: B1 | H52: Residencial | I52: Residencial baixa renda – faixa 04 | J52: Não se aplica | K52: 0 | L52: 37121669900.0 | M52: Não se aplica | N52: Não se aplica | O52: CATIVO | P52: Energia TE (kWh) | Q52: 2024-01-01T00:00:00.000 | R52: 12338954
A53: 2026-09-15T00:00:00.000 | B53: 15139629000194 | C53: COELBA | D53: COMPANHIA DE ELETRICIDADE DO ESTADO DA BAHIA COELBA | E53: Regular | F53: Distribuição | G53: A4 | H53: Não se aplica | I53: Não se aplica | J53: Não se aplica | K53: 0 | L53: 6981180000116.0 | M53: CEMIG DISTRIBUIÇÃO S.A | N53: Ponta | O53: DISTRIBUIÇÃO | P53: Receita Demanda (R$) | Q53: 2024-01-01T00:00:00.000 | R53: 3782.39
A54: 2026-09-15T00:00:00.000 | B54: 15139629000194 | C54: COELBA | D54: COMPANHIA DE ELETRICIDADE DO ESTADO DA BAHIA COELBA | E54: Regular | F54: Geração | G54: A2 | H54: Não se aplica | I54: Não se aplica | J54: Não se aplica | K54: 31770 | L54: 0.0 | M54: Ventos da Bahia IV | N54: Não se aplica | O54: GERAÇÃO | P54: Receita Demanda (R$) | Q54: 2024-01-01T00:00:00.000 | R54: 59443.09
A55: 2026-09-15T00:00:00.000 | B55: 15139629000194 | C55: COELBA | D55: COMPANHIA DE ELETRICIDADE DO ESTADO DA BAHIA COELBA | E55: Regular | F55: Azul | G55: A3 | H55: Industrial | I55: Não se aplica | J55: Não se aplica | K55: 0 | L55: 37121669900.0 | M55: Não se aplica | N55: Ponta | O55: CATIVO | P55: Receita Ultrapassagem Demanda (R$) | Q55: 2024-01-01T00:00:00.000 | R55: 87936.98
A56: 2026-09-15T00:00:00.000 | B56: 15139629000194 | C56: COELBA | D56: COMPANHIA DE ELETRICIDADE DO ESTADO DA BAHIA COELBA | E56: Sistema de Compensação GD II | F56: Convencional | G56: B1 | H56: Residencial | I56: Residencial baixa renda – faixa 04 | J56: Não se aplica | K56: 0 | L56: 37121669900.0 | M56: Não se aplica | N56: Não se aplica | O56: CATIVO | P56: Receita Energia (R$) | Q56: 2024-01-01T00:00:00.000 | R56: 1045
A57: 2026-09-15T00:00:00.000 | B57: 15139629000194 | C57: COELBA | D57: COMPANHIA DE ELETRICIDADE DO ESTADO DA BAHIA COELBA | E57: Regular | F57: Distribuição | G57: A4 | H57: Não se aplica | I57: Não se aplica | J57: Não se aplica | K57: 0 | L57: 6981180000116.0 | M57: CEMIG DISTRIBUIÇÃO S.A | N57: Não se aplica | O57: DISTRIBUIÇÃO | P57: PIS/COFINS (R$) | Q57: 2024-01-01T00:00:00.000 | R57: 298.64
... A84: 2026-09-15T00:00:00.000 | B84: 15139629000194 | C84: COELBA | D84: COMPANHIA DE ELETRICIDADE DO ESTADO DA BAHIA COELBA | E84: Sistema Individual - Regular | F84: Energia Fotovoltaica (Res. 083/2004) | G84: B3 | H84: Comercial | I84: Não se aplica | J84: Não se aplica | K84: 0 | L84: 37121669900.0 | M84: Não se aplica | N84: Não se aplica | O84: CATIVO | P84: COFINS (R$) | Q84: 2024-01-01T00:00:00.000 | R84: 48.63
A85: 2026-09-15T00:00:00.000 | B85: 15139629000194 | C85: COELBA | D85: COMPANHIA DE ELETRICIDADE DO ESTADO DA BAHIA COELBA | E85: Regular | F85: Azul | G85: A2 | H85: Industrial | I85: Não se aplica | J85: Não se aplica | K85: 0 | M85: Não se aplica | N85: Fora ponta | O85: LIVRE | P85: Receita Ultrapassagem Demanda (R$) | Q85: 2024-01-01T00:00:00.000 | R85: 63552.8
A86: 2026-09-15T00:00:00.000 | B86: 15139629000194 | C86: COELBA | D86: COMPANHIA DE ELETRICIDADE DO ESTADO DA BAHIA COELBA | E86: Regular | F86: Geração | G86: A2 | H86: Não se aplica | I86: Não se aplica | J86: Não se aplica | K86: 29004 | L86: 0.0 | M86: Colino 1 | N86: Não se aplica | O86: GERAÇÃO | P86: Receita Demanda (R$) | Q86: 2024-01-01T00:00:00.000 | R86: 14520
A87: 2026-09-15T00:00:00.000 | B87: 15139629000194 | C87: COELBA | D87: COMPANHIA DE ELETRICIDADE DO ESTADO DA BAHIA COELBA | E87: Regular | F87: Azul | G87: A3a | H87: Industrial | I87: Não se aplica | J87: Não se aplica | K87: 0 | L87: 37121669900.0 | M87: Não se aplica | N87: Fora ponta | O87: CATIVO | P87: Receita Ultrapassagem Demanda (R$) | Q87: 2024-01-01T00:00:00.000 | R87: 1101.5
A88: 2026-09-15T00:00:00.000 | B88: 15139629000194 | C88: COELBA | D88: COMPANHIA DE ELETRICIDADE DO ESTADO DA BAHIA COELBA | E88: Regular | F88: Branca | G88: B3 | H88: Comercial | I88: Não se aplica | J88: Não se aplica | K88: 0 | L88: 37121669900.0 | M88: Não se aplica | N88: Não se aplica | O88: CATIVO | P88: Número de consumidores | Q88: 2024-01-01T00:00:00.000 | R88: 988
A89: 2026-09-15T00:00:00.000 | B89: 15139629000194 | C89: COELBA | D89: COMPANHIA DE ELETRICIDADE DO ESTADO DA BAHIA COELBA | E89: Regular | F89: Azul | G89: A2 | H89: Industrial | I89: Não se aplica | J89: Não se aplica | K89: 0 | M89: Não se aplica | N89: Não se aplica | O89: LIVRE | P89: Energia TUSD (kWh) | Q89: 2024-01-01T00:00:00.000 | R89: 12614182
A90: 2026-09-15T00:00:00.000 | B90: 15139629000194 | C90: COELBA | D90: COMPANHIA DE ELETRICIDADE DO ESTADO DA BAHIA COELBA | E90: Regular | F90: Geração | G90: A3 | H90: Não se aplica | I90: Não se aplica | J90: Não se aplica | K90: 33473 | L90: 0.0 | M90: Sertão Solar Barreiras IV | N90: Não se aplica | O90: GERAÇÃO | P90: Receita Demanda (R$) | Q90: 2024-01-01T00:00:00.000 | R90: 112630.61
A91: 2026-09-15T00:00:00.000 | B91: 15139629000194 | C91: COELBA | D91: COMPANHIA DE ELETRICIDADE DO ESTADO DA BAHIA COELBA | E91: Regular | F91: Azul | G91: A3a | H91: Industrial | I91: Não se aplica | J91: Não se aplica | K91: 0 | L91: 37121669900.0 | M91: Não se aplica | N91: Não se aplica | O91: CATIVO | P91: PIS/PASEP (R$) | Q91: 2024-01-01T00:00:00.000 | R91: 6358.57
A92: 2026-09-15T00:00:00.000 | B92: 15139629000194 | C92: COELBA | D92: COMPANHIA DE ELETRICIDADE DO ESTADO DA BAHIA COELBA | E92: Sistema de Compensação GD II | F92: Verde | G92: A4 | H92: Comercial | I92: Não se aplica | J92: Não se aplica | K92: 0 | L92: 37121669900.0 | M92: Não se aplica | N92: Ponta | O92: CATIVO | P92: Energia TE (kWh) | Q92: 2024-01-01T00:00:00.000 | R92: 8253
A93: 2026-09-15T00:00:00.000 | B93: 15139629000194 | C93: COELBA | D93: COMPANHIA DE ELETRICIDADE DO ESTADO DA BAHIA COELBA | E93: Regular | F93: Azul | G93: A2 | H93: Industrial | I93: Não se aplica | J93: Fonte incentivada | K93: 0 | M93: Não se aplica | N93: Não se aplica | O93: LIVRE | P93: Número de Consumidores | Q93: 2024-01-01T00:00:00.000 | R93: 7
A94: 2026-09-15T00:00:00.000 | B94: 15139629000194 | C94: COELBA | D94: COMPANHIA DE ELETRICIDADE DO ESTADO DA BAHIA COELBA | E94: Regular | F94: Geração | G94: A3 | H94: Não se aplica | I94: Não se aplica | J94: Não se aplica | K94: 33473 | L94: 0.0 | M94: Sertão Solar Barreiras IV | N94: Não se aplica | O94: GERAÇÃO | P94: Demanda Faturada (kW) | Q94: 2024-01-01T00:00:00.000 | R94: 23056
A95: 2026-09-15T00:00:00.000 | B95: 15139629000194 | C95: COELBA | D95: COMPANHIA DE ELETRICIDADE DO ESTADO DA BAHIA COELBA | E95: Regular | F95: Azul | G95: A3 | H95: Industrial | I95: Não se aplica | J95: Não se aplica | K95: 0 | L95: 37121669900.0 | M95: Não se aplica | N95: Não se aplica | O95: CATIVO | P95: Número de consumidores | Q95: 2024-01-01T00:00:00.000 | R95: 10
A96: 2026-09-15T00:00:00.000 | B96: 15139629000194 | C96: COELBA | D96: COMPANHIA DE ELETRICIDADE DO ESTADO DA BAHIA COELBA | E96: Sistema de Compensação GD I | F96: Verde | G96: A4 | H96: Comercial | I96: Não se aplica | J96: Não se aplica | K96: 0 | L96: 37121669900.0 | M96: Não se aplica | N96: Ponta | O96: CATIVO | P96: Energia TE (kWh) | Q96: 2024-01-01T00:00:00.000 | R96: 419721
A97: 2026-09-15T00:00:00.000 | B97: 15139629000194 | C97: COELBA | D97: COMPANHIA DE ELETRICIDADE DO ESTADO DA BAHIA COELBA | E97: Regular | F97: Azul | G97: A2 | H97: Industrial | I97: Não se aplica | J97: Fonte incentivada | K97: 0 | M97: Não se aplica | N97: Fora ponta | O97: LIVRE | P97: Demanda Faturada (kW) | Q97: 2024-01-01T00:00:00.000 | R97: 69047
A98: 2026-09-15T00:00:00.000 | B98: 15139629000194 | C98: COELBA | D98: COMPANHIA DE ELETRICIDADE DO ESTADO DA BAHIA COELBA | E98: Regular | F98: Geração | G98: A3 | H98: Não se aplica | I98: Não se aplica | J98: Não se aplica | K98: 33473 | L98: 0.0 | M98: Sertão Solar Barreiras IV | N98: Não se aplica | O98: GERAÇÃO | P98: Desconto Demanda % | Q98: 2024-01-01T00:00:00.000 | R98: 50
A99: 2026-09-15T00:00:00.000 | B99: 15139629000194 | C99: COELBA | D99: COMPANHIA DE ELETRICIDADE DO ESTADO DA BAHIA COELBA | E99: Regular | F99: Azul | G99: A3 | H99: Industrial | I99: Não se aplica | J99: Não se aplica | K99: 0 | L99: 37121669900.0 | M99: Não se aplica | N99: Fora ponta | O99: CATIVO | P99: Demanda Faturada (kW) | Q99: 2024-01-01T00:00:00.000 | R99: 24265
A100: 2026-09-15T00:00:00.000 | B100: 15139629000194 | C100: COELBA | D100: COMPANHIA DE ELETRICIDADE DO ESTADO DA BAHIA COELBA | E100: Refaturamento - Regular | F100: Branca | G100: B3 | H100: Comercial | I100: Não se aplica | J100: Não se aplica | K100: 0 | L100: 37121669900.0 | M100: Não se aplica | N100: Ponta | O100: CATIVO | P100: Energia TE (kWh) | Q100: 2024-01-01T00:00:00.000 | R100: -239
A101: 2026-09-15T00:00:00.000 | B101: 15139629000194 | C101: COELBA | D101: COMPANHIA DE ELETRICIDADE DO ESTADO DA BAHIA COELBA | E101: Regular | F101: Azul | G101: A2 | H101: Industrial | I101: Não se aplica | J101: Fonte incentivada | K101: 0 | M101: Não se aplica | N101: Ponta | O101: LIVRE | P101: Receita Demanda (R$) | Q101: 2024-01-01T00:00:00.000 | R101: 984749.13
A102: 2026-09-15T00:00:00.000 | B102: 15139629000194 | C102: COELBA | D102: COMPANHIA DE ELETRICIDADE DO ESTADO DA BAHIA COELBA | E102: Regular | F102: Geração | G102: A3 | H102: Não se aplica | I102: Não se aplica | J102: Não se aplica | K102: 33473 | L102: 0.0 | M102: Sertão Solar Barreiras IV | N102: Não se aplica | O102: GERAÇÃO | P102: Demanda Contratada kW | Q102: 2024-01-01T00:00:00.000 | R102: 23050
A103: 2026-09-15T00:00:00.000 | B103: 15139629000194 | C103: COELBA | D103: COMPANHIA DE ELETRICIDADE DO ESTADO DA BAHIA COELBA | E103: Regular | F103: Azul | G103: A3 | H103: Industrial | I103: Não se aplica | J103: Não se aplica | K103: 0 | L103: 37121669900.0 | M103: Não se aplica | N103: Ponta | O103: CATIVO | P103: Receita Demanda (R$) | Q103: 2024-01-01T00:00:00.000 | R103: 667822.15
A104: 2026-09-15T00:00:00.000 | B104: 15139629000194 | C104: COELBA | D104: COMPANHIA DE ELETRICIDADE DO ESTADO DA BAHIA COELBA | E104: Refaturamento - Regular | F104: Branca | G104: B3 | H104: Comercial | I104: Não se aplica | J104: Não se aplica | K104: 0 | L104: 37121669900.0 | M104: Não se aplica | N104: Não se aplica | O104: CATIVO | P104: Número de consumidores | Q104: 2024-01-01T00:00:00.000 | R104: 1
A105: 2026-09-15T00:00:00.000 | B105: 15139629000194 | C105: COELBA | D105: COMPANHIA DE ELETRICIDADE DO ESTADO DA BAHIA COELBA | E105: Regular | F105: Azul | G105: A2 | H105: Industrial | I105: Não se aplica | J105: Fonte incentivada | K105: 0 | M105: Não se aplica | N105: Não se aplica | O105: LIVRE | P105: PIS/COFINS (R$) | Q105: 2024-01-01T00:00:00.000 | R105: 117811.57
A106: 2026-09-15T00:00:00.000 | B106: 15139629000194 | C106: COELBA | D106: COMPANHIA DE ELETRICIDADE DO ESTADO DA BAHIA COELBA | E106: Regular | F106: Geração | G106: A3 | H106: Não se aplica | I106: Não se aplica | J106: Não se aplica | K106: 33473 | L106: 0.0 | M106: Sertão Solar Barreiras IV | N106: Não se aplica | O106: GERAÇÃO | P106: PIS/COFINS (R$) | Q106: 2024-01-01T00:00:00.000 | R106: 6190.57
A107: 2026-09-15T00:00:00.000 | B107: 15139629000194 | C107: COELBA | D107: COMPANHIA DE ELETRICIDADE DO ESTADO DA BAHIA COELBA | E107: Regular | F107: Azul | G107: A3 | H107: Industrial | I107: Não se aplica | J107: Não se aplica | K107: 0 | L107: 37121669900.0 | M107: Não se aplica | N107: Ponta | O107: CATIVO | P107: Energia TE (kWh) | Q107: 2024-01-01T00:00:00.000 | R107: 834606
A108: 2026-09-15T00:00:00.000 | B108: 15139629000194 | C108: COELBA | D108: COMPANHIA DE ELETRICIDADE DO ESTADO DA BAHIA COELBA | E108: Refaturamento - Regular | F108: Branca | G108: B3 | H108: Comercial | I108: Não se aplica | J108: Não se aplica | K108: 0 | L108: 37121669900.0 | M108: Não se aplica | N108: Não se aplica | O108: CATIVO | P108: ICMS (R$) | Q108: 2024-01-01T00:00:00.000 | R108: -1233.84
A109: 2026-09-15T00:00:00.000 | B109: 15139629000194 | C109: COELBA | D109: COMPANHIA DE ELETRICIDADE DO ESTADO DA BAHIA COELBA | E109: Regular | F109: Azul | G109: A2 | H109: Industrial | I109: Não se aplica | J109: Fonte incentivada | K109: 0 | M109: Não se aplica | N109: Não se aplica | O109: LIVRE | P109: Energia TUSD (kWh) | Q109: 2024-01-01T00:00:00.000 | R109: 12571430
A110: 2026-09-15T00:00:00.000 | B110: 15139629000194 | C110: COELBA | D110: COMPANHIA DE ELETRICIDADE DO ESTADO DA BAHIA COELBA | E110: Regular | F110: Geração | G110: A3a | H110: Não se aplica | I110: Não se aplica | J110: Não se aplica | K110: 35446 | L110: 0.0 | M110: Sirivera | N110: Não se aplica | O110: GERAÇÃO | P110: PIS/COFINS (R$) | Q110: 2024-01-01T00:00:00.000 | R110: 924.53
A111: 2026-09-15T00:00:00.000 | B111: 15139629000194 | C111: COELBA | D111: COMPANHIA DE ELETRICIDADE DO ESTADO DA BAHIA COELBA | E111: Sistema de Compensação GD I | F111: Convencional | G111: B3 | H111: Industrial | I111: Não se aplica | J111: Não se aplica | K111: 0 | L111: 37121669900.0 | M111: Não se aplica | N111: Não se aplica | O111: CATIVO | P111: Energia TE (kWh) | Q111: 2024-01-01T00:00:00.000 | R111: 845492
A112: 2026-09-15T00:00:00.000 | B112: 15139629000194 | C112: COELBA | D112: COMPANHIA DE ELETRICIDADE DO ESTADO DA BAHIA COELBA | E112: Refaturamento - Regular | F112: Branca | G112: B3 | H112: Comercial | I112: Não se aplica | J112: Não se aplica | K112: 0 | L112: 37121669900.0 | M112: Não se aplica | N112: Intermediário | O112: CATIVO | P112: Receita Energia (R$) | Q112: 2024-01-01T00:00:00.000 | R112: -547.33
A113: 2026-09-15T00:00:00.000 | B113: 15139629000194 | C113: COELBA | D113: COMPANHIA DE ELETRICIDADE DO ESTADO DA BAHIA COELBA | E113: Regular | F113: Azul | G113: A3 | H113: Industrial | I113: Não se aplica | J113: Não se aplica | K113: 0 | M113: Não se aplica | N113: Não se aplica | O113: LIVRE | P113: Receita Energia (R$) | Q113: 2024-01-01T00:00:00.000 | R113: 681864.16
A114: 2026-09-15T00:00:00.000 | B114: 15139629000194 | C114: COELBA | D114: COMPANHIA DE ELETRICIDADE DO ESTADO DA BAHIA COELBA | E114: Regular | F114: Geração | G114: A3a | H114: Não se aplica | I114: Não se aplica | J114: Não se aplica | K114: 35446 | L114: 0.0 | M114: Sirivera | N114: Não se aplica | O114: GERAÇÃO | P114: Receita Demanda (R$) | Q114: 2024-01-01T00:00:00.000 | R114: 16821
A115: 2026-09-15T00:00:00.000 | B115: 15139629000194 | C115: COELBA | D115: COMPANHIA DE ELETRICIDADE DO ESTADO DA BAHIA COELBA | E115: Sistema de Compensação GD I | F115: Verde | G115: A3a | H115: Comercial | I115: Não se aplica | J115: Não se aplica | K115: 0 | L115: 37121669900.0 | M115: Não se aplica | N115: Não se aplica | O115: CATIVO | P115: Receita Demanda (R$) | Q115: 2024-01-01T00:00:00.000 | R115: 663312
A116: 2026-09-15T00:00:00.000 | B116: 15139629000194 | C116: COELBA | D116: COMPANHIA DE ELETRICIDADE DO ESTADO DA BAHIA COELBA | E116: Regular | F116: Convencional | G116: B2 | H116: Rural | I116: Não se aplica | J116: Não se aplica | K116: 0 | L116: 37121669900.0 | M116: Não se aplica | N116: Não se aplica | O116: CATIVO | P116: Energia TE (kWh) | Q116: 2024-01-01T00:00:00.000 | R116: 31063470
A117: 2026-09-15T00:00:00.000 | B117: 15139629000194 | C117: COELBA | D117: COMPANHIA DE ELETRICIDADE DO ESTADO DA BAHIA COELBA | E117: Regular | F117: Azul | G117: A3 | H117: Industrial | I117: Não se aplica | J117: Não se aplica | K117: 0 | M117: Não se aplica | N117: Não se aplica | O117: LIVRE | P117: PIS/COFINS (R$) | Q117: 2024-01-01T00:00:00.000 | R117: 183572.87
A118: 2026-09-15T00:00:00.000 | B118: 15139629000194 | C118: COELBA | D118: COMPANHIA DE ELETRICIDADE DO ESTADO DA BAHIA COELBA | E118: Regular | F118: Geração | G118: A3a | H118: Não se aplica | I118: Não se aplica | J118: Não se aplica | K118: 35446 | L118: 0.0 | M118: Sirivera | N118: Não se aplica | O118: GERAÇÃO | P118: Desconto Demanda % | Q118: 2024-01-01T00:00:00.000 | R118: 50
A119: 2026-09-15T00:00:00.000 | B119: 15139629000194 | C119: COELBA | D119: COMPANHIA DE ELETRICIDADE DO ESTADO DA BAHIA COELBA | E119: Regular | F119: Verde | G119: A3a | H119: Comercial | I119: Não se aplica | J119: Não se aplica | K119: 0 | L119: 37121669900.0 | M119: Não se aplica | N119: Não se aplica | O119: CATIVO | P119: Receita Demanda (R$) | Q119: 2024-01-01T00:00:00.000 | R119: 508447.91
A120: 2026-09-15T00:00:00.000 | B120: 15139629000194 | C120: COELBA | D120: COMPANHIA DE ELETRICIDADE DO ESTADO DA BAHIA COELBA | E120: Sistema de Compensação GD I | F120: Convencional | G120: B2 | H120: Rural | I120: Não se aplica | J120: Não se aplica | K120: 0 | L120: 37121669900.0 | M120: Não se aplica | N120: Não se aplica | O120: CATIVO | P120: Número de consumidores | Q120: 2024-01-01T00:00:00.000 | R120: 8910
A121: 2026-09-15T00:00:00.000 | B121: 15139629000194 | C121: COELBA | D121: COMPANHIA DE ELETRICIDADE DO ESTADO DA BAHIA COELBA | E121: Regular | F121: Azul | G121: A3 | H121: Comercial | I121: Não se aplica | J121: Não se aplica | K121: 0 | M121: Não se aplica | N121: Não se aplica | O121: LIVRE | P121: ICMS (R$) | Q121: 2024-01-01T00:00:00.000 | R121: 58338.33
